Workbook

Sheet Cover
A1: Moderna, Inc. (MRNA) - Intrinsic Value Model
A2: Valuation date 2026-09-30 | Prices as of 2026-09-25/28 | USD billions unless stated | Analysis, not investment advice
A4: Market price ($) | C4: =Drivers!$C$5 -> 199
A5: Probability-weighted DCF ($/share) | C5: =Summary!C10 -> 28.765561
A6: Blended intrinsic value ($/share) | C6: =Summary!F19 -> 33.087699
A7: Base scenario ($/share) | C7: =Summary!C7 -> 26.47574
A8: Bull scenario ($/share) | C8: =Summary!C8 -> 72.179586
A9: Blue-sky ceiling ($/share) | C9: =Summary!C9 -> 272.72192
A10: Monte Carlo P10 / P50 / P90 | C10: =TEXT(6.90160125596957,"$0")&" / "&TEXT(28.557500697222,"$0")&" / "&TEXT(63.6353294338,"$0") -> $7 / $29 / $64
A11: WACC (build-up) | C11: =Drivers!$C$30 -> 0.1043
A14: Legend: blue = hard-coded input (edit on Drivers); black = formula; green = link to another sheet; yellow fill = key assumption.
A15: How to use: change any blue cell on Drivers (e.g. INT melanoma peak, PoS, price factor, WACC) and every scenario, the SOTP and the Summary recalculate.
A16: M_* sheets are identical formula grids; only cell C2 (scenario index) differs. Monte Carlo, tornado, comps and guidance tabs are pasted engine outputs.
A17: Engine: scripts/valuation_engine.py reads data/assumptions.json; scripts/audit_model.py recalculates this workbook in LibreOffice and checks it matches the engine.

Sheet Summary
A1: Moderna (MRNA) - Probability-weighted intrinsic value
A2: Analysis, not investment advice. Values in $/share unless stated. Valuation date 2026-09-30.
A4: Scenario | B4: Probability | C4: Value/share | D4: EV ($B) | E4: Equity ($B) | F4: TV share of EV | G4: vs price
A5: Failure | B5: =Drivers!D56 -> 0.1 | C5: =M_Failure!$C$109 -> 6.9016013 | D5: =M_Failure!$C$103 -> -7.8042261 | E5: =M_Failure!$C$107 -> -5.1164168 | F5: =M_Failure!$C$104 -> 0 | G5: =C5/Drivers!$C$5-1 -> -0.96531859
A6: Bear | B6: =Drivers!E56 -> 0.25 | C6: =M_Bear!$C$109 -> 6.9016013 | D6: =M_Bear!$C$103 -> -4.0242469 | E6: =M_Bear!$C$107 -> -1.1364375 | F6: =M_Bear!$C$104 -> 0 | G6: =C6/Drivers!$C$5-1 -> -0.96531859
A7: Base | B7: =Drivers!F56 -> 0.45 | C7: =M_Base!$C$109 -> 26.47574 | D7: =M_Base!$C$103 -> 7.7281382 | E7: =M_Base!$C$107 -> 10.915948 | F7: =M_Base!$C$104 -> 0.18776475 | G7: =C7/Drivers!$C$5-1 -> -0.86695608
A8: Bull | B8: =Drivers!G56 -> 0.2 | C8: =M_Bull!$C$109 -> 72.179586 | D8: =M_Bull!$C$103 -> 27.305042 | E8: =M_Bull!$C$107 -> 30.692851 | F8: =M_Bull!$C$104 -> 0.19205377 | G8: =C8/Drivers!$C$5-1 -> -0.63728851
A9: Blue-sky (ceiling, unweighted) | B9: =Drivers!H56 -> 0 | C9: =M_BlueSky!$C$109 -> 272.72192 | D9: =M_BlueSky!$C$103 -> 115.82159 | E9: =M_BlueSky!$C$107 -> 119.19218 | F9: =M_BlueSky!$C$104 -> 0.41451048 | G9: =C9/Drivers!$C$5-1 -> 0.37046193
A10: Probability-weighted DCF value | C10: =SUMPRODUCT(B5:B8,C5:C8) -> 28.765561
A12: Method | B12: Low | C12: Mid | D12: High | E12: Weight | F12: Weighted | G12: Rationale
A13: Scenario rNPV/FCFF DCF (prob.-weighted) | B13: =C6 -> 6.9016013 | C13: =C10 -> 28.765561 | D13: =C8 -> 72.179586 | E13: 0.45 | F13: =C13*E13 -> 12.944502 | G13: Primary; asset-level risk explicit
A14: Monte Carlo (engine output, 20k draws) | B14: 6.9016013 | C14: 32.978244 | D14: 63.635329 | E14: 0.25 | F14: =C14*E14 -> 8.244561 | G14: P10 / mean / P90 from valuation_engine.py
A15: Forward peer multiple (EV/Sales 2030E) | B15: =$J$50 -> 22.034724 | C15: =$J$52 -> 30.409481 | D15: =$J$54 -> 38.784238 | E15: 0.15 | F15: =C15*E15 -> 4.5614221 | G15: Regression on 13 commercial peers
A16: Transaction reference (EV/risk-adj. peak) | B16: =$J$58 -> 51.963482 | C16: =($J$58+$J$59)/2 -> 68.807964 | D16: =$J$59 -> 85.652447 | E16: 0.1 | F16: =C16*E16 -> 6.8807964 | G16: Control value; includes acquirer synergies
A17: Earnings power value (no growth) | B17: =$J$64 -> 11.355086 | C17: =$J$64 -> 11.355086 | D17: =$J$64 -> 11.355086 | E17: 0.025 | F17: =C17*E17 -> 0.28387715 | G17: What exists today
A18: Asset / liquidation floor | B18: =Drivers!$C$141 -> 6.9016013 | C18: =Drivers!$C$141 -> 6.9016013 | D18: =Drivers!$C$141 -> 6.9016013 | E18: 0.025 | F18: =C18*E18 -> 0.17254003 | G18: Downside floor
A19: Blended intrinsic value (credibility-weighted) | E19: =SUM(E13:E18) -> 1 | F19: =SUM(F13:F18) -> 33.087699
A20: Market price | F20: =Drivers!$C$5 -> 199
A21: Blended value vs price | F21: =F19/Drivers!$C$5-1 -> -0.83373016
A23: Monte Carlo distribution (engine output)
A24: Statistic | B24: $/share
A25: P5 | B25: 6.9016013
A26: P10 | B26: 6.9016013
A27: P25 | B27: 14.115153
A28: P50 | B28: 28.557501
A29: P75 | B29: 45.325864
A30: P90 | B30: 63.635329
A31: P95 | B31: 77.309893
A32: P99 | B32: 108.53126
A33: mean | B33: 32.978244
A34: P(value > market price) | B34: 0.00025
A36: Reverse DCF (engine output)
A37: Implied INT risk-adj. peak sales ($B), all else base | B37: 81.406429
A38: Required unadjusted INT peak if every indication succeeds, base terms ($B) | B38: 93.466816
A39: ...and with bull price/margin/respiratory ($B) | B39: 51.209472 | I39: Auxiliary calculations
A40: Base-case unadjusted INT peak (10 indications, $B) | B40: 22 | I40: Regression const (ln EV/S) | J40: 1.3889575
A41: Implied WACC on base cash flows | B41: 0.019777133 | I41: Regression coef: 3y revenue CAGR | J41: 1.174444
A42: Implied probability of Blue-sky vs Bull | B42: 0.63238723 | I42: Regression coef: operating margin | J42: 0.23300818
I43: Base attributable revenue 2030 | J43: =M_Base!F81 -> 4.2898
I44: 3y CAGR 2027-30 | J44: =(M_Base!F81/M_Base!C81)^(1/3)-1 -> 0.19051078
I45: EBIT margin 2030 | J45: =M_Base!F85/M_Base!F81 -> -0.093473051
I46: Fitted EV/Sales | J46: =EXP($J$40+$J$41*MIN($J$44,1)+$J$42*MAX($J$45,-1)) -> 4.9082713
I47: PV of FCFF Q4-26..2030 | J47: =M_Base!$C$97+SUMPRODUCT(M_Base!C90:F90,M_Base!C92:F92) -> -4.4616299
I48: Base WACC | J48: =M_Base!$C$19 -> 0.1043
I49: Equity @ 0.75x fitted multiple | J49: =0.75*$J$46*$J$43*(1+$J$48)^(-4.25)+$J$47+Drivers!$C$6-M_Base!$C$106 -> 9.0849166
I50: Per share @ 0.75x | J50: =IF(($J$49)*1000/(Drivers!$C$19+Drivers!$C$22)<=Drivers!$C$21,($J$49)*1000/(Drivers!$C$19+Drivers!$C$22),IF((($J$49)*1000+Drivers!$C$20*Drivers!$C$21)/(Drivers!$C$19+Drivers!$C$22+Drivers!$C$20)<=Drivers!$C$10,(($J$49)*1000+Drivers!$C$20*Drivers!$C$21)/(Drivers!$C$19+Drivers!$C$22+Drivers!$C$20),(($J$49)*1000+Drivers!$C$20*Drivers!$C$21+Drivers!$C$11*Drivers!$C$10)/(Drivers!$C$19+Drivers!$C$22+Drivers!$C$20+Drivers!$C$11))) -> 22.034724
I51: Equity @ 1.0x fitted multiple | J51: =1*$J$46*$J$43*(1+$J$48)^(-4.25)+$J$47+Drivers!$C$6-M_Base!$C$106 -> 12.537829
I52: Per share @ 1.0x | J52: =IF(($J$51)*1000/(Drivers!$C$19+Drivers!$C$22)<=Drivers!$C$21,($J$51)*1000/(Drivers!$C$19+Drivers!$C$22),IF((($J$51)*1000+Drivers!$C$20*Drivers!$C$21)/(Drivers!$C$19+Drivers!$C$22+Drivers!$C$20)<=Drivers!$C$10,(($J$51)*1000+Drivers!$C$20*Drivers!$C$21)/(Drivers!$C$19+Drivers!$C$22+Drivers!$C$20),(($J$51)*1000+Drivers!$C$20*Drivers!$C$21+Drivers!$C$11*Drivers!$C$10)/(Drivers!$C$19+Drivers!$C$22+Drivers!$C$20+Drivers!$C$11))) -> 30.409481
I53: Equity @ 1.25x fitted multiple | J53: =1.25*$J$46*$J$43*(1+$J$48)^(-4.25)+$J$47+Drivers!$C$6-M_Base!$C$106 -> 15.990741
I54: Per share @ 1.25x | J54: =IF(($J$53)*1000/(Drivers!$C$19+Drivers!$C$22)<=Drivers!$C$21,($J$53)*1000/(Drivers!$C$19+Drivers!$C$22),IF((($J$53)*1000+Drivers!$C$20*Drivers!$C$21)/(Drivers!$C$19+Drivers!$C$22+Drivers!$C$20)<=Drivers!$C$10,(($J$53)*1000+Drivers!$C$20*Drivers!$C$21)/(Drivers!$C$19+Drivers!$C$22+Drivers!$C$20),(($J$53)*1000+Drivers!$C$20*Drivers!$C$21+Drivers!$C$11*Drivers!$C$10)/(Drivers!$C$19+Drivers!$C$22+Drivers!$C$20+Drivers!$C$11))) -> 38.784238
I55: Base max attributable revenue (risk-adj. peak) | J55: =MAX(M_Base!C81:U81) -> 7.4334701
I56: EV / risk-adj. peak sales - low | J56: 2.5
I57: EV / risk-adj. peak sales - high | J57: 4.5
I58: Transaction value/share - low | J58: =IF(($J$56*$J$55+Drivers!$C$6-M_Base!$C$106)*1000/(Drivers!$C$19+Drivers!$C$22)<=Drivers!$C$21,($J$56*$J$55+Drivers!$C$6-M_Base!$C$106)*1000/(Drivers!$C$19+Drivers!$C$22),IF((($J$56*$J$55+Drivers!$C$6-M_Base!$C$106)*1000+Drivers!$C$20*Drivers!$C$21)/(Drivers!$C$19+Drivers!$C$22+Drivers!$C$20)<=Drivers!$C$10,(($J$56*$J$55+Drivers!$C$6-M_Base!$C$106)*1000+Drivers!$C$20*Drivers!$C$21)/(Drivers!$C$19+Drivers!$C$22+Drivers!$C$20),(($J$56*$J$55+Drivers!$C$6-M_Base!$C$106)*1000+Drivers!$C$20*Drivers!$C$21+Drivers!$C$11*Drivers!$C$10)/(Drivers!$C$19+Drivers!$C$22+Drivers!$C$20+Drivers!$C$11))) -> 51.963482
I59: Transaction value/share - high | J59: =IF(($J$57*$J$55+Drivers!$C$6-M_Base!$C$106)*1000/(Drivers!$C$19+Drivers!$C$22)<=Drivers!$C$21,($J$57*$J$55+Drivers!$C$6-M_Base!$C$106)*1000/(Drivers!$C$19+Drivers!$C$22),IF((($J$57*$J$55+Drivers!$C$6-M_Base!$C$106)*1000+Drivers!$C$20*Drivers!$C$21)/(Drivers!$C$19+Drivers!$C$22+Drivers!$C$20)<=Drivers!$C$10,(($J$57*$J$55+Drivers!$C$6-M_Base!$C$106)*1000+Drivers!$C$20*Drivers!$C$21)/(Drivers!$C$19+Drivers!$C$22+Drivers!$C$20),(($J$57*$J$55+Drivers!$C$6-M_Base!$C$106)*1000+Drivers!$C$20*Drivers!$C$21+Drivers!$C$11*Drivers!$C$10)/(Drivers!$C$19+Drivers!$C$22+Drivers!$C$20+Drivers!$C$11))) -> 85.652447
I60: EPV: steady gross margin (no flu/combo scale) | J60: =Drivers!$I$75-0.03 -> 0.72
I61: EPV: EBIT on $2.04B revenue | J61: =Drivers!$C$35*$J$60-MAX(Drivers!$C$80,Drivers!$C$79*Drivers!$C$35)-Drivers!$C$129-0.45 -> 0.1988
I62: EPV: NOPAT | J62: =IF($J$61>0,$J$61*(1-Drivers!$C$31),$J$61) -> 0.161028
I63: EPV: equity | J63: =$J$62/$J$48+Drivers!$C$6-Drivers!$C$7-Drivers!$C$8-Drivers!$C$12-Drivers!$C$13*(Drivers!$C$14+Drivers!$C$15*Drivers!$C$16)/(1+$J$48)-Drivers!$F$55 -> 4.681702
I64: EPV per share | J64: =IF(($J$63)*1000/(Drivers!$C$19+Drivers!$C$22)<=Drivers!$C$21,($J$63)*1000/(Drivers!$C$19+Drivers!$C$22),IF((($J$63)*1000+Drivers!$C$20*Drivers!$C$21)/(Drivers!$C$19+Drivers!$C$22+Drivers!$C$20)<=Drivers!$C$10,(($J$63)*1000+Drivers!$C$20*Drivers!$C$21)/(Drivers!$C$19+Drivers!$C$22+Drivers!$C$20),(($J$63)*1000+Drivers!$C$20*Drivers!$C$21+Drivers!$C$11*Drivers!$C$10)/(Drivers!$C$19+Drivers!$C$22+Drivers!$C$20+Drivers!$C$11))) -> 11.355086

Sheet Drivers
A1: DRIVERS - every model input (blue = hard-coded input; edit here). Units: USD billions unless stated.
A4: 1. Market & capital structure (valuation date 2026-09-30)
B5: Market price ($/share) | C5: 199 | D5: Nasdaq close 2026-09-25 $198.88; intraday 2026-09-28 ~$198-199 (data/mrna_price_daily.csv, data/peer_quotes_2026-09-28.json)
B6: Cash & investments, est. 9/30/26 | C6: 8.04 | D6: Jun-30-26 $6.910B (10-Q) - $0.950B Arbutus payment (Jul-26) + $2.628B convert net of capped call (8-K 2026-09-01: 2.9573-0.3288) - ~$0.55B est. Q3 operating burn (implied by YE-26 guide $4.7-5.2B ex-convert, 8-K 2026-07-31). Q3-26 10-Q not yet filed: ESTIMATE
B7: Ares term loan | C7: 0.6 | D7: Ares senior secured, SOFR+5.50% (~9.2%), matures 2030-11-24 (10-Q Q2-26 note 11)
B8: Convertible notes 2032 (face) | C8: 3 | D8: 0.00% notes due 2032-03-01, capped call to $392.62 (8-K 2026-09-01). Treated as debt at face; net share dilution only above the cap.
B9: Conversion price ($) | C9: 210.58
B10: Capped-call cap ($) | C10: 392.62
B11: Convert shares (m) | C11: 14.2461
B12: Finance leases | C12: 0.037
B13: Arbutus contingent payment | C13: 1.3 | D13: Settlement 8-K 2026-03-05: $1.3B due if Federal Circuit affirms rejection of s.1498 defence; pro-rated if partial. Probabilities JUDGMENT (Fed. Cir. affirmance base rate ~70%).
B14: P(pay in full) | C14: 0.6
B15: P(partial) | C15: 0.1
B16: Partial fraction | C16: 0.5
B17: Years to payment | C17: 1
B18: Pfizer/BioNTech litigation option | C18: 0.05 | D18: EP'949 revoked by EPO Board of Appeal Sep-2026 (JUVE Patent), nullifying UK/Dusseldorf wins; US patents invalidated at PTAB (on appeal). Residual option value JUDGMENT.
B19: Basic shares (m) | C19: 399.3 | D19: Nasdaq market cap $79.57B / $199.285 = 399.3M (2026-09-28); 10-Q Q2-26 weighted basic 398M
B20: Options (m) | C20: 29 | D20: 10-K 2025: 27.18M options @ $38.63 WAEP, 11.20M RSU/PSU; 10-Q Q2-26: 42M anti-dilutive equivalents. 2026 split ESTIMATED.
B21: Options WAEP ($) | C21: 40
B22: RSU/PSU (m) | C22: 13
A24: 2. Discount rate & tax
B25: Risk-free (10y UST) | C25: 0.0517 | D25: 10-yr UST 2026-09-25 (home.treasury.gov, data/ust_yields_2026.csv)
B26: Equity risk premium | C26: 0.045 | D26: JUDGMENT; implied US ERP range 4-5.5%
B27: Beta | C27: 1.2 | D27: Weekly vs SPY, 3y ex Aug-19-2026 jump = 1.32, 5y = 1.17; Blume-adjusted 1.11-1.22 (data/beta_estimates.json)
B28: Pre-tax cost of debt | C28: 0.075
B29: Debt weight | C29: 0.045
B30: WACC (build-up; used by Base) | C30: =ROUND((1-Drivers!$C$29)*(Drivers!$C$25+Drivers!$C$27*Drivers!$C$26)+Drivers!$C$29*Drivers!$C$28,4) -> 0.1043 | D30: (1-4.5pct) x CoE [5.17 + 1.20 x 4.5 = 10.57pct] + 4.5pct x 7.5pct pre-tax (NOLs remove the debt tax shield) = 10.43pct
B31: Cash tax rate | C31: 0.19 | D31: 21% federal + state, less FDII/credits; JUDGMENT
B32: NOL / deduction pool at 9/30/26 | C32: 12.5 | D32: Federal NOL $4.1B (10-K 2025 note 14, non-expiring) + 2026 tax loss ~$2.9B + ~$5.5B of unamortized capitalised R&E deductible after the 2025 tax act (DTA $1.693B / ~23%, domestic portion) -> ~$12.5B. ESTIMATE.
B33: NOL usage limit (% of taxable income) | C33: 0.8
B34: Q4-2026 stub FCF | C34: -0.46 | D34: Q4-26 operating cash burn implied by YE-26 cash guide midpoint $4.95B (8-K 2026-07-31) after est. Q3 burn
B35: 2026 revenue base (for working capital) | C35: 2.04 | D35: Guidance-tracker base case (data/guidance_forward_adjusted.csv)
A37: 3. Scenario levers (columns D..H = Failure, Bear, Base, Bull, Blue-sky; Blue-sky is a ceiling test, not weighted)
B38: Lever | D38: Failure | E38: Bear | F38: Base | G38: Bull | H38: Blue-sky | I38: Note
B39: COVID revenue multiplier | D39: 0.75 | E39: 0.85 | F39: 1 | G39: 1.1 | H39: 1.1
B40: Flu (mFLUSIVA) peak multiplier | D40: 0.5 | E40: 0.6 | F40: 1 | G40: 1.6 | H40: 1.6
B41: Flu+COVID combo peak multiplier | D41: 0.5 | E41: 0.6 | F41: 1 | G41: 1.6 | H41: 1.6
B42: Norovirus PoS | D42: 0.15 | E42: 0.2 | F42: 0.3 | G42: 0.45 | H42: 1
B43: Respiratory gross-margin shift | D43: -0.04 | E43: -0.02 | F43: 0 | G43: 0.02 | H43: 0.03
B44: INT melanoma PoS | D44: 0 | E44: 0.85 | F44: 0.88 | G44: 0.93 | H44: 1
B45: INT melanoma peak global sales ($B, before price factor) | D45: 2.8 | E45: 1.5 | F45: 2.8 | G45: 5 | H45: 6
B46: INT melanoma launch year | D46: 2027 | E46: 2028 | F46: 2027 | G46: 2027 | H46: 2027
B47: INT other-indication PoS multiplier (>=10 => all 100%) | D47: 0.4 | E47: 0.7 | F47: 1 | G47: 1.33 | H47: 10
B48: INT other-indication peak multiplier | D48: 0.8 | E48: 0.8 | F48: 1 | G48: 1.2 | H48: 1.5
B49: INT price factor (1.0 = US net ~$300k) | D49: 0.8 | E49: 0.75 | F49: 1 | G49: 1.4 | H49: 1.58
B50: INT mature profit-pool margin | D50: 0.55 | E50: 0.55 | F50: 0.55 | G50: 0.55 | H50: 0.62
... B52: Future-pipeline credit factor | D52: 0.25 | E52: 0.5 | F52: 0.75 | G52: 1 | H52: 1
B53: WACC | D53: =Drivers!$C$30 -> 0.1043 | E53: =Drivers!$C$30 -> 0.1043 | F53: =Drivers!$C$30 -> 0.1043 | G53: =Drivers!$C$30 -> 0.1043 | H53: 0.08
B54: Terminal growth | D54: -0.01 | E54: -0.01 | F54: 0 | G54: 0.01 | H54: 0.02
B55: Other patent litigation (expected cost) | D55: 1 | E55: 0.8 | F55: 0.5 | G55: 0.3 | H55: 0.3
B56: Scenario probability | D56: 0.1 | E56: 0.25 | F56: 0.45 | G56: 0.2 | H56: 0 | I56: Positive Ph3 oncology BLAs are approved ~85-90% of the time; interim success at a pre-specified IA implies HR well below 0.75 but magnitude undisclosed until ESMO. Launch-vs-consensus base rate: roughly 2/3 of launches under-deliver sell-side peak forecasts. Moderna's own launch record: Spikevax (pandemic) >> guide; mRESVIA << guide; mNEXSPIKE in line. Revenue-guidance confidence 65/100 (1y) falling to 47 (3y). -> downside-skewed weights. JUDGMENT.
B57: Probabilities sum (must be 100%) | C57: =SUM(D56:G56) -> 1
A59: 4. Respiratory franchise (paths are 2027..2032, then rules below)
B60: COVID revenue path 2027-32 | D60: 1.85 | E60: 1.7 | F60: 1.55 | G60: 1.45 | H60: 1.38 | I60: 1.3 | K60: 2025 COVID sales $1.81B (10-K); 2026 guide up to +10% total revenue; 2027 EU tender opening (Analyst Day 2025) offsets US policy headwinds; combo cannibalises from 2028. JUDGMENT anchored on guidance-confidence 65/100.
B61: COVID growth after 2032 | C61: -0.02
B62: Flu peak revenue | C62: 0.8 | D62: mFLUSIVA BLA 125869 approved 2026-08-05 (50+; accelerated for 65+), rVE 26.6% vs standard dose (FDA SBRA). No ACIP preferential rec for 65+ yet. EU/CA/AU under review.
B63: Flu launch year | C63: 2027
B64: Flu ramp years | C64: 5
B65: Combo peak revenue | C65: 1.4 | D65: mCOMBRIAX approved EU Apr-2026; US re-filing awaiting FDA guidance; mgmt targets US 2028 (Analyst Day 2025).
B66: Combo launch year | C66: 2027
B67: Combo ramp years | C67: 5
B68: Combo US approval PoS | C68: 0.7
B69: Combo US share of peak | C69: 0.55
B70: RSV peak revenue | C70: 0.15 | D70: mRESVIA: $8M 2025 sales, $10M 1H-26 (10-K/10-Q); EU joint procurement up to 24M doses (Q2-26 release).
B71: Norovirus peak revenue | C71: 1.2 | D71: mRNA-1403 Ph3 (NCT06592794, ~38k pts) missed early-success criteria at interim Jul-2026; additional cohort. PoS JUDGMENT (industry Ph3 vaccine PoS ~70%, cut for interim miss).
B72: Norovirus launch year | C72: 2029
B73: Norovirus ramp years | C73: 5
B74: Other revenue (stand-ready, grants...) | C74: 0.15 | D74: Stand-ready manufacturing ($80M 2025, $63M 1H-26), grants, collaboration, pandemic contracts
B75: Gross margin path 2027-32 | D75: 0.64 | E75: 0.68 | F75: 0.71 | G75: 0.73 | H75: 0.74 | I75: 0.75 | K75: Product GM ex-settlement 2025 72% on sales but 2026 COGS guide $0.8B ex-settlement (~40% of sales incl. unutilised capacity + write-downs); mgmt: +10pts over 3 yrs (Analyst Day 2025).
B76: Blackstone royalty on flu+combo | C76: 0.025 | D76: Up to $750M funding for flu; low-single-digit royalty + up to $750M sales milestones on flu & combo if US approval relied on funded data (10-Q Q2-26 note 5). mFLUSIVA approval relied on P304 -> triggered.
B77: Blackstone sales milestones cap | C77: 0.75
B78: Milestone accrual rate (% of flu+combo) | C78: 0.08
B79: Respiratory S&M % revenue | C79: 0.14
B80: Respiratory S&M floor | C80: 0.4
B81: Respiratory R&D 2027-32 (then +2%/yr) | D81: 0.75 | E81: 0.62 | F81: 0.55 | G81: 0.5 | H81: 0.48 | I81: 0.46 | K81: Variant updates, PMRs (P910 confirmatory flu study), norovirus Ph3, EBV/CMV/Lyme/H5. JUDGMENT allocation of guided R&D ($2.9B 2026).
B82: Working capital % of revenue change | C82: 0.1
A84: 5. Intismeran (INT) - 50/50 profit share with Merck
B85: Moderna share of profit pool | C85: 0.5 | D85: Costs and profits shared 50/50 worldwide (PCV/INT Agreement; 10-K 2025)
B86: Uptake curve (share of peak, yrs 0..6) | D86: 0.08 | E86: 0.25 | F86: 0.45 | G86: 0.65 | H86: 0.82 | I86: 0.93 | J86: 1
B87: Years before exclusivity erosion | C87: 12
B88: Price/volume step at erosion | C88: 0.8
B89: Annual decay after erosion | C89: 0.97
B90: Profit-pool margin at launch | C90: 0.2 | D90: Profit pool margin before shared R&D: COGS ~30% blended at scale (US $300k vs ~$70k/pt mfg+sequencing), S&M ~12%, G&A ~3%. JUDGMENT.
B91: Years to mature margin | C91: 5
B92: Moderna INT development cost 2027-34 | D92: 0.4 | E92: 0.4 | F92: 0.4 | G92: 0.4 | H92: 0.35 | I92: 0.35 | J92: 0.3 | K92: 0.25 | M92: Moderna net INT expense $97M/qtr (10-Q Q2-26 note 5) -> ~$0.4B/yr
B93: INT development cost after 2034 | C93: 0.2
B94: Indication | C94: Phase | D94: Launch | E94: Peak ($B) | F94: PoS | G94: Source / note
B95: Adjuvant melanoma IIB-IV (INTerpath-001) | C95: Ph3 positive | D95: 2027 | E95: 2.8 | F95: 0.88 | G95: Met RFS & DMFS at interim (8/19/26); ESMO Oct-23-27 2026; BTD & PRIME. US ~14k/yr IIB-IV resected, ~8k on adjuvant PD-1 (ACS/SEER stage mix).
B96: Adjuvant NSCLC II-IIIB (INTerpath-002) | C96: Ph3 | D96: 2031 | E96: 4 | F96: 0.45 | G96: NCT06077760, n=868, primary completion Jun-2030. Goldman: melanoma+lung $10.9B peak.
B97: Post-neoadjuvant non-pCR NSCLC (INTerpath-009) | C97: Ph3 | D97: 2034 | E97: 1.5 | F97: 0.4 | G97: NCT06623422, n=680, PCD May-2033
B98: Resected stage I NSCLC (INTerpath-014) | C98: Ph3 | D98: 2035 | E98: 2.5 | F98: 0.35 | G98: NCT07513376, n=876, PCD Aug-2034
B99: Adjuvant RCC (INTerpath-004) | C99: Ph2 | D99: 2031 | E99: 1.2 | F99: 0.25 | G99: NCT06307431, n=272, PCD Apr-2027
B100: MIBC adjuvant (INTerpath-005) | C100: Ph2 | D100: 2033 | E100: 1 | F100: 0.2 | G100: NCT06305767, n=230, PCD Oct-2029
B101: NMIBC + BCG (INTerpath-011) | C101: Ph2 | D101: 2034 | E101: 1 | F101: 0.15 | G101: NCT06833073, n=308, PCD Sep-2031
B102: 1L advanced melanoma (INTerpath-012) | C102: Ph2 | D102: 2031 | E102: 0.8 | F102: 0.2 | G102: NCT06961006, n=160, PCD Jul-2028
B103: 1L metastatic squamous NSCLC (INTerpath-013) | C103: Ph2 | D103: 2032 | E103: 1.2 | F103: 0.15 | G103: NCT07221474, n=180, PCD Jul-2029
B104: Other solid tumours - future INT indications (pre-Ph2) | C104: Ph1 / not started | D104: 2035 | E104: 6 | F104: 0.1 | G104: Platform read-through: Ph1 in adjuvant PDAC, perioperative gastric & NSCLC (INTerpath backgrounder; NCT03313778); Merck/Moderna 'plans for continued expansion'. PoS JUDGMENT (industry Ph1->approval ~5-10% oncology, raised for validated mechanism).
A106: 6. Other pipeline & corporate
B107: mRNA-4359 PoS | C107: 0.1 | D107: Wholly owned PD-L1/IDO cancer antigen therapy; Ph1b CPI-refractory melanoma ORR 24% (67% if PD-L1>=1%) (10-K 2025). NCT05533697.
B108: mRNA-4359 peak | C108: 2
...

Sheet SOTP
A1: Sum-of-the-parts - Base scenario (pre-tax PV incl. pro-rata terminal value; tax shown separately)
A3: Component | B3: PV ($B) | C3: $ / share (on basic) | D3: Note
A4: Respiratory franchise | B4: =1*(SUMPRODUCT(M_Base!C52:U52,M_Base!C92:U92)+M_Base!$C$100*M_Base!U52/M_Base!U90) -> 13.773608 | C4: =B4*1000/Drivers!$C$19 -> 34.494385 | D4: COVID, flu, combo, RSV, norovirus
A5: Intismeran (50% share, net of dev.) | B5: =1*(SUMPRODUCT(M_Base!C68:U68,M_Base!C92:U92)+M_Base!$C$100*M_Base!U68/M_Base!U90) -> 6.6417922 | C5: =B5*1000/Drivers!$C$19 -> 16.633589 | D5: 10 indications, PoS-weighted
A6: mRNA-4359 | B6: =1*(SUMPRODUCT(M_Base!C72:U72,M_Base!C92:U92)+M_Base!$C$100*M_Base!U72/M_Base!U90) -> -0.19104088 | C6: =B6*1000/Drivers!$C$19 -> -0.47843947 | D6: wholly owned
A7: Rare disease & royalties | B7: =1*(SUMPRODUCT(M_Base!C76:U76,M_Base!C92:U92)+M_Base!$C$100*M_Base!U76/M_Base!U90) -> 0.44361461 | C7: =B7*1000/Drivers!$C$19 -> 1.1109807 | D7: PA (Recordati), MMA, CF
A8: Corporate G&A | B8: =-1*(SUMPRODUCT(M_Base!C78:U78,M_Base!C92:U92)+M_Base!$C$100*M_Base!U78/M_Base!U90) -> -4.8294873 | C8: =B8*1000/Drivers!$C$19 -> -12.094884
A9: Unallocated R&D (platform/shared/SBC) | B9: =-1*(SUMPRODUCT(M_Base!C80:U80,M_Base!C92:U92)+M_Base!$C$100*M_Base!U80/M_Base!U90) -> -11.864245 | C9: =B9*1000/Drivers!$C$19 -> -29.71261 | D9: credited below via future-pipeline line
A10: Cash taxes (after NOLs) | B10: =-1*(SUMPRODUCT(M_Base!C88:U88,M_Base!C92:U92)+M_Base!$C$100*M_Base!U88/M_Base!U90) -> -0.29227645 | C10: =B10*1000/Drivers!$C$19 -> -0.73197208
A11: Net capex & working capital | B11: =-(SUMPRODUCT(M_Base!C82:U82,M_Base!C92:U92)-SUMPRODUCT(M_Base!C83:U83,M_Base!C92:U92)+SUMPRODUCT(M_Base!C84:U84,M_Base!C92:U92))-M_Base!$C$100*(M_Base!U82-M_Base!U83+M_Base!U84)/M_Base!U90 -> -0.73268555 | C11: =B11*1000/Drivers!$C$19 -> -1.834925
A12: Q4-2026 stub cash burn | B12: =M_Base!$C$97 -> -0.45433056 | C12: =B12*1000/Drivers!$C$19 -> -1.1378176
A13: Unidentified future pipeline (credit) | B13: =M_Base!$C$102 -> 5.2331894 | C13: =B13*1000/Drivers!$C$19 -> 13.105909
A14: Enterprise value (sum) | B14: =SUM(B4:B13) -> 7.7281382 | C14: =B14*1000/Drivers!$C$19 -> 19.354215 | D14: check vs M_Base EV: | E14: =B14-M_Base!$C$103 -> 0
A15: + Cash & investments (est.) | B15: =Drivers!$C$6 -> 8.04 | C15: =B15*1000/Drivers!$C$19 -> 20.135237
A16: - Term loan | B16: =-Drivers!$C$7 -> -0.6 | C16: =B16*1000/Drivers!$C$19 -> -1.5026296
A17: - Convertible notes (face) | B17: =-Drivers!$C$8 -> -3 | C17: =B17*1000/Drivers!$C$19 -> -7.513148
A18: - Finance leases | B18: =-Drivers!$C$12 -> -0.037 | C18: =B18*1000/Drivers!$C$19 -> -0.092662159
A19: - Arbutus contingent (expected PV) | B19: =-M_Base!$C$105 -> -0.76519062 | C19: =B19*1000/Drivers!$C$19 -> -1.9163301
A20: - Other patent litigation | B20: =-M_Base!$C$21 -> -0.5 | C20: =B20*1000/Drivers!$C$19 -> -1.2521913
A21: + Pfizer/BioNTech litigation option | B21: =Drivers!$C$18 -> 0.05 | C21: =B21*1000/Drivers!$C$19 -> 0.12521913
A22: Equity value (sum) | B22: =SUM(B14:B21) -> 10.915948 | C22: =B22*1000/Drivers!$C$19 -> 27.33771
A23: Value per share (Base) | B23: =M_Base!$C$109 -> 26.47574

Sheet M_Failure
A1: M_Failure - scenario model (ESMO data weak (HR ~0.85) / FDA (CBER) requires OS -> melanoma not approved; readthrough cuts other INT PoS by 60%; respiratory bear.)
A2: Scenario index (1=Failure..5=Blue-sky) | C2: 1
A4: Scenario levers (green = pulled from Drivers)
A5: COVID revenue multiplier | C5: =INDEX(Drivers!$D$39:$H$39,$C$2) -> 0.75
A6: Flu (mFLUSIVA) peak multiplier | C6: =INDEX(Drivers!$D$40:$H$40,$C$2) -> 0.5
A7: Flu+COVID combo peak multiplier | C7: =INDEX(Drivers!$D$41:$H$41,$C$2) -> 0.5
A8: Norovirus PoS | C8: =INDEX(Drivers!$D$42:$H$42,$C$2) -> 0.15
A9: Respiratory gross-margin shift | C9: =INDEX(Drivers!$D$43:$H$43,$C$2) -> -0.04
A10: INT melanoma PoS | C10: =INDEX(Drivers!$D$44:$H$44,$C$2) -> 0
A11: INT melanoma peak global sales ($B, before price factor) | C11: =INDEX(Drivers!$D$45:$H$45,$C$2) -> 2.8
A12: INT melanoma launch year | C12: =INDEX(Drivers!$D$46:$H$46,$C$2) -> 2027
A13: INT other-indication PoS multiplier (>=10 => all 100%) | C13: =INDEX(Drivers!$D$47:$H$47,$C$2) -> 0.4
A14: INT other-indication peak multiplier | C14: =INDEX(Drivers!$D$48:$H$48,$C$2) -> 0.8
A15: INT price factor (1.0 = US net ~$300k) | C15: =INDEX(Drivers!$D$49:$H$49,$C$2) -> 0.8
A16: INT mature profit-pool margin | C16: =INDEX(Drivers!$D$50:$H$50,$C$2) -> 0.55
A17: Unallocated R&D multiplier | C17: =INDEX(Drivers!$D$51:$H$51,$C$2) -> 0.6
A18: Future-pipeline credit factor | C18: =INDEX(Drivers!$D$52:$H$52,$C$2) -> 0.25
A19: WACC | C19: =INDEX(Drivers!$D$53:$H$53,$C$2) -> 0.1043
A20: Terminal growth | C20: =INDEX(Drivers!$D$54:$H$54,$C$2) -> -0.01
A21: Other patent litigation (expected cost) | C21: =INDEX(Drivers!$D$55:$H$55,$C$2) -> 1
A22: INT indications: scenario-adjusted launch / peak / PoS
A23: Indication | C23: Launch | D23: Peak | E23: PoS
A24: =Drivers!$B$95 -> Adjuvant melanoma IIB-IV (INTerpath-001) | C24: =$C$12 -> 2027 | D24: =$C$11 -> 2.8 | E24: =$C$10 -> 0
A25: =Drivers!$B$96 -> Adjuvant NSCLC II-IIIB (INTerpath-002) | C25: =Drivers!$D$96 -> 2031 | D25: =Drivers!$E$96*$C$14 -> 3.2 | E25: =MIN(Drivers!$F$96*$C$13,IF($C$13>=10,1,0.95)) -> 0.18
A26: =Drivers!$B$97 -> Post-neoadjuvant non-pCR NSCLC (INTerpath-009) | C26: =Drivers!$D$97 -> 2034 | D26: =Drivers!$E$97*$C$14 -> 1.2 | E26: =MIN(Drivers!$F$97*$C$13,IF($C$13>=10,1,0.95)) -> 0.16
A27: =Drivers!$B$98 -> Resected stage I NSCLC (INTerpath-014) | C27: =Drivers!$D$98 -> 2035 | D27: =Drivers!$E$98*$C$14 -> 2 | E27: =MIN(Drivers!$F$98*$C$13,IF($C$13>=10,1,0.95)) -> 0.14
A28: =Drivers!$B$99 -> Adjuvant RCC (INTerpath-004) | C28: =Drivers!$D$99 -> 2031 | D28: =Drivers!$E$99*$C$14 -> 0.96 | E28: =MIN(Drivers!$F$99*$C$13,IF($C$13>=10,1,0.95)) -> 0.1
A29: =Drivers!$B$100 -> MIBC adjuvant (INTerpath-005) | C29: =Drivers!$D$100 -> 2033 | D29: =Drivers!$E$100*$C$14 -> 0.8 | E29: =MIN(Drivers!$F$100*$C$13,IF($C$13>=10,1,0.95)) -> 0.08
A30: =Drivers!$B$101 -> NMIBC + BCG (INTerpath-011) | C30: =Drivers!$D$101 -> 2034 | D30: =Drivers!$E$101*$C$14 -> 0.8 | E30: =MIN(Drivers!$F$101*$C$13,IF($C$13>=10,1,0.95)) -> 0.06
A31: =Drivers!$B$102 -> 1L advanced melanoma (INTerpath-012) | C31: =Drivers!$D$102 -> 2031 | D31: =Drivers!$E$102*$C$14 -> 0.64 | E31: =MIN(Drivers!$F$102*$C$13,IF($C$13>=10,1,0.95)) -> 0.08
A32: =Drivers!$B$103 -> 1L metastatic squamous NSCLC (INTerpath-013) | C32: =Drivers!$D$103 -> 2032 | D32: =Drivers!$E$103*$C$14 -> 0.96 | E32: =MIN(Drivers!$F$103*$C$13,IF($C$13>=10,1,0.95)) -> 0.06
A33: =Drivers!$B$104 -> Other solid tumours - future INT indications (pre-Ph2) | C33: =Drivers!$D$104 -> 2035 | D33: =Drivers!$E$104*$C$14 -> 4.8 | E33: =MIN(Drivers!$F$104*$C$13,IF($C$13>=10,1,0.95)) -> 0.04
A35: Year | B35: unit | C35: 2027 | D35: 2028 | E35: 2029 | F35: 2030 | G35: 2031 | H35: 2032 | I35: 2033 | J35: 2034 | K35: 2035 | L35: 2036 | M35: 2037 | N35: 2038 | O35: 2039 | P35: 2040 | Q35: 2041 | R35: 2042 | S35: 2043 | T35: 2044 | U35: 2045
A36: Year index i | C36: 0 | D36: 1 | E36: 2 | F36: 3 | G36: 4 | H36: 5 | I36: 6 | J36: 7 | K36: 8 | L36: 9 | M36: 10 | N36: 11 | O36: 12 | P36: 13 | Q36: 14 | R36: 15 | S36: 16 | T36: 17 | U36: 18
A37: RESPIRATORY FRANCHISE
A38: COVID (Spikevax, mNEXSPIKE, partnerships) | B38: $B | C38: =Drivers!$D$60*$C$5 -> 1.3875 | D38: =Drivers!$E$60*$C$5 -> 1.275 | E38: =Drivers!$F$60*$C$5 -> 1.1625 | F38: =Drivers!$G$60*$C$5 -> 1.0875 | G38: =Drivers!$H$60*$C$5 -> 1.035 | H38: =Drivers!$I$60*$C$5 -> 0.975 | I38: =H38*(1+Drivers!$C$61) -> 0.9555 | J38: =I38*(1+Drivers!$C$61) -> 0.93639 | K38: =J38*(1+Drivers!$C$61) -> 0.9176622 | L38: =K38*(1+Drivers!$C$61) -> 0.89930896 | M38: =L38*(1+Drivers!$C$61) -> 0.88132278 | N38: =M38*(1+Drivers!$C$61) -> 0.86369632 | O38: =N38*(1+Drivers!$C$61) -> 0.84642239 | P38: =O38*(1+Drivers!$C$61) -> 0.82949395 | ... U38: =T38*(1+Drivers!$C$61) -> 0.74979683
A39: Flu (mFLUSIVA) | B39: $B | C39: =Drivers!$C$62*IF((C$35-Drivers!$C$63)<0,0,MIN(((C$35-Drivers!$C$63)+1)/Drivers!$C$64,1))*$C$6 -> 0.08 | D39: =Drivers!$C$62*IF((D$35-Drivers!$C$63)<0,0,MIN(((D$35-Drivers!$C$63)+1)/Drivers!$C$64,1))*$C$6 -> 0.16 | E39: =Drivers!$C$62*IF((E$35-Drivers!$C$63)<0,0,MIN(((E$35-Drivers!$C$63)+1)/Drivers!$C$64,1))*$C$6 -> 0.24 | F39: =Drivers!$C$62*IF((F$35-Drivers!$C$63)<0,0,MIN(((F$35-Drivers!$C$63)+1)/Drivers!$C$64,1))*$C$6 -> 0.32 | G39: =Drivers!$C$62*IF((G$35-Drivers!$C$63)<0,0,MIN(((G$35-Drivers!$C$63)+1)/Drivers!$C$64,1))*$C$6 -> 0.4 | H39: =Drivers!$C$62*IF((H$35-Drivers!$C$63)<0,0,MIN(((H$35-Drivers!$C$63)+1)/Drivers!$C$64,1))*$C$6 -> 0.4 | I39: =Drivers!$C$62*IF((I$35-Drivers!$C$63)<0,0,MIN(((I$35-Drivers!$C$63)+1)/Drivers!$C$64,1))*$C$6 -> 0.4 | J39: =Drivers!$C$62*IF((J$35-Drivers!$C$63)<0,0,MIN(((J$35-Drivers!$C$63)+1)/Drivers!$C$64,1))*$C$6 -> 0.4 | ... U39: =Drivers!$C$62*IF((U$35-Drivers!$C$63)<0,0,MIN(((U$35-Drivers!$C$63)+1)/Drivers!$C$64,1))*$C$6 -> 0.4
A40: Flu+COVID combo (mCOMBRIAX) | B40: $B | C40: =Drivers!$C$65*IF((C$35-Drivers!$C$66)<0,0,MIN(((C$35-Drivers!$C$66)+1)/Drivers!$C$67,1))*$C$7*((1-Drivers!$C$69)+Drivers!$C$69*Drivers!$C$68) -> 0.1169 | D40: =Drivers!$C$65*IF((D$35-Drivers!$C$66)<0,0,MIN(((D$35-Drivers!$C$66)+1)/Drivers!$C$67,1))*$C$7*((1-Drivers!$C$69)+Drivers!$C$69*Drivers!$C$68) -> 0.2338 | E40: =Drivers!$C$65*IF((E$35-Drivers!$C$66)<0,0,MIN(((E$35-Drivers!$C$66)+1)/Drivers!$C$67,1))*$C$7*((1-Drivers!$C$69)+Drivers!$C$69*Drivers!$C$68) -> 0.3507 | F40: =Drivers!$C$65*IF((F$35-Drivers!$C$66)<0,0,MIN(((F$35-Drivers!$C$66)+1)/Drivers!$C$67,1))*$C$7*((1-Drivers!$C$69)+Drivers!$C$69*Drivers!$C$68) -> 0.4676 | G40: =Drivers!$C$65*IF((G$35-Drivers!$C$66)<0,0,MIN(((G$35-Drivers!$C$66)+1)/Drivers!$C$67,1))*$C$7*((1-Drivers!$C$69)+Drivers!$C$69*Drivers!$C$68) -> 0.5845 | H40: =Drivers!$C$65*IF((H$35-Drivers!$C$66)<0,0,MIN(((H$35-Drivers!$C$66)+1)/Drivers!$C$67,1))*$C$7*((1-Drivers!$C$69)+Drivers!$C$69*Drivers!$C$68) -> 0.5845 | I40: =Drivers!$C$65*IF((I$35-Drivers!$C$66)<0,0,MIN(((I$35-Drivers!$C$66)+1)/Drivers!$C$67,1))*$C$7*((1-Drivers!$C$69)+Drivers!$C$69*Drivers!$C$68) -> 0.5845 | J40: =Drivers!$C$65*IF((J$35-Drivers!$C$66)<0,0,MIN(((J$35-Drivers!$C$66)+1)/Drivers!$C$67,1))*$C$7*((1-Drivers!$C$69)+Drivers!$C$69*Drivers!$C$68) -> 0.5845 | ... U40: =Drivers!$C$65*IF((U$35-Drivers!$C$66)<0,0,MIN(((U$35-Drivers!$C$66)+1)/Drivers!$C$67,1))*$C$7*((1-Drivers!$C$69)+Drivers!$C$69*Drivers!$C$68) -> 0.5845
A41: RSV (mRESVIA) | B41: $B | C41: =Drivers!$C$70*MIN((C$35-2026)/3,1) -> 0.05 | D41: =Drivers!$C$70*MIN((D$35-2026)/3,1) -> 0.1 | E41: =Drivers!$C$70*MIN((E$35-2026)/3,1) -> 0.15 | F41: =Drivers!$C$70*MIN((F$35-2026)/3,1) -> 0.15 | G41: =Drivers!$C$70*MIN((G$35-2026)/3,1) -> 0.15 | H41: =Drivers!$C$70*MIN((H$35-2026)/3,1) -> 0.15 | I41: =Drivers!$C$70*MIN((I$35-2026)/3,1) -> 0.15 | J41: =Drivers!$C$70*MIN((J$35-2026)/3,1) -> 0.15 | ... U41: =Drivers!$C$70*MIN((U$35-2026)/3,1) -> 0.15
A42: Norovirus (risk-adjusted) | B42: $B | C42: =$C$8*Drivers!$C$71*IF((C$35-Drivers!$C$72)<0,0,MIN(((C$35-Drivers!$C$72)+1)/Drivers!$C$73,1)) -> 0 | D42: =$C$8*Drivers!$C$71*IF((D$35-Drivers!$C$72)<0,0,MIN(((D$35-Drivers!$C$72)+1)/Drivers!$C$73,1)) -> 0 | E42: =$C$8*Drivers!$C$71*IF((E$35-Drivers!$C$72)<0,0,MIN(((E$35-Drivers!$C$72)+1)/Drivers!$C$73,1)) -> 0.036 | F42: =$C$8*Drivers!$C$71*IF((F$35-Drivers!$C$72)<0,0,MIN(((F$35-Drivers!$C$72)+1)/Drivers!$C$73,1)) -> 0.072 | G42: =$C$8*Drivers!$C$71*IF((G$35-Drivers!$C$72)<0,0,MIN(((G$35-Drivers!$C$72)+1)/Drivers!$C$73,1)) -> 0.108 | H42: =$C$8*Drivers!$C$71*IF((H$35-Drivers!$C$72)<0,0,MIN(((H$35-Drivers!$C$72)+1)/Drivers!$C$73,1)) -> 0.144 | I42: =$C$8*Drivers!$C$71*IF((I$35-Drivers!$C$72)<0,0,MIN(((I$35-Drivers!$C$72)+1)/Drivers!$C$73,1)) -> 0.18 | J42: =$C$8*Drivers!$C$71*IF((J$35-Drivers!$C$72)<0,0,MIN(((J$35-Drivers!$C$72)+1)/Drivers!$C$73,1)) -> 0.18 | ... U42: =$C$8*Drivers!$C$71*IF((U$35-Drivers!$C$72)<0,0,MIN(((U$35-Drivers!$C$72)+1)/Drivers!$C$73,1)) -> 0.18
A43: Other revenue | B43: $B | C43: =Drivers!$C$74 -> 0.15 | D43: =Drivers!$C$74 -> 0.15 | E43: =Drivers!$C$74 -> 0.15 | F43: =Drivers!$C$74 -> 0.15 | G43: =Drivers!$C$74 -> 0.15 | H43: =Drivers!$C$74 -> 0.15 | I43: =Drivers!$C$74 -> 0.15 | J43: =Drivers!$C$74 -> 0.15 | ... U43: =Drivers!$C$74 -> 0.15
A44: Respiratory revenue | B44: $B | C44: =SUM(C38:C43) -> 1.7844 | D44: =SUM(D38:D43) -> 1.9188 | E44: =SUM(E38:E43) -> 2.0892 | F44: =SUM(F38:F43) -> 2.2471 | G44: =SUM(G38:G43) -> 2.4275 | H44: =SUM(H38:H43) -> 2.4035 | I44: =SUM(I38:I43) -> 2.42 | J44: =SUM(J38:J43) -> 2.40089 | ... U44: =SUM(U38:U43) -> 2.2142968
A45: Gross margin | B45: % | C45: =Drivers!$D$75+$C$9 -> 0.6 | D45: =Drivers!$E$75+$C$9 -> 0.64 | E45: =Drivers!$F$75+$C$9 -> 0.67 | F45: =Drivers!$G$75+$C$9 -> 0.69 | G45: =Drivers!$H$75+$C$9 -> 0.7 | H45: =Drivers!$I$75+$C$9 -> 0.71 | I45: =Drivers!$I$75+$C$9 -> 0.71 | J45: =Drivers!$I$75+$C$9 -> 0.71 | K45: =Drivers!$I$75+$C$9 -> 0.71 | L45: =Drivers!$I$75+$C$9 -> 0.71 | M45: =Drivers!$I$75+$C$9 -> 0.71 | N45: =Drivers!$I$75+$C$9 -> 0.71 | O45: =Drivers!$I$75+$C$9 -> 0.71 | ... U45: =Drivers!$I$75+$C$9 -> 0.71
A46: Flu + combo revenue | B46: $B | C46: =C39+C40 -> 0.1969 | D46: =D39+D40 -> 0.3938 | E46: =E39+E40 -> 0.5907 | F46: =F39+F40 -> 0.7876 | G46: =G39+G40 -> 0.9845 | H46: =H39+H40 -> 0.9845 | I46: =I39+I40 -> 0.9845 | J46: =J39+J40 -> 0.9845 | ... U46: =U39+U40 -> 0.9845
A47: Blackstone sales milestones paid | B47: $B | C47: =MIN(Drivers!$C$77-0,Drivers!$C$78*C46) -> 0.015752 | D47: =MIN(Drivers!$C$77-C48,Drivers!$C$78*D46) -> 0.031504 | E47: =MIN(Drivers!$C$77-D48,Drivers!$C$78*E46) -> 0.047256 | F47: =MIN(Drivers!$C$77-E48,Drivers!$C$78*F46) -> 0.063008 | G47: =MIN(Drivers!$C$77-F48,Drivers!$C$78*G46) -> 0.07876 | H47: =MIN(Drivers!$C$77-G48,Drivers!$C$78*H46) -> 0.07876 | I47: =MIN(Drivers!$C$77-H48,Drivers!$C$78*I46) -> 0.07876 | J47: =MIN(Drivers!$C$77-I48,Drivers!$C$78*J46) -> 0.07876 | K47: =MIN(Drivers!$C$77-J48,Drivers!$C$78*K46) -> 0.07876 | ... U47: =MIN(Drivers!$C$77-T48,Drivers!$C$78*U46) -> 0
A48: Blackstone milestones cumulative | B48: $B | C48: =C47 -> 0.015752 | D48: =C48+D47 -> 0.047256 | E48: =D48+E47 -> 0.094512 | F48: =E48+F47 -> 0.15752 | G48: =F48+G47 -> 0.23628 | H48: =G48+H47 -> 0.31504 | I48: =H48+I47 -> 0.3938 | J48: =I48+J47 -> 0.47256 | K48: =J48+K47 -> 0.55132 | ... U48: =T48+U47 -> 0.75
A49: Blackstone royalty + milestones | B49: $B | C49: =Drivers!$C$76*C46+C47 -> 0.0206745 | D49: =Drivers!$C$76*D46+D47 -> 0.041349 | E49: =Drivers!$C$76*E46+E47 -> 0.0620235 | F49: =Drivers!$C$76*F46+F47 -> 0.082698 | G49: =Drivers!$C$76*G46+G47 -> 0.1033725 | H49: =Drivers!$C$76*H46+H47 -> 0.1033725 | I49: =Drivers!$C$76*I46+I47 -> 0.1033725 | J49: =Drivers!$C$76*J46+J47 -> 0.1033725 | ... U49: =Drivers!$C$76*U46+U47 -> 0.0246125
A50: Respiratory S&M | B50: $B | C50: =MAX(Drivers!$C$80,Drivers!$C$79*C44) -> 0.4 | D50: =MAX(Drivers!$C$80,Drivers!$C$79*D44) -> 0.4 | E50: =MAX(Drivers!$C$80,Drivers!$C$79*E44) -> 0.4 | F50: =MAX(Drivers!$C$80,Drivers!$C$79*F44) -> 0.4 | G50: =MAX(Drivers!$C$80,Drivers!$C$79*G44) -> 0.4 | H50: =MAX(Drivers!$C$80,Drivers!$C$79*H44) -> 0.4 | I50: =MAX(Drivers!$C$80,Drivers!$C$79*I44) -> 0.4 | J50: =MAX(Drivers!$C$80,Drivers!$C$79*J44) -> 0.4 | ... U50: =MAX(Drivers!$C$80,Drivers!$C$79*U44) -> 0.4
A51: Respiratory R&D | B51: $B | C51: =Drivers!$D$81 -> 0.75 | D51: =Drivers!$E$81 -> 0.62 | E51: =Drivers!$F$81 -> 0.55 | F51: =Drivers!$G$81 -> 0.5 | G51: =Drivers!$H$81 -> 0.48 | H51: =Drivers!$I$81 -> 0.46 | I51: =H51*1.02 -> 0.4692 | J51: =I51*1.02 -> 0.478584 | K51: =J51*1.02 -> 0.48815568 | L51: =K51*1.02 -> 0.49791879 | M51: =L51*1.02 -> 0.50787717 | N51: =M51*1.02 -> 0.51803471 | O51: =N51*1.02 -> 0.52839541 | P51: =O51*1.02 -> 0.53896332 | ... U51: =T51*1.02 -> 0.59505905
A52: Respiratory contribution | B52: $B | C52: =C44*C45-C49-C50-C51 -> -0.1000345 | D52: =D44*D45-D49-D50-D51 -> 0.166683 | E52: =E44*E45-E49-E50-E51 -> 0.3877405 | F52: =F44*F45-F49-F50-F51 -> 0.567801 | G52: =G44*G45-G49-G50-G51 -> 0.7158775 | H52: =H44*H45-H49-H50-H51 -> 0.7431125 | I52: =I44*I45-I49-I50-I51 -> 0.7456275 | J52: =J44*J45-J49-J50-J51 -> 0.7226754 | ... U52: =U44*U45-U49-U50-U51 -> 0.5524792
A53: INTISMERAN (risk-adjusted global sales; Moderna books 50% of profit pool)
A54: Adjuvant melanoma IIB-IV (INTerpath-001) | B54: $B | C54: =$D$24*$C$15*IF((C$35-$C$24)<0,0,IF((C$35-$C$24)>=7,1,INDEX(Drivers!$D$86:$J$86,(C$35-$C$24)+1)))*IF((C$35-$C$24)<Drivers!$C$87,1,Drivers!$C$88*Drivers!$C$89^((C$35-$C$24)-Drivers!$C$87))*$E$24 -> 0 | D54: =$D$24*$C$15*IF((D$35-$C$24)<0,0,IF((D$35-$C$24)>=7,1,INDEX(Drivers!$D$86:$J$86,(D$35-$C$24)+1)))*IF((D$35-$C$24)<Drivers!$C$87,1,Drivers!$C$88*Drivers!$C$89^((D$35-$C$24)-Drivers!$C$87))*$E$24 -> 0 | E54: =$D$24*$C$15*IF((E$35-$C$24)<0,0,IF((E$35-$C$24)>=7,1,INDEX(Drivers!$D$86:$J$86,(E$35-$C$24)+1)))*IF((E$35-$C$24)<Drivers!$C$87,1,Drivers!$C$88*Drivers!$C$89^((E$35-$C$24)-Drivers!$C$87))*$E$24 -> 0 | F54: =$D$24*$C$15*IF((F$35-$C$24)<0,0,IF((F$35-$C$24)>=7,1,INDEX(Drivers!$D$86:$J$86,(F$35-$C$24)+1)))*IF((F$35-$C$24)<Drivers!$C$87,1,Drivers!$C$88*Drivers!$C$89^((F$35-$C$24)-Drivers!$C$87))*$E$24 -> 0 | G54: =$D$24*$C$15*IF((G$35-$C$24)<0,0,IF((G$35-$C$24)>=7,1,INDEX(Drivers!$D$86:$J$86,(G$35-$C$24)+1)))*IF((G$35-$C$24)<Drivers!$C$87,1,Drivers!$C$88*Drivers!$C$89^((G$35-$C$24)-Drivers!$C$87))*$E$24 -> 0 | H54: =$D$24*$C$15*IF((H$35-$C$24)<0,0,IF((H$35-$C$24)>=7,1,INDEX(Drivers!$D$86:$J$86,(H$35-$C$24)+1)))*IF((H$35-$C$24)<Drivers!$C$87,1,Drivers!$C$88*Drivers!$C$89^((H$35-$C$24)-Drivers!$C$87))*$E$24 -> 0 | I54: =$D$24*$C$15*IF((I$35-$C$24)<0,0,IF((I$35-$C$24)>=7,1,INDEX(Drivers!$D$86:$J$86,(I$35-$C$24)+1)))*IF((I$35-$C$24)<Drivers!$C$87,1,Drivers!$C$88*Drivers!$C$89^((I$35-$C$24)-Drivers!$C$87))*$E$24 -> 0 | J54: =$D$24*$C$15*IF((J$35-$C$24)<0,0,IF((J$35-$C$24)>=7,1,INDEX(Drivers!$D$86:$J$86,(J$35-$C$24)+1)))*IF((J$35-$C$24)<Drivers!$C$87,1,Drivers!$C$88*Drivers!$C$89^((J$35-$C$24)-Drivers!$C$87))*$E$24 -> 0 | ... U54: =$D$24*$C$15*IF((U$35-$C$24)<0,0,IF((U$35-$C$24)>=7,1,INDEX(Drivers!$D$86:$J$86,(U$35-$C$24)+1)))*IF((U$35-$C$24)<Drivers!$C$87,1,Drivers!$C$88*Drivers!$C$89^((U$35-$C$24)-Drivers!$C$87))*$E$24 -> 0
A55: Adjuvant NSCLC II-IIIB (INTerpath-002) | B55: $B | C55: =$D$25*$C$15*IF((C$35-$C$25)<0,0,IF((C$35-$C$25)>=7,1,INDEX(Drivers!$D$86:$J$86,(C$35-$C$25)+1)))*IF((C$35-$C$25)<Drivers!$C$87,1,Drivers!$C$88*Drivers!$C$89^((C$35-$C$25)-Drivers!$C$87))*$E$25 -> 0 | D55: =$D$25*$C$15*IF((D$35-$C$25)<0,0,IF((D$35-$C$25)>=7,1,INDEX(Drivers!$D$86:$J$86,(D$35-$C$25)+1)))*IF((D$35-$C$25)<Drivers!$C$87,1,Drivers!$C$88*Drivers!$C$89^((D$35-$C$25)-Drivers!$C$87))*$E$25 -> 0 | E55: =$D$25*$C$15*IF((E$35-$C$25)<0,0,IF((E$35-$C$25)>=7,1,INDEX(Drivers!$D$86:$J$86,(E$35-$C$25)+1)))*IF((E$35-$C$25)<Drivers!$C$87,1,Drivers!$C$88*Drivers!$C$89^((E$35-$C$25)-Drivers!$C$87))*$E$25 -> 0 | F55: =$D$25*$C$15*IF((F$35-$C$25)<0,0,IF((F$35-$C$25)>=7,1,INDEX(Drivers!$D$86:$J$86,(F$35-$C$25)+1)))*IF((F$35-$C$25)<Drivers!$C$87,1,Drivers!$C$88*Drivers!$C$89^((F$35-$C$25)-Drivers!$C$87))*$E$25 -> 0 | G55: =$D$25*$C$15*IF((G$35-$C$25)<0,0,IF((G$35-$C$25)>=7,1,INDEX(Drivers!$D$86:$J$86,(G$35-$C$25)+1)))*IF((G$35-$C$25)<Drivers!$C$87,1,Drivers!$C$88*Drivers!$C$89^((G$35-$C$25)-Drivers!$C$87))*$E$25 -> 0.036864 | H55: =$D$25*$C$15*IF((H$35-$C$25)<0,0,IF((H$35-$C$25)>=7,1,INDEX(Drivers!$D$86:$J$86,(H$35-$C$25)+1)))*IF((H$35-$C$25)<Drivers!$C$87,1,Drivers!$C$88*Drivers!$C$89^((H$35-$C$25)-Drivers!$C$87))*$E$25 -> 0.1152 | I55: =$D$25*$C$15*IF((I$35-$C$25)<0,0,IF((I$35-$C$25)>=7,1,INDEX(Drivers!$D$86:$J$86,(I$35-$C$25)+1)))*IF((I$35-$C$25)<Drivers!$C$87,1,Drivers!$C$88*Drivers!$C$89^((I$35-$C$25)-Drivers!$C$87))*$E$25 -> 0.20736 | J55: =$D$25*$C$15*IF((J$35-$C$25)<0,0,IF((J$35-$C$25)>=7,1,INDEX(Drivers!$D$86:$J$86,(J$35-$C$25)+1)))*IF((J$35-$C$25)<Drivers!$C$87,1,Drivers!$C$88*Drivers!$C$89^((J$35-$C$25)-Drivers!$C$87))*$E$25 -> 0.29952 | ... U55: =$D$25*$C$15*IF((U$35-$C$25)<0,0,IF((U$35-$C$25)>=7,1,INDEX(Drivers!$D$86:$J$86,(U$35-$C$25)+1)))*IF((U$35-$C$25)<Drivers!$C$87,1,Drivers!$C$88*Drivers!$C$89^((U$35-$C$25)-Drivers!$C$87))*$E$25 -> 0.34685338
A56: Post-neoadjuvant non-pCR NSCLC (INTerpath-009) | B56: $B | C56: =$D$26*$C$15*IF((C$35-$C$26)<0,0,IF((C$35-$C$26)>=7,1,INDEX(Drivers!$D$86:$J$86,(C$35-$C$26)+1)))*IF((C$35-$C$26)<Drivers!$C$87,1,Drivers!$C$88*Drivers!$C$89^((C$35-$C$26)-Drivers!$C$87))*$E$26 -> 0 | D56: =$D$26*$C$15*IF((D$35-$C$26)<0,0,IF((D$35-$C$26)>=7,1,INDEX(Drivers!$D$86:$J$86,(D$35-$C$26)+1)))*IF((D$35-$C$26)<Drivers!$C$87,1,Drivers!$C$88*Drivers!$C$89^((D$35-$C$26)-Drivers!$C$87))*$E$26 -> 0 | E56: =$D$26*$C$15*IF((E$35-$C$26)<0,0,IF((E$35-$C$26)>=7,1,INDEX(Drivers!$D$86:$J$86,(E$35-$C$26)+1)))*IF((E$35-$C$26)<Drivers!$C$87,1,Drivers!$C$88*Drivers!$C$89^((E$35-$C$26)-Drivers!$C$87))*$E$26 -> 0 | F56: =$D$26*$C$15*IF((F$35-$C$26)<0,0,IF((F$35-$C$26)>=7,1,INDEX(Drivers!$D$86:$J$86,(F$35-$C$26)+1)))*IF((F$35-$C$26)<Drivers!$C$87,1,Drivers!$C$88*Drivers!$C$89^((F$35-$C$26)-Drivers!$C$87))*$E$26 -> 0 | G56: =$D$26*$C$15*IF((G$35-$C$26)<0,0,IF((G$35-$C$26)>=7,1,INDEX(Drivers!$D$86:$J$86,(G$35-$C$26)+1)))*IF((G$35-$C$26)<Drivers!$C$87,1,Drivers!$C$88*Drivers!$C$89^((G$35-$C$26)-Drivers!$C$87))*$E$26 -> 0 | H56: =$D$26*$C$15*IF((H$35-$C$26)<0,0,IF((H$35-$C$26)>=7,1,INDEX(Drivers!$D$86:$J$86,(H$35-$C$26)+1)))*IF((H$35-$C$26)<Drivers!$C$87,1,Drivers!$C$88*Drivers!$C$89^((H$35-$C$26)-Drivers!$C$87))*$E$26 -> 0 | I56: =$D$26*$C$15*IF((I$35-$C$26)<0,0,IF((I$35-$C$26)>=7,1,INDEX(Drivers!$D$86:$J$86,(I$35-$C$26)+1)))*IF((I$35-$C$26)<Drivers!$C$87,1,Drivers!$C$88*Drivers!$C$89^((I$35-$C$26)-Drivers!$C$87))*$E$26 -> 0 | J56: =$D$26*$C$15*IF((J$35-$C$26)<0,0,IF((J$35-$C$26)>=7,1,INDEX(Drivers!$D$86:$J$86,(J$35-$C$26)+1)))*IF((J$35-$C$26)<Drivers!$C$87,1,Drivers!$C$88*Drivers!$C$89^((J$35-$C$26)-Drivers!$C$87))*$E$26 -> 0.012288 | ... U56: =$D$26*$C$15*IF((U$35-$C$26)<0,0,IF((U$35-$C$26)>=7,1,INDEX(Drivers!$D$86:$J$86,(U$35-$C$26)+1)))*IF((U$35-$C$26)<Drivers!$C$87,1,Drivers!$C$88*Drivers!$C$89^((U$35-$C$26)-Drivers!$C$87))*$E$26 -> 0.1536
A57: Resected stage I NSCLC (INTerpath-014) | B57: $B | C57: =$D$27*$C$15*IF((C$35-$C$27)<0,0,IF((C$35-$C$27)>=7,1,INDEX(Drivers!$D$86:$J$86,(C$35-$C$27)+1)))*IF((C$35-$C$27)<Drivers!$C$87,1,Drivers!$C$88*Drivers!$C$89^((C$35-$C$27)-Drivers!$C$87))*$E$27 -> 0 | D57: =$D$27*$C$15*IF((D$35-$C$27)<0,0,IF((D$35-$C$27)>=7,1,INDEX(Drivers!$D$86:$J$86,(D$35-$C$27)+1)))*IF((D$35-$C$27)<Drivers!$C$87,1,Drivers!$C$88*Drivers!$C$89^((D$35-$C$27)-Drivers!$C$87))*$E$27 -> 0 | E57: =$D$27*$C$15*IF((E$35-$C$27)<0,0,IF((E$35-$C$27)>=7,1,INDEX(Drivers!$D$86:$J$86,(E$35-$C$27)+1)))*IF((E$35-$C$27)<Drivers!$C$87,1,Drivers!$C$88*Drivers!$C$89^((E$35-$C$27)-Drivers!$C$87))*$E$27 -> 0 | F57: =$D$27*$C$15*IF((F$35-$C$27)<0,0,IF((F$35-$C$27)>=7,1,INDEX(Drivers!$D$86:$J$86,(F$35-$C$27)+1)))*IF((F$35-$C$27)<Drivers!$C$87,1,Drivers!$C$88*Drivers!$C$89^((F$35-$C$27)-Drivers!$C$87))*$E$27 -> 0 | G57: =$D$27*$C$15*IF((G$35-$C$27)<0,0,IF((G$35-$C$27)>=7,1,INDEX(Drivers!$D$86:$J$86,(G$35-$C$27)+1)))*IF((G$35-$C$27)<Drivers!$C$87,1,Drivers!$C$88*Drivers!$C$89^((G$35-$C$27)-Drivers!$C$87))*$E$27 -> 0 | H57: =$D$27*$C$15*IF((H$35-$C$27)<0,0,IF((H$35-$C$27)>=7,1,INDEX(Drivers!$D$86:$J$86,(H$35-$C$27)+1)))*IF((H$35-$C$27)<Drivers!$C$87,1,Drivers!$C$88*Drivers!$C$89^((H$35-$C$27)-Drivers!$C$87))*$E$27 -> 0 | I57: =$D$27*$C$15*IF((I$35-$C$27)<0,0,IF((I$35-$C$27)>=7,1,INDEX(Drivers!$D$86:$J$86,(I$35-$C$27)+1)))*IF((I$35-$C$27)<Drivers!$C$87,1,Drivers!$C$88*Drivers!$C$89^((I$35-$C$27)-Drivers!$C$87))*$E$27 -> 0 | J57: =$D$27*$C$15*IF((J$35-$C$27)<0,0,IF((J$35-$C$27)>=7,1,INDEX(Drivers!$D$86:$J$86,(J$35-$C$27)+1)))*IF((J$35-$C$27)<Drivers!$C$87,1,Drivers!$C$88*Drivers!$C$89^((J$35-$C$27)-Drivers!$C$87))*$E$27 -> 0 | ... U57: =$D$27*$C$15*IF((U$35-$C$27)<0,0,IF((U$35-$C$27)>=7,1,INDEX(Drivers!$D$86:$J$86,(U$35-$C$27)+1)))*IF((U$35-$C$27)<Drivers!$C$87,1,Drivers!$C$88*Drivers!$C$89^((U$35-$C$27)-Drivers!$C$87))*$E$27 -> 0.224
A58: Adjuvant RCC (INTerpath-004) | B58: $B | C58: =$D$28*$C$15*IF((C$35-$C$28)<0,0,IF((C$35-$C$28)>=7,1,INDEX(Drivers!$D$86:$J$86,(C$35-$C$28)+1)))*IF((C$35-$C$28)<Drivers!$C$87,1,Drivers!$C$88*Drivers!$C$89^((C$35-$C$28)-Drivers!$C$87))*$E$28 -> 0 | D58: =$D$28*$C$15*IF((D$35-$C$28)<0,0,IF((D$35-$C$28)>=7,1,INDEX(Drivers!$D$86:$J$86,(D$35-$C$28)+1)))*IF((D$35-$C$28)<Drivers!$C$87,1,Drivers!$C$88*Drivers!$C$89^((D$35-$C$28)-Drivers!$C$87))*$E$28 -> 0 | E58: =$D$28*$C$15*IF((E$35-$C$28)<0,0,IF((E$35-$C$28)>=7,1,INDEX(Drivers!$D$86:$J$86,(E$35-$C$28)+1)))*IF((E$35-$C$28)<Drivers!$C$87,1,Drivers!$C$88*Drivers!$C$89^((E$35-$C$28)-Drivers!$C$87))*$E$28 -> 0 | F58: =$D$28*$C$15*IF((F$35-$C$28)<0,0,IF((F$35-$C$28)>=7,1,INDEX(Drivers!$D$86:$J$86,(F$35-$C$28)+1)))*IF((F$35-$C$28)<Drivers!$C$87,1,Drivers!$C$88*Drivers!$C$89^((F$35-$C$28)-Drivers!$C$87))*$E$28 -> 0 | G58: =$D$28*$C$15*IF((G$35-$C$28)<0,0,IF((G$35-$C$28)>=7,1,INDEX(Drivers!$D$86:$J$86,(G$35-$C$28)+1)))*IF((G$35-$C$28)<Drivers!$C$87,1,Drivers!$C$88*Drivers!$C$89^((G$35-$C$28)-Drivers!$C$87))*$E$28 -> 0.006144 | H58: =$D$28*$C$15*IF((H$35-$C$28)<0,0,IF((H$35-$C$28)>=7,1,INDEX(Drivers!$D$86:$J$86,(H$35-$C$28)+1)))*IF((H$35-$C$28)<Drivers!$C$87,1,Drivers!$C$88*Drivers!$C$89^((H$35-$C$28)-Drivers!$C$87))*$E$28 -> 0.0192 | I58: =$D$28*$C$15*IF((I$35-$C$28)<0,0,IF((I$35-$C$28)>=7,1,INDEX(Drivers!$D$86:$J$86,(I$35-$C$28)+1)))*IF((I$35-$C$28)<Drivers!$C$87,1,Drivers!$C$88*Drivers!$C$89^((I$35-$C$28)-Drivers!$C$87))*$E$28 -> 0.03456 | J58: =$D$28*$C$15*IF((J$35-$C$28)<0,0,IF((J$35-$C$28)>=7,1,INDEX(Drivers!$D$86:$J$86,(J$35-$C$28)+1)))*IF((J$35-$C$28)<Drivers!$C$87,1,Drivers!$C$88*Drivers!$C$89^((J$35-$C$28)-Drivers!$C$87))*$E$28 -> 0.04992 | ... U58: =$D$28*$C$15*IF((U$35-$C$28)<0,0,IF((U$35-$C$28)>=7,1,INDEX(Drivers!$D$86:$J$86,(U$35-$C$28)+1)))*IF((U$35-$C$28)<Drivers!$C$87,1,Drivers!$C$88*Drivers!$C$89^((U$35-$C$28)-Drivers!$C$87))*$E$28 -> 0.057808896
A59: MIBC adjuvant (INTerpath-005) | B59: $B | C59: =$D$29*$C$15*IF((C$35-$C$29)<0,0,IF((C$35-$C$29)>=7,1,INDEX(Drivers!$D$86:$J$86,(C$35-$C$29)+1)))*IF((C$35-$C$29)<Drivers!$C$87,1,Drivers!$C$88*Drivers!$C$89^((C$35-$C$29)-Drivers!$C$87))*$E$29 -> 0 | D59: =$D$29*$C$15*IF((D$35-$C$29)<0,0,IF((D$35-$C$29)>=7,1,INDEX(Drivers!$D$86:$J$86,(D$35-$C$29)+1)))*IF((D$35-$C$29)<Drivers!$C$87,1,Drivers!$C$88*Drivers!$C$89^((D$35-$C$29)-Drivers!$C$87))*$E$29 -> 0 | E59: =$D$29*$C$15*IF((E$35-$C$29)<0,0,IF((E$35-$C$29)>=7,1,INDEX(Drivers!$D$86:$J$86,(E$35-$C$29)+1)))*IF((E$35-$C$29)<Drivers!$C$87,1,Drivers!$C$88*Drivers!$C$89^((E$35-$C$29)-Drivers!$C$87))*$E$29 -> 0 | F59: =$D$29*$C$15*IF((F$35-$C$29)<0,0,IF((F$35-$C$29)>=7,1,INDEX(Drivers!$D$86:$J$86,(F$35-$C$29)+1)))*IF((F$35-$C$29)<Drivers!$C$87,1,Drivers!$C$88*Drivers!$C$89^((F$35-$C$29)-Drivers!$C$87))*$E$29 -> 0 | G59: =$D$29*$C$15*IF((G$35-$C$29)<0,0,IF((G$35-$C$29)>=7,1,INDEX(Drivers!$D$86:$J$86,(G$35-$C$29)+1)))*IF((G$35-$C$29)<Drivers!$C$87,1,Drivers!$C$88*Drivers!$C$89^((G$35-$C$29)-Drivers!$C$87))*$E$29 -> 0 | H59: =$D$29*$C$15*IF((H$35-$C$29)<0,0,IF((H$35-$C$29)>=7,1,INDEX(Drivers!$D$86:$J$86,(H$35-$C$29)+1)))*IF((H$35-$C$29)<Drivers!$C$87,1,Drivers!$C$88*Drivers!$C$89^((H$35-$C$29)-Drivers!$C$87))*$E$29 -> 0 | I59: =$D$29*$C$15*IF((I$35-$C$29)<0,0,IF((I$35-$C$29)>=7,1,INDEX(Drivers!$D$86:$J$86,(I$35-$C$29)+1)))*IF((I$35-$C$29)<Drivers!$C$87,1,Drivers!$C$88*Drivers!$C$89^((I$35-$C$29)-Drivers!$C$87))*$E$29 -> 0.004096 | J59: =$D$29*$C$15*IF((J$35-$C$29)<0,0,IF((J$35-$C$29)>=7,1,INDEX(Drivers!$D$86:$J$86,(J$35-$C$29)+1)))*IF((J$35-$C$29)<Drivers!$C$87,1,Drivers!$C$88*Drivers!$C$89^((J$35-$C$29)-Drivers!$C$87))*$E$29 -> 0.0128 | ... U59: =$D$29*$C$15*IF((U$35-$C$29)<0,0,IF((U$35-$C$29)>=7,1,INDEX(Drivers!$D$86:$J$86,(U$35-$C$29)+1)))*IF((U$35-$C$29)<Drivers!$C$87,1,Drivers!$C$88*Drivers!$C$89^((U$35-$C$29)-Drivers!$C$87))*$E$29 -> 0.04096
A60: NMIBC + BCG (INTerpath-011) | B60: $B | C60: =$D$30*$C$15*IF((C$35-$C$30)<0,0,IF((C$35-$C$30)>=7,1,INDEX(Drivers!$D$86:$J$86,(C$35-$C$30)+1)))*IF((C$35-$C$30)<Drivers!$C$87,1,Drivers!$C$88*Drivers!$C$89^((C$35-$C$30)-Drivers!$C$87))*$E$30 -> 0 | D60: =$D$30*$C$15*IF((D$35-$C$30)<0,0,IF((D$35-$C$30)>=7,1,INDEX(Drivers!$D$86:$J$86,(D$35-$C$30)+1)))*IF((D$35-$C$30)<Drivers!$C$87,1,Drivers!$C$88*Drivers!$C$89^((D$35-$C$30)-Drivers!$C$87))*$E$30 -> 0 | E60: =$D$30*$C$15*IF((E$35-$C$30)<0,0,IF((E$35-$C$30)>=7,1,INDEX(Drivers!$D$86:$J$86,(E$35-$C$30)+1)))*IF((E$35-$C$30)<Drivers!$C$87,1,Drivers!$C$88*Drivers!$C$89^((E$35-$C$30)-Drivers!$C$87))*$E$30 -> 0 | F60: =$D$30*$C$15*IF((F$35-$C$30)<0,0,IF((F$35-$C$30)>=7,1,INDEX(Drivers!$D$86:$J$86,(F$35-$C$30)+1)))*IF((F$35-$C$30)<Drivers!$C$87,1,Drivers!$C$88*Drivers!$C$89^((F$35-$C$30)-Drivers!$C$87))*$E$30 -> 0 | G60: =$D$30*$C$15*IF((G$35-$C$30)<0,0,IF((G$35-$C$30)>=7,1,INDEX(Drivers!$D$86:$J$86,(G$35-$C$30)+1)))*IF((G$35-$C$30)<Drivers!$C$87,1,Drivers!$C$88*Drivers!$C$89^((G$35-$C$30)-Drivers!$C$87))*$E$30 -> 0 | H60: =$D$30*$C$15*IF((H$35-$C$30)<0,0,IF((H$35-$C$30)>=7,1,INDEX(Drivers!$D$86:$J$86,(H$35-$C$30)+1)))*IF((H$35-$C$30)<Drivers!$C$87,1,Drivers!$C$88*Drivers!$C$89^((H$35-$C$30)-Drivers!$C$87))*$E$30 -> 0 | I60: =$D$30*$C$15*IF((I$35-$C$30)<0,0,IF((I$35-$C$30)>=7,1,INDEX(Drivers!$D$86:$J$86,(I$35-$C$30)+1)))*IF((I$35-$C$30)<Drivers!$C$87,1,Drivers!$C$88*Drivers!$C$89^((I$35-$C$30)-Drivers!$C$87))*$E$30 -> 0 | J60: =$D$30*$C$15*IF((J$35-$C$30)<0,0,IF((J$35-$C$30)>=7,1,INDEX(Drivers!$D$86:$J$86,(J$35-$C$30)+1)))*IF((J$35-$C$30)<Drivers!$C$87,1,Drivers!$C$88*Drivers!$C$89^((J$35-$C$30)-Drivers!$C$87))*$E$30 -> 0.003072 | ... U60: =$D$30*$C$15*IF((U$35-$C$30)<0,0,IF((U$35-$C$30)>=7,1,INDEX(Drivers!$D$86:$J$86,(U$35-$C$30)+1)))*IF((U$35-$C$30)<Drivers!$C$87,1,Drivers!$C$88*Drivers!$C$89^((U$35-$C$30)-Drivers!$C$87))*$E$30 -> 0.0384
A61: 1L advanced melanoma (INTerpath-012) | B61: $B | C61: =$D$31*$C$15*IF((C$35-$C$31)<0,0,IF((C$35-$C$31)>=7,1,INDEX(Drivers!$D$86:$J$86,(C$35-$C$31)+1)))*IF((C$35-$C$31)<Drivers!$C$87,1,Drivers!$C$88*Drivers!$C$89^((C$35-$C$31)-Drivers!$C$87))*$E$31 -> 0 | D61: =$D$31*$C$15*IF((D$35-$C$31)<0,0,IF((D$35-$C$31)>=7,1,INDEX(Drivers!$D$86:$J$86,(D$35-$C$31)+1)))*IF((D$35-$C$31)<Drivers!$C$87,1,Drivers!$C$88*Drivers!$C$89^((D$35-$C$31)-Drivers!$C$87))*$E$31 -> 0 | E61: =$D$31*$C$15*IF((E$35-$C$31)<0,0,IF((E$35-$C$31)>=7,1,INDEX(Drivers!$D$86:$J$86,(E$35-$C$31)+1)))*IF((E$35-$C$31)<Drivers!$C$87,1,Drivers!$C$88*Drivers!$C$89^((E$35-$C$31)-Drivers!$C$87))*$E$31 -> 0 | F61: =$D$31*$C$15*IF((F$35-$C$31)<0,0,IF((F$35-$C$31)>=7,1,INDEX(Drivers!$D$86:$J$86,(F$35-$C$31)+1)))*IF((F$35-$C$31)<Drivers!$C$87,1,Drivers!$C$88*Drivers!$C$89^((F$35-$C$31)-Drivers!$C$87))*$E$31 -> 0 | G61: =$D$31*$C$15*IF((G$35-$C$31)<0,0,IF((G$35-$C$31)>=7,1,INDEX(Drivers!$D$86:$J$86,(G$35-$C$31)+1)))*IF((G$35-$C$31)<Drivers!$C$87,1,Drivers!$C$88*Drivers!$C$89^((G$35-$C$31)-Drivers!$C$87))*$E$31 -> 0.0032768 | H61: =$D$31*$C$15*IF((H$35-$C$31)<0,0,IF((H$35-$C$31)>=7,1,INDEX(Drivers!$D$86:$J$86,(H$35-$C$31)+1)))*IF((H$35-$C$31)<Drivers!$C$87,1,Drivers!$C$88*Drivers!$C$89^((H$35-$C$31)-Drivers!$C$87))*$E$31 -> 0.01024 | I61: =$D$31*$C$15*IF((I$35-$C$31)<0,0,IF((I$35-$C$31)>=7,1,INDEX(Drivers!$D$86:$J$86,(I$35-$C$31)+1)))*IF((I$35-$C$31)<Drivers!$C$87,1,Drivers!$C$88*Drivers!$C$89^((I$35-$C$31)-Drivers!$C$87))*$E$31 -> 0.018432 | J61: =$D$31*$C$15*IF((J$35-$C$31)<0,0,IF((J$35-$C$31)>=7,1,INDEX(Drivers!$D$86:$J$86,(J$35-$C$31)+1)))*IF((J$35-$C$31)<Drivers!$C$87,1,Drivers!$C$88*Drivers!$C$89^((J$35-$C$31)-Drivers!$C$87))*$E$31 -> 0.026624 | ... U61: =$D$31*$C$15*IF((U$35-$C$31)<0,0,IF((U$35-$C$31)>=7,1,INDEX(Drivers!$D$86:$J$86,(U$35-$C$31)+1)))*IF((U$35-$C$31)<Drivers!$C$87,1,Drivers!$C$88*Drivers!$C$89^((U$35-$C$31)-Drivers!$C$87))*$E$31 -> 0.030831411
A62: 1L metastatic squamous NSCLC (INTerpath-013) | B62: $B | C62: =$D$32*$C$15*IF((C$35-$C$32)<0,0,IF((C$35-$C$32)>=7,1,INDEX(Drivers!$D$86:$J$86,(C$35-$C$32)+1)))*IF((C$35-$C$32)<Drivers!$C$87,1,Drivers!$C$88*Drivers!$C$89^((C$35-$C$32)-Drivers!$C$87))*$E$32 -> 0 | D62: =$D$32*$C$15*IF((D$35-$C$32)<0,0,IF((D$35-$C$32)>=7,1,INDEX(Drivers!$D$86:$J$86,(D$35-$C$32)+1)))*IF((D$35-$C$32)<Drivers!$C$87,1,Drivers!$C$88*Drivers!$C$89^((D$35-$C$32)-Drivers!$C$87))*$E$32 -> 0 | E62: =$D$32*$C$15*IF((E$35-$C$32)<0,0,IF((E$35-$C$32)>=7,1,INDEX(Drivers!$D$86:$J$86,(E$35-$C$32)+1)))*IF((E$35-$C$32)<Drivers!$C$87,1,Drivers!$C$88*Drivers!$C$89^((E$35-$C$32)-Drivers!$C$87))*$E$32 -> 0 | F62: =$D$32*$C$15*IF((F$35-$C$32)<0,0,IF((F$35-$C$32)>=7,1,INDEX(Drivers!$D$86:$J$86,(F$35-$C$32)+1)))*IF((F$35-$C$32)<Drivers!$C$87,1,Drivers!$C$88*Drivers!$C$89^((F$35-$C$32)-Drivers!$C$87))*$E$32 -> 0 | G62: =$D$32*$C$15*IF((G$35-$C$32)<0,0,IF((G$35-$C$32)>=7,1,INDEX(Drivers!$D$86:$J$86,(G$35-$C$32)+1)))*IF((G$35-$C$32)<Drivers!$C$87,1,Drivers!$C$88*Drivers!$C$89^((G$35-$C$32)-Drivers!$C$87))*$E$32 -> 0 | H62: =$D$32*$C$15*IF((H$35-$C$32)<0,0,IF((H$35-$C$32)>=7,1,INDEX(Drivers!$D$86:$J$86,(H$35-$C$32)+1)))*IF((H$35-$C$32)<Drivers!$C$87,1,Drivers!$C$88*Drivers!$C$89^((H$35-$C$32)-Drivers!$C$87))*$E$32 -> 0.0036864 | I62: =$D$32*$C$15*IF((I$35-$C$32)<0,0,IF((I$35-$C$32)>=7,1,INDEX(Drivers!$D$86:$J$86,(I$35-$C$32)+1)))*IF((I$35-$C$32)<Drivers!$C$87,1,Drivers!$C$88*Drivers!$C$89^((I$35-$C$32)-Drivers!$C$87))*$E$32 -> 0.01152 | J62: =$D$32*$C$15*IF((J$35-$C$32)<0,0,IF((J$35-$C$32)>=7,1,INDEX(Drivers!$D$86:$J$86,(J$35-$C$32)+1)))*IF((J$35-$C$32)<Drivers!$C$87,1,Drivers!$C$88*Drivers!$C$89^((J$35-$C$32)-Drivers!$C$87))*$E$32 -> 0.020736 | ... U62: =$D$32*$C$15*IF((U$35-$C$32)<0,0,IF((U$35-$C$32)>=7,1,INDEX(Drivers!$D$86:$J$86,(U$35-$C$32)+1)))*IF((U$35-$C$32)<Drivers!$C$87,1,Drivers!$C$88*Drivers!$C$89^((U$35-$C$32)-Drivers!$C$87))*$E$32 -> 0.03575808
A63: Other solid tumours - future INT indications (pr | B63: $B | C63: =$D$33*$C$15*IF((C$35-$C$33)<0,0,IF((C$35-$C$33)>=7,1,INDEX(Drivers!$D$86:$J$86,(C$35-$C$33)+1)))*IF((C$35-$C$33)<Drivers!$C$87,1,Drivers!$C$88*Drivers!$C$89^((C$35-$C$33)-Drivers!$C$87))*$E$33 -> 0 | D63: =$D$33*$C$15*IF((D$35-$C$33)<0,0,IF((D$35-$C$33)>=7,1,INDEX(Drivers!$D$86:$J$86,(D$35-$C$33)+1)))*IF((D$35-$C$33)<Drivers!$C$87,1,Drivers!$C$88*Drivers!$C$89^((D$35-$C$33)-Drivers!$C$87))*$E$33 -> 0 | E63: =$D$33*$C$15*IF((E$35-$C$33)<0,0,IF((E$35-$C$33)>=7,1,INDEX(Drivers!$D$86:$J$86,(E$35-$C$33)+1)))*IF((E$35-$C$33)<Drivers!$C$87,1,Drivers!$C$88*Drivers!$C$89^((E$35-$C$33)-Drivers!$C$87))*$E$33 -> 0 | F63: =$D$33*$C$15*IF((F$35-$C$33)<0,0,IF((F$35-$C$33)>=7,1,INDEX(Drivers!$D$86:$J$86,(F$35-$C$33)+1)))*IF((F$35-$C$33)<Drivers!$C$87,1,Drivers!$C$88*Drivers!$C$89^((F$35-$C$33)-Drivers!$C$87))*$E$33 -> 0 | G63: =$D$33*$C$15*IF((G$35-$C$33)<0,0,IF((G$35-$C$33)>=7,1,INDEX(Drivers!$D$86:$J$86,(G$35-$C$33)+1)))*IF((G$35-$C$33)<Drivers!$C$87,1,Drivers!$C$88*Drivers!$C$89^((G$35-$C$33)-Drivers!$C$87))*$E$33 -> 0 | H63: =$D$33*$C$15*IF((H$35-$C$33)<0,0,IF((H$35-$C$33)>=7,1,INDEX(Drivers!$D$86:$J$86,(H$35-$C$33)+1)))*IF((H$35-$C$33)<Drivers!$C$87,1,Drivers!$C$88*Drivers!$C$89^((H$35-$C$33)-Drivers!$C$87))*$E$33 -> 0 | I63: =$D$33*$C$15*IF((I$35-$C$33)<0,0,IF((I$35-$C$33)>=7,1,INDEX(Drivers!$D$86:$J$86,(I$35-$C$33)+1)))*IF((I$35-$C$33)<Drivers!$C$87,1,Drivers!$C$88*Drivers!$C$89^((I$35-$C$33)-Drivers!$C$87))*$E$33 -> 0 | J63: =$D$33*$C$15*IF((J$35-$C$33)<0,0,IF((J$35-$C$33)>=7,1,INDEX(Drivers!$D$86:$J$86,(J$35-$C$33)+1)))*IF((J$35-$C$33)<Drivers!$C$87,1,Drivers!$C$88*Drivers!$C$89^((J$35-$C$33)-Drivers!$C$87))*$E$33 -> 0 | ... U63: =$D$33*$C$15*IF((U$35-$C$33)<0,0,IF((U$35-$C$33)>=7,1,INDEX(Drivers!$D$86:$J$86,(U$35-$C$33)+1)))*IF((U$35-$C$33)<Drivers!$C$87,1,Drivers!$C$88*Drivers!$C$89^((U$35-$C$33)-Drivers!$C$87))*$E$33 -> 0.1536
A64: INT global sales (risk-adjusted) | B64: $B | C64: =SUM(C54:C63) -> 0 | D64: =SUM(D54:D63) -> 0 | E64: =SUM(E54:E63) -> 0 | F64: =SUM(F54:F63) -> 0 | G64: =SUM(G54:G63) -> 0.0462848 | H64: =SUM(H54:H63) -> 0.1483264 | I64: =SUM(I54:I63) -> 0.275968 | J64: =SUM(J54:J63) -> 0.42496 | ... U64: =SUM(U54:U63) -> 1.0818118
A65: Profit-pool margin | B65: % | C65: =IF((C$35-$C$24)<0,0,Drivers!$C$90+($C$16-Drivers!$C$90)*MIN((C$35-$C$24)/Drivers!$C$91,1)) -> 0.2 | D65: =IF((D$35-$C$24)<0,0,Drivers!$C$90+($C$16-Drivers!$C$90)*MIN((D$35-$C$24)/Drivers!$C$91,1)) -> 0.27 | E65: =IF((E$35-$C$24)<0,0,Drivers!$C$90+($C$16-Drivers!$C$90)*MIN((E$35-$C$24)/Drivers!$C$91,1)) -> 0.34 | F65: =IF((F$35-$C$24)<0,0,Drivers!$C$90+($C$16-Drivers!$C$90)*MIN((F$35-$C$24)/Drivers!$C$91,1)) -> 0.41 | G65: =IF((G$35-$C$24)<0,0,Drivers!$C$90+($C$16-Drivers!$C$90)*MIN((G$35-$C$24)/Drivers!$C$91,1)) -> 0.48 | H65: =IF((H$35-$C$24)<0,0,Drivers!$C$90+($C$16-Drivers!$C$90)*MIN((H$35-$C$24)/Drivers!$C$91,1)) -> 0.55 | I65: =IF((I$35-$C$24)<0,0,Drivers!$C$90+($C$16-Drivers!$C$90)*MIN((I$35-$C$24)/Drivers!$C$91,1)) -> 0.55 | J65: =IF((J$35-$C$24)<0,0,Drivers!$C$90+($C$16-Drivers!$C$90)*MIN((J$35-$C$24)/Drivers!$C$91,1)) -> 0.55 | ... U65: =IF((U$35-$C$24)<0,0,Drivers!$C$90+($C$16-Drivers!$C$90)*MIN((U$35-$C$24)/Drivers!$C$91,1)) -> 0.55
A66: Moderna 50% share of profit pool | B66: $B | C66: =Drivers!$C$85*C64*C65 -> 0 | D66: =Drivers!$C$85*D64*D65 -> 0 | E66: =Drivers!$C$85*E64*E65 -> 0 | F66: =Drivers!$C$85*F64*F65 -> 0 | G66: =Drivers!$C$85*G64*G65 -> 0.011108352 | H66: =Drivers!$C$85*H64*H65 -> 0.04078976 | I66: =Drivers!$C$85*I64*I65 -> 0.0758912 | J66: =Drivers!$C$85*J64*J65 -> 0.116864 | ... U66: =Drivers!$C$85*U64*U65 -> 0.29749823
A67: Moderna share of INT development | B67: $B | C67: =Drivers!$D$92 -> 0.4 | D67: =Drivers!$E$92 -> 0.4 | E67: =Drivers!$F$92 -> 0.4 | F67: =Drivers!$G$92 -> 0.4 | G67: =Drivers!$H$92 -> 0.35 | H67: =Drivers!$I$92 -> 0.35 | I67: =Drivers!$J$92 -> 0.3 | J67: =Drivers!$K$92 -> 0.25 | K67: =Drivers!$C$93 -> 0.2 | L67: =Drivers!$C$93 -> 0.2 | M67: =Drivers!$C$93 -> 0.2 | N67: =Drivers!$C$93 -> 0.2 | O67: =Drivers!$C$93 -> 0.2 | P67: =Drivers!$C$93 -> 0.2 | Q67: =Drivers!$C$93 -> 0.2 | R67: =Drivers!$C$93 -> 0.2 | ... U67: =Drivers!$C$93 -> 0.2
A68: INT contribution | B68: $B | C68: =C66-C67 -> -0.4 | D68: =D66-D67 -> -0.4 | E68: =E66-E67 -> -0.4 | F68: =F66-F67 -> -0.4 | G68: =G66-G67 -> -0.33889165 | H68: =H66-H67 -> -0.30921024 | I68: =I66-I67 -> -0.2241088 | J68: =J66-J67 -> -0.133136 | ... U68: =U66-U67 -> 0.097498235
A69: OTHER PIPELINE
A70: mRNA-4359 sales (risk-adjusted) | B70: $B | C70: =Drivers!$C$107*Drivers!$C$108*IF((C$35-Drivers!$C$109)<0,0,IF((C$35-Drivers!$C$109)>=7,1,INDEX(Drivers!$D$86:$J$86,(C$35-Drivers!$C$109)+1)))*IF((C$35-Drivers!$C$109)<Drivers!$C$87,1,Drivers!$C$88*Drivers!$C$89^((C$35-Drivers!$C$109)-Drivers!$C$87)) -> 0 | D70: =Drivers!$C$107*Drivers!$C$108*IF((D$35-Drivers!$C$109)<0,0,IF((D$35-Drivers!$C$109)>=7,1,INDEX(Drivers!$D$86:$J$86,(D$35-Drivers!$C$109)+1)))*IF((D$35-Drivers!$C$109)<Drivers!$C$87,1,Drivers!$C$88*Drivers!$C$89^((D$35-Drivers!$C$109)-Drivers!$C$87)) -> 0 | E70: =Drivers!$C$107*Drivers!$C$108*IF((E$35-Drivers!$C$109)<0,0,IF((E$35-Drivers!$C$109)>=7,1,INDEX(Drivers!$D$86:$J$86,(E$35-Drivers!$C$109)+1)))*IF((E$35-Drivers!$C$109)<Drivers!$C$87,1,Drivers!$C$88*Drivers!$C$89^((E$35-Drivers!$C$109)-Drivers!$C$87)) -> 0 | F70: =Drivers!$C$107*Drivers!$C$108*IF((F$35-Drivers!$C$109)<0,0,IF((F$35-Drivers!$C$109)>=7,1,INDEX(Drivers!$D$86:$J$86,(F$35-Drivers!$C$109)+1)))*IF((F$35-Drivers!$C$109)<Drivers!$C$87,1,Drivers!$C$88*Drivers!$C$89^((F$35-Drivers!$C$109)-Drivers!$C$87)) -> 0 | G70: =Drivers!$C$107*Drivers!$C$108*IF((G$35-Drivers!$C$109)<0,0,IF((G$35-Drivers!$C$109)>=7,1,INDEX(Drivers!$D$86:$J$86,(G$35-Drivers!$C$109)+1)))*IF((G$35-Drivers!$C$109)<Drivers!$C$87,1,Drivers!$C$88*Drivers!$C$89^((G$35-Drivers!$C$109)-Drivers!$C$87)) -> 0.016 | H70: =Drivers!$C$107*Drivers!$C$108*IF((H$35-Drivers!$C$109)<0,0,IF((H$35-Drivers!$C$109)>=7,1,INDEX(Drivers!$D$86:$J$86,(H$35-Drivers!$C$109)+1)))*IF((H$35-Drivers!$C$109)<Drivers!$C$87,1,Drivers!$C$88*Drivers!$C$89^((H$35-Drivers!$C$109)-Drivers!$C$87)) -> 0.05 | I70: =Drivers!$C$107*Drivers!$C$108*IF((I$35-Drivers!$C$109)<0,0,IF((I$35-Drivers!$C$109)>=7,1,INDEX(Drivers!$D$86:$J$86,(I$35-Drivers!$C$109)+1)))*IF((I$35-Drivers!$C$109)<Drivers!$C$87,1,Drivers!$C$88*Drivers!$C$89^((I$35-Drivers!$C$109)-Drivers!$C$87)) -> 0.09 | J70: =Drivers!$C$107*Drivers!$C$108*IF((J$35-Drivers!$C$109)<0,0,IF((J$35-Drivers!$C$109)>=7,1,INDEX(Drivers!$D$86:$J$86,(J$35-Drivers!$C$109)+1)))*IF((J$35-Drivers!$C$109)<Drivers!$C$87,1,Drivers!$C$88*Drivers!$C$89^((J$35-Drivers!$C$109)-Drivers!$C$87)) -> 0.13 | ... U70: =Drivers!$C$107*Drivers!$C$108*IF((U$35-Drivers!$C$109)<0,0,IF((U$35-Drivers!$C$109)>=7,1,INDEX(Drivers!$D$86:$J$86,(U$35-Drivers!$C$109)+1)))*IF((U$35-Drivers!$C$109)<Drivers!$C$87,1,Drivers!$C$88*Drivers!$C$89^((U$35-Drivers!$C$109)-Drivers!$C$87)) -> 0.150544
A71: mRNA-4359 development | B71: $B | C71: =Drivers!$D$111 -> 0.12 | D71: =Drivers!$E$111+Drivers!$C$112*Drivers!$C$113/3 -> 0.19083333 | E71: =Drivers!$F$111+Drivers!$C$112*Drivers!$C$113/3 -> 0.19083333 | F71: =Drivers!$G$111+Drivers!$C$112*Drivers!$C$113/3 -> 0.14083333 | G71: =Drivers!$H$111 -> 0.08 | H71: =0 -> 0 | I71: =0 -> 0 | J71: =0 -> 0 | K71: =0 -> 0 | L71: =0 -> 0 | M71: =0 -> 0 | N71: =0 -> 0 | O71: =0 -> 0 | ... U71: =0 -> 0
A72: mRNA-4359 contribution | B72: $B | C72: =C70*IF((C$35-Drivers!$C$109)<0,0,0.1+(Drivers!$C$110-0.1)*MIN((C$35-Drivers!$C$109)/5,1))-C71 -> -0.12 | D72: =D70*IF((D$35-Drivers!$C$109)<0,0,0.1+(Drivers!$C$110-0.1)*MIN((D$35-Drivers!$C$109)/5,1))-D71 -> -0.19083333 | E72: =E70*IF((E$35-Drivers!$C$109)<0,0,0.1+(Drivers!$C$110-0.1)*MIN((E$35-Drivers!$C$109)/5,1))-E71 -> -0.19083333 | F72: =F70*IF((F$35-Drivers!$C$109)<0,0,0.1+(Drivers!$C$110-0.1)*MIN((F$35-Drivers!$C$109)/5,1))-F71 -> -0.14083333 | G72: =G70*IF((G$35-Drivers!$C$109)<0,0,0.1+(Drivers!$C$110-0.1)*MIN((G$35-Drivers!$C$109)/5,1))-G71 -> -0.0784 | H72: =H70*IF((H$35-Drivers!$C$109)<0,0,0.1+(Drivers!$C$110-0.1)*MIN((H$35-Drivers!$C$109)/5,1))-H71 -> 0.0085 | I72: =I70*IF((I$35-Drivers!$C$109)<0,0,0.1+(Drivers!$C$110-0.1)*MIN((I$35-Drivers!$C$109)/5,1))-I71 -> 0.0216 | J72: =J70*IF((J$35-Drivers!$C$109)<0,0,0.1+(Drivers!$C$110-0.1)*MIN((J$35-Drivers!$C$109)/5,1))-J71 -> 0.0403 | ... U72: =U70*IF((U$35-Drivers!$C$109)<0,0,0.1+(Drivers!$C$110-0.1)*MIN((U$35-Drivers!$C$109)/5,1))-U71 -> 0.0677448
A73: PA sales (Recordati, risk-adjusted) | B73: $B | C73: =Drivers!$C$114*Drivers!$C$115*IF((C$35-Drivers!$C$116)<0,0,MIN(((C$35-Drivers!$C$116)+1)/5,1)) -> 0 | D73: =Drivers!$C$114*Drivers!$C$115*IF((D$35-Drivers!$C$116)<0,0,MIN(((D$35-Drivers!$C$116)+1)/5,1)) -> 0.044 | E73: =Drivers!$C$114*Drivers!$C$115*IF((E$35-Drivers!$C$116)<0,0,MIN(((E$35-Drivers!$C$116)+1)/5,1)) -> 0.088 | F73: =Drivers!$C$114*Drivers!$C$115*IF((F$35-Drivers!$C$116)<0,0,MIN(((F$35-Drivers!$C$116)+1)/5,1)) -> 0.132 | G73: =Drivers!$C$114*Drivers!$C$115*IF((G$35-Drivers!$C$116)<0,0,MIN(((G$35-Drivers!$C$116)+1)/5,1)) -> 0.176 | H73: =Drivers!$C$114*Drivers!$C$115*IF((H$35-Drivers!$C$116)<0,0,MIN(((H$35-Drivers!$C$116)+1)/5,1)) -> 0.22 | I73: =Drivers!$C$114*Drivers!$C$115*IF((I$35-Drivers!$C$116)<0,0,MIN(((I$35-Drivers!$C$116)+1)/5,1)) -> 0.22 | J73: =Drivers!$C$114*Drivers!$C$115*IF((J$35-Drivers!$C$116)<0,0,MIN(((J$35-Drivers!$C$116)+1)/5,1)) -> 0.22 | ... U73: =Drivers!$C$114*Drivers!$C$115*IF((U$35-Drivers!$C$116)<0,0,MIN(((U$35-Drivers!$C$116)+1)/5,1)) -> 0.22
A74: MMA sales (risk-adjusted) | B74: $B | C74: =Drivers!$C$120*Drivers!$C$121*IF((C$35-Drivers!$C$122)<0,0,MIN(((C$35-Drivers!$C$122)+1)/5,1)) -> 0 | D74: =Drivers!$C$120*Drivers!$C$121*IF((D$35-Drivers!$C$122)<0,0,MIN(((D$35-Drivers!$C$122)+1)/5,1)) -> 0 | E74: =Drivers!$C$120*Drivers!$C$121*IF((E$35-Drivers!$C$122)<0,0,MIN(((E$35-Drivers!$C$122)+1)/5,1)) -> 0 | F74: =Drivers!$C$120*Drivers!$C$121*IF((F$35-Drivers!$C$122)<0,0,MIN(((F$35-Drivers!$C$122)+1)/5,1)) -> 0 | G74: =Drivers!$C$120*Drivers!$C$121*IF((G$35-Drivers!$C$122)<0,0,MIN(((G$35-Drivers!$C$122)+1)/5,1)) -> 0.016 | H74: =Drivers!$C$120*Drivers!$C$121*IF((H$35-Drivers!$C$122)<0,0,MIN(((H$35-Drivers!$C$122)+1)/5,1)) -> 0.032 | I74: =Drivers!$C$120*Drivers!$C$121*IF((I$35-Drivers!$C$122)<0,0,MIN(((I$35-Drivers!$C$122)+1)/5,1)) -> 0.048 | J74: =Drivers!$C$120*Drivers!$C$121*IF((J$35-Drivers!$C$122)<0,0,MIN(((J$35-Drivers!$C$122)+1)/5,1)) -> 0.064 | ... U74: =Drivers!$C$120*Drivers!$C$121*IF((U$35-Drivers!$C$122)<0,0,MIN(((U$35-Drivers!$C$122)+1)/5,1)) -> 0.08
A75: CF royalty (risk-adjusted) | B75: $B | C75: =Drivers!$C$125*Drivers!$C$126*IF((C$35-Drivers!$C$127)<0,0,MIN(((C$35-Drivers!$C$127)+1)/5,1))*Drivers!$C$128 -> 0 | D75: =Drivers!$C$125*Drivers!$C$126*IF((D$35-Drivers!$C$127)<0,0,MIN(((D$35-Drivers!$C$127)+1)/5,1))*Drivers!$C$128 -> 0 | E75: =Drivers!$C$125*Drivers!$C$126*IF((E$35-Drivers!$C$127)<0,0,MIN(((E$35-Drivers!$C$127)+1)/5,1))*Drivers!$C$128 -> 0 | F75: =Drivers!$C$125*Drivers!$C$126*IF((F$35-Drivers!$C$127)<0,0,MIN(((F$35-Drivers!$C$127)+1)/5,1))*Drivers!$C$128 -> 0 | G75: =Drivers!$C$125*Drivers!$C$126*IF((G$35-Drivers!$C$127)<0,0,MIN(((G$35-Drivers!$C$127)+1)/5,1))*Drivers!$C$128 -> 0.0016 | H75: =Drivers!$C$125*Drivers!$C$126*IF((H$35-Drivers!$C$127)<0,0,MIN(((H$35-Drivers!$C$127)+1)/5,1))*Drivers!$C$128 -> 0.0032 | I75: =Drivers!$C$125*Drivers!$C$126*IF((I$35-Drivers!$C$127)<0,0,MIN(((I$35-Drivers!$C$127)+1)/5,1))*Drivers!$C$128 -> 0.0048 | J75: =Drivers!$C$125*Drivers!$C$126*IF((J$35-Drivers!$C$127)<0,0,MIN(((J$35-Drivers!$C$127)+1)/5,1))*Drivers!$C$128 -> 0.0064 | ... U75: =Drivers!$C$125*Drivers!$C$126*IF((U$35-Drivers!$C$127)<0,0,MIN(((U$35-Drivers!$C$127)+1)/5,1))*Drivers!$C$128 -> 0.008
A76: Rare disease & royalties contribution | B76: $B | C76: =C73*Drivers!$C$117+Drivers!$C$114*(Drivers!$C$118*(C$35=Drivers!$C$116)+Drivers!$C$119*(C$35=Drivers!$C$116+3))+C74*Drivers!$C$123-Drivers!$C$124*Drivers!$C$114*AND(C$35>=2027,C$35<=2030)+C75 -> -0.044 | D76: =D73*Drivers!$C$117+Drivers!$C$114*(Drivers!$C$118*(D$35=Drivers!$C$116)+Drivers!$C$119*(D$35=Drivers!$C$116+3))+D74*Drivers!$C$123-Drivers!$C$124*Drivers!$C$114*AND(D$35>=2027,D$35<=2030)+D75 -> 0.0231 | E76: =E73*Drivers!$C$117+Drivers!$C$114*(Drivers!$C$118*(E$35=Drivers!$C$116)+Drivers!$C$119*(E$35=Drivers!$C$116+3))+E74*Drivers!$C$123-Drivers!$C$124*Drivers!$C$114*AND(E$35>=2027,E$35<=2030)+E75 -> -0.0308 | F76: =F73*Drivers!$C$117+Drivers!$C$114*(Drivers!$C$118*(F$35=Drivers!$C$116)+Drivers!$C$119*(F$35=Drivers!$C$116+3))+F74*Drivers!$C$123-Drivers!$C$124*Drivers!$C$114*AND(F$35>=2027,F$35<=2030)+F75 -> -0.0242 | G76: =G73*Drivers!$C$117+Drivers!$C$114*(Drivers!$C$118*(G$35=Drivers!$C$116)+Drivers!$C$119*(G$35=Drivers!$C$116+3))+G74*Drivers!$C$123-Drivers!$C$124*Drivers!$C$114*AND(G$35>=2027,G$35<=2030)+G75 -> 0.091 | H76: =H73*Drivers!$C$117+Drivers!$C$114*(Drivers!$C$118*(H$35=Drivers!$C$116)+Drivers!$C$119*(H$35=Drivers!$C$116+3))+H74*Drivers!$C$123-Drivers!$C$124*Drivers!$C$114*AND(H$35>=2027,H$35<=2030)+H75 -> 0.0522 | I76: =I73*Drivers!$C$117+Drivers!$C$114*(Drivers!$C$118*(I$35=Drivers!$C$116)+Drivers!$C$119*(I$35=Drivers!$C$116+3))+I74*Drivers!$C$123-Drivers!$C$124*Drivers!$C$114*AND(I$35>=2027,I$35<=2030)+I75 -> 0.0618 | J76: =J73*Drivers!$C$117+Drivers!$C$114*(Drivers!$C$118*(J$35=Drivers!$C$116)+Drivers!$C$119*(J$35=Drivers!$C$116+3))+J74*Drivers!$C$123-Drivers!$C$124*Drivers!$C$114*AND(J$35>=2027,J$35<=2030)+J75 -> 0.0714 | ... U76: =U73*Drivers!$C$117+Drivers!$C$114*(Drivers!$C$118*(U$35=Drivers!$C$116)+Drivers!$C$119*(U$35=Drivers!$C$116+3))+U74*Drivers!$C$123-Drivers!$C$124*Drivers!$C$114*AND(U$35>=2027,U$35<=2030)+U75 -> 0.081
A77: CORPORATE, TAX & FREE CASH FLOW
A78: Corporate G&A | B78: $B | C78: =Drivers!$C$129*(1+Drivers!$C$130)^C$36 -> 0.42 | D78: =Drivers!$C$129*(1+Drivers!$C$130)^D$36 -> 0.4284 | E78: =Drivers!$C$129*(1+Drivers!$C$130)^E$36 -> 0.436968 | F78: =Drivers!$C$129*(1+Drivers!$C$130)^F$36 -> 0.44570736 | G78: =Drivers!$C$129*(1+Drivers!$C$130)^G$36 -> 0.45462151 | H78: =Drivers!$C$129*(1+Drivers!$C$130)^H$36 -> 0.46371394 | I78: =Drivers!$C$129*(1+Drivers!$C$130)^I$36 -> 0.47298822 | J78: =Drivers!$C$129*(1+Drivers!$C$130)^J$36 -> 0.48244798 | ... U78: =Drivers!$C$129*(1+Drivers!$C$130)^U$36 -> 0.59986342
A79: Unallocated R&D (before scenario multiplier) | B79: $B | C79: =Drivers!$D$131 -> 1.2 | D79: =Drivers!$E$131 -> 1.15 | E79: =Drivers!$F$131 -> 1.12 | F79: =Drivers!$G$131 -> 1.1 | G79: =Drivers!$H$131 -> 1.1 | H79: =Drivers!$I$131 -> 1.1 | I79: =H79*(1+Drivers!$C$132) -> 1.122 | J79: =I79*(1+Drivers!$C$132) -> 1.14444 | K79: =J79*(1+Drivers!$C$132) -> 1.1673288 | L79: =K79*(1+Drivers!$C$132) -> 1.1906754 | M79: =L79*(1+Drivers!$C$132) -> 1.2144889 | N79: =M79*(1+Drivers!$C$132) -> 1.2387787 | O79: =N79*(1+Drivers!$C$132) -> 1.2635542 | P79: =O79*(1+Drivers!$C$132) -> 1.2888253 | ... U79: =T79*(1+Drivers!$C$132) -> 1.4229673
A80: Unallocated R&D | B80: $B | C80: =C79*$C$17 -> 0.72 | D80: =D79*$C$17 -> 0.69 | E80: =E79*$C$17 -> 0.672 | F80: =F79*$C$17 -> 0.66 | G80: =G79*$C$17 -> 0.66 | H80: =H79*$C$17 -> 0.66 | I80: =I79*$C$17 -> 0.6732 | J80: =J79*$C$17 -> 0.686664 | ... U80: =U79*$C$17 -> 0.85378038
A81: Attributable revenue (resp + 50% INT + other) | B81: $B | C81: =C44+Drivers!$C$85*C64+C70+C74+C73*Drivers!$C$117+C75 -> 1.7844 | D81: =D44+Drivers!$C$85*D64+D70+D74+D73*Drivers!$C$117+D75 -> 1.9254 | E81: =E44+Drivers!$C$85*E64+E70+E74+E73*Drivers!$C$117+E75 -> 2.1024 | F81: =F44+Drivers!$C$85*F64+F70+F74+F73*Drivers!$C$117+F75 -> 2.2669 | G81: =G44+Drivers!$C$85*G64+G70+G74+G73*Drivers!$C$117+G75 -> 2.5106424 | H81: =H44+Drivers!$C$85*H64+H70+H74+H73*Drivers!$C$117+H75 -> 2.5958632 | I81: =I44+Drivers!$C$85*I64+I70+I74+I73*Drivers!$C$117+I75 -> 2.733784 | J81: =J44+Drivers!$C$85*J64+J70+J74+J73*Drivers!$C$117+J75 -> 2.84677 | ... U81: =U44+Drivers!$C$85*U64+U70+U74+U73*Drivers!$C$117+U75 -> 3.0267467
A82: Capex | B82: $B | C82: =Drivers!$D$134 -> 0.3 | D82: =Drivers!$E$134 -> 0.25 | E82: =Drivers!$F$134 -> 0.25 | F82: =Drivers!$G$134 -> 0.25 | G82: =Drivers!$H$134 -> 0.25 | H82: =Drivers!$I$134 -> 0.25 | I82: =Drivers!$C$135*I81 -> 0.10935136 | J82: =Drivers!$C$135*J81 -> 0.1138708 | K82: =Drivers!$C$135*K81 -> 0.11879887 | L82: =Drivers!$C$135*L81 -> 0.12263089 | M82: =Drivers!$C$135*M81 -> 0.12583528 | N82: =Drivers!$C$135*N81 -> 0.12747057 | O82: =Drivers!$C$135*O81 -> 0.12855754 | P82: =Drivers!$C$135*P81 -> 0.12897992 | ... U82: =Drivers!$C$135*U81 -> 0.12106987
A83: D&A | B83: $B | C83: =Drivers!$C$136 -> 0.23 | D83: =Drivers!$C$136 -> 0.23 | E83: =Drivers!$C$136 -> 0.23 | F83: =Drivers!$C$136 -> 0.23 | G83: =Drivers!$C$136 -> 0.23 | H83: =Drivers!$C$136 -> 0.23 | I83: =0.8*I82 -> 0.087481088 | J83: =0.8*J82 -> 0.09109664 | K83: =0.8*K82 -> 0.095039098 | L83: =0.8*L82 -> 0.098104709 | M83: =0.8*M82 -> 0.10066822 | N83: =0.8*N82 -> 0.10197646 | O83: =0.8*O82 -> 0.10284603 | P83: =0.8*P82 -> 0.10318393 | ... U83: =0.8*U82 -> 0.096855895
A84: Increase in working capital | B84: $B | C84: =Drivers!$C$82*(C81-Drivers!$C$35) -> -0.02556 | D84: =Drivers!$C$82*(D81-C81) -> 0.0141 | E84: =Drivers!$C$82*(E81-D81) -> 0.0177 | F84: =Drivers!$C$82*(F81-E81) -> 0.01645 | G84: =Drivers!$C$82*(G81-F81) -> 0.02437424 | H84: =Drivers!$C$82*(H81-G81) -> 0.00852208 | I84: =Drivers!$C$82*(I81-H81) -> 0.01379208 | J84: =Drivers!$C$82*(J81-I81) -> 0.0112986 | K84: =Drivers!$C$82*(K81-J81) -> 0.01232018 | ... U84: =Drivers!$C$82*(U81-T81) -> -0.0032365375
A85: EBIT | B85: $B | C85: =C52+C68+C72+C76-C78-C80 -> -1.8040345 | D85: =D52+D68+D72+D76-D78-D80 -> -1.5194503 | E85: =E52+E68+E72+E76-E78-E80 -> -1.3428608 | F85: =F52+F68+F72+F76-F78-F80 -> -1.1029397 | G85: =G52+G68+G72+G76-G78-G80 -> -0.72503566 | H85: =H52+H68+H72+H76-H78-H80 -> -0.62911168 | I85: =I52+I68+I72+I76-I78-I80 -> -0.54126952 | J85: =J52+J68+J72+J76-J78-J80 -> -0.46787258 | ... U85: =U52+U68+U72+U76-U78-U80 -> -0.65492157
A86: NOL pool - opening | B86: $B | C86: =Drivers!$C$32 -> 12.5 | D86: =C89 -> 14.304035 | E86: =D89 -> 15.823485 | F86: =E89 -> 17.166346 | G86: =F89 -> 18.269285 | H86: =G89 -> 18.994321 | I86: =H89 -> 19.623433 | J86: =I89 -> 20.164702 | K86: =J89 -> 20.632575 | ... U86: =T89 -> 24.665511
A87: NOL used | B87: $B | C87: =IF(C85>0,MIN(C86,Drivers!$C$33*C85),0) -> 0 | D87: =IF(D85>0,MIN(D86,Drivers!$C$33*D85),0) -> 0 | E87: =IF(E85>0,MIN(E86,Drivers!$C$33*E85),0) -> 0 | F87: =IF(F85>0,MIN(F86,Drivers!$C$33*F85),0) -> 0 | G87: =IF(G85>0,MIN(G86,Drivers!$C$33*G85),0) -> 0 | H87: =IF(H85>0,MIN(H86,Drivers!$C$33*H85),0) -> 0 | I87: =IF(I85>0,MIN(I86,Drivers!$C$33*I85),0) -> 0 | J87: =IF(J85>0,MIN(J86,Drivers!$C$33*J85),0) -> 0 | ... U87: =IF(U85>0,MIN(U86,Drivers!$C$33*U85),0) -> 0
A88: Cash taxes | B88: $B | C88: =IF(C85>0,Drivers!$C$31*(C85-C87),0) -> 0 | D88: =IF(D85>0,Drivers!$C$31*(D85-D87),0) -> 0 | E88: =IF(E85>0,Drivers!$C$31*(E85-E87),0) -> 0 | F88: =IF(F85>0,Drivers!$C$31*(F85-F87),0) -> 0 | G88: =IF(G85>0,Drivers!$C$31*(G85-G87),0) -> 0 | H88: =IF(H85>0,Drivers!$C$31*(H85-H87),0) -> 0 | I88: =IF(I85>0,Drivers!$C$31*(I85-I87),0) -> 0 | J88: =IF(J85>0,Drivers!$C$31*(J85-J87),0) -> 0 | ... U88: =IF(U85>0,Drivers!$C$31*(U85-U87),0) -> 0
A89: NOL pool - closing | B89: $B | C89: =C86-C87+IF(C85<0,-C85,0) -> 14.304035 | D89: =D86-D87+IF(D85<0,-D85,0) -> 15.823485 | E89: =E86-E87+IF(E85<0,-E85,0) -> 17.166346 | F89: =F86-F87+IF(F85<0,-F85,0) -> 18.269285 | G89: =G86-G87+IF(G85<0,-G85,0) -> 18.994321 | H89: =H86-H87+IF(H85<0,-H85,0) -> 19.623433 | I89: =I86-I87+IF(I85<0,-I85,0) -> 20.164702 | J89: =J86-J87+IF(J85<0,-J85,0) -> 20.632575 | ... U89: =U86-U87+IF(U85<0,-U85,0) -> 25.320433
A90: Free cash flow to firm | B90: $B | C90: =C85-C88-(C82-C83)-C84 -> -1.8484745 | D90: =D85-D88-(D82-D83)-D84 -> -1.5535503 | E90: =E85-E88-(E82-E83)-E84 -> -1.3805608 | F90: =F85-F88-(F82-F83)-F84 -> -1.1393897 | G90: =G85-G88-(G82-G83)-G84 -> -0.7694099 | H90: =H85-H88-(H82-H83)-H84 -> -0.65763376 | I90: =I85-I88-(I82-I83)-I84 -> -0.57693187 | J90: =J85-J88-(J82-J83)-J84 -> -0.50194534 | ... U90: =U85-U88-(U82-U83)-U84 -> -0.675899
A91: Discount period (mid-year, from 9/30/26) | B91: yrs | C91: =0.25+C$36+0.5 -> 0.75 | D91: =0.25+D$36+0.5 -> 1.75 | E91: =0.25+E$36+0.5 -> 2.75 | F91: =0.25+F$36+0.5 -> 3.75 | G91: =0.25+G$36+0.5 -> 4.75 | H91: =0.25+H$36+0.5 -> 5.75 | I91: =0.25+I$36+0.5 -> 6.75 | J91: =0.25+J$36+0.5 -> 7.75 | ... U91: =0.25+U$36+0.5 -> 18.75
A92: Discount factor | B92: x | C92: =(1+$C$19)^(-C91) -> 0.92829219 | D92: =(1+$C$19)^(-D91) -> 0.84061595 | E92: =(1+$C$19)^(-E91) -> 0.76122063 | F92: =(1+$C$19)^(-F91) -> 0.68932413 | G92: =(1+$C$19)^(-G91) -> 0.62421817 | H92: =(1+$C$19)^(-H91) -> 0.56526141 | I92: =(1+$C$19)^(-I91) -> 0.51187305 | J92: =(1+$C$19)^(-J91) -> 0.46352716 | ... U92: =(1+$C$19)^(-U91) -> 0.15563863
A93: PV of FCFF | B93: $B | C93: =C90*C92 -> -1.7159244 | D93: =D90*D92 -> -1.3059392 | E93: =E90*E92 -> -1.0509114 | F93: =F90*F92 -> -0.78540881 | G93: =G90*G92 -> -0.48027964 | H93: =H90*H92 -> -0.37173498 | I93: =I90*I92 -> -0.29531587 | J93: =J90*J92 -> -0.2326653 | ... U93: =U90*U92 -> -0.10519599
A94: R&D creating future pipeline (credit base) | B94: $B | C94: =IF(C$35<=2032,Drivers!$C$133*C80,C80) -> 0.252 | D94: =IF(D$35<=2032,Drivers!$C$133*D80,D80) -> 0.2415 | E94: =IF(E$35<=2032,Drivers!$C$133*E80,E80) -> 0.2352 | F94: =IF(F$35<=2032,Drivers!$C$133*F80,F80) -> 0.231 | G94: =IF(G$35<=2032,Drivers!$C$133*G80,G80) -> 0.231 | H94: =IF(H$35<=2032,Drivers!$C$133*H80,H80) -> 0.231 | I94: =IF(I$35<=2032,Drivers!$C$133*I80,I80) -> 0.6732 | J94: =IF(J$35<=2032,Drivers!$C$133*J80,J80) -> 0.686664 | ... U94: =IF(U$35<=2032,Drivers!$C$133*U80,U80) -> 0.85378038
A96: VALUATION
A97: PV of Q4-2026 stub FCF | C97: =Drivers!$C$34*(1+$C$19)^(-0.125) -> -0.45433056
A98: PV of FCFF 2027-2045 | C98: =SUM(C93:U93) -> -7.5057632
A99: Terminal value at end-2045 | C99: =U90*(1+$C$20)/($C$19-$C$20) -> -5.8542433
A100: PV of terminal value | C100: =$C$99*(1+$C$19)^(-19.25) -> -0.86705097
A101: PV of pipeline-creating R&D (incl. terminal) | C101: =SUMPRODUCT(C94:U94,C92:U92)+U94*(1+$C$20)/($C$19-$C$20)*(1+$C$19)^(-19.25) -> 5.0514499
A102: Unidentified future pipeline (credit) | C102: =$C$18*$C$101*(1-Drivers!$C$31) -> 1.0229186
A103: Enterprise value | C103: =$C$97+$C$98+$C$100+$C$102 -> -7.8042261
...

Sheet M_Bear
A1: M_Bear - scenario model (Melanoma approved 2028 with modest HR (~0.75), price ~$200k US; NSCLC PoS cut; COVID erodes faster; flu/combo half of base.)
A2: Scenario index (1=Failure..5=Blue-sky) | C2: 2
A4: Scenario levers (green = pulled from Drivers)
A5: COVID revenue multiplier | C5: =INDEX(Drivers!$D$39:$H$39,$C$2) -> 0.85
A6: Flu (mFLUSIVA) peak multiplier | C6: =INDEX(Drivers!$D$40:$H$40,$C$2) -> 0.6
A7: Flu+COVID combo peak multiplier | C7: =INDEX(Drivers!$D$41:$H$41,$C$2) -> 0.6
A8: Norovirus PoS | C8: =INDEX(Drivers!$D$42:$H$42,$C$2) -> 0.2
A9: Respiratory gross-margin shift | C9: =INDEX(Drivers!$D$43:$H$43,$C$2) -> -0.02
A10: INT melanoma PoS | C10: =INDEX(Drivers!$D$44:$H$44,$C$2) -> 0.85
A11: INT melanoma peak global sales ($B, before price factor) | C11: =INDEX(Drivers!$D$45:$H$45,$C$2) -> 1.5
A12: INT melanoma launch year | C12: =INDEX(Drivers!$D$46:$H$46,$C$2) -> 2028
A13: INT other-indication PoS multiplier (>=10 => all 100%) | C13: =INDEX(Drivers!$D$47:$H$47,$C$2) -> 0.7
A14: INT other-indication peak multiplier | C14: =INDEX(Drivers!$D$48:$H$48,$C$2) -> 0.8
A15: INT price factor (1.0 = US net ~$300k) | C15: =INDEX(Drivers!$D$49:$H$49,$C$2) -> 0.75
A16: INT mature profit-pool margin | C16: =INDEX(Drivers!$D$50:$H$50,$C$2) -> 0.55
A17: Unallocated R&D multiplier | C17: =INDEX(Drivers!$D$51:$H$51,$C$2) -> 0.85
A18: Future-pipeline credit factor | C18: =INDEX(Drivers!$D$52:$H$52,$C$2) -> 0.5
A19: WACC | C19: =INDEX(Drivers!$D$53:$H$53,$C$2) -> 0.1043
A20: Terminal growth | C20: =INDEX(Drivers!$D$54:$H$54,$C$2) -> -0.01
A21: Other patent litigation (expected cost) | C21: =INDEX(Drivers!$D$55:$H$55,$C$2) -> 0.8
A22: INT indications: scenario-adjusted launch / peak / PoS
A23: Indication | C23: Launch | D23: Peak | E23: PoS
A24: =Drivers!$B$95 -> Adjuvant melanoma IIB-IV (INTerpath-001) | C24: =$C$12 -> 2028 | D24: =$C$11 -> 1.5 | E24: =$C$10 -> 0.85
A25: =Drivers!$B$96 -> Adjuvant NSCLC II-IIIB (INTerpath-002) | C25: =Drivers!$D$96 -> 2031 | D25: =Drivers!$E$96*$C$14 -> 3.2 | E25: =MIN(Drivers!$F$96*$C$13,IF($C$13>=10,1,0.95)) -> 0.315
A26: =Drivers!$B$97 -> Post-neoadjuvant non-pCR NSCLC (INTerpath-009) | C26: =Drivers!$D$97 -> 2034 | D26: =Drivers!$E$97*$C$14 -> 1.2 | E26: =MIN(Drivers!$F$97*$C$13,IF($C$13>=10,1,0.95)) -> 0.28
A27: =Drivers!$B$98 -> Resected stage I NSCLC (INTerpath-014) | C27: =Drivers!$D$98 -> 2035 | D27: =Drivers!$E$98*$C$14 -> 2 | E27: =MIN(Drivers!$F$98*$C$13,IF($C$13>=10,1,0.95)) -> 0.245
A28: =Drivers!$B$99 -> Adjuvant RCC (INTerpath-004) | C28: =Drivers!$D$99 -> 2031 | D28: =Drivers!$E$99*$C$14 -> 0.96 | E28: =MIN(Drivers!$F$99*$C$13,IF($C$13>=10,1,0.95)) -> 0.175
A29: =Drivers!$B$100 -> MIBC adjuvant (INTerpath-005) | C29: =Drivers!$D$100 -> 2033 | D29: =Drivers!$E$100*$C$14 -> 0.8 | E29: =MIN(Drivers!$F$100*$C$13,IF($C$13>=10,1,0.95)) -> 0.14
A30: =Drivers!$B$101 -> NMIBC + BCG (INTerpath-011) | C30: =Drivers!$D$101 -> 2034 | D30: =Drivers!$E$101*$C$14 -> 0.8 | E30: =MIN(Drivers!$F$101*$C$13,IF($C$13>=10,1,0.95)) -> 0.105
A31: =Drivers!$B$102 -> 1L advanced melanoma (INTerpath-012) | C31: =Drivers!$D$102 -> 2031 | D31: =Drivers!$E$102*$C$14 -> 0.64 | E31: =MIN(Drivers!$F$102*$C$13,IF($C$13>=10,1,0.95)) -> 0.14
A32: =Drivers!$B$103 -> 1L metastatic squamous NSCLC (INTerpath-013) | C32: =Drivers!$D$103 -> 2032 | D32: =Drivers!$E$103*$C$14 -> 0.96 | E32: =MIN(Drivers!$F$103*$C$13,IF($C$13>=10,1,0.95)) -> 0.105
A33: =Drivers!$B$104 -> Other solid tumours - future INT indications (pre-Ph2) | C33: =Drivers!$D$104 -> 2035 | D33: =Drivers!$E$104*$C$14 -> 4.8 | E33: =MIN(Drivers!$F$104*$C$13,IF($C$13>=10,1,0.95)) -> 0.07
A35: Year | B35: unit | C35: 2027 | D35: 2028 | E35: 2029 | F35: 2030 | G35: 2031 | H35: 2032 | I35: 2033 | J35: 2034 | K35: 2035 | L35: 2036 | M35: 2037 | N35: 2038 | O35: 2039 | P35: 2040 | Q35: 2041 | R35: 2042 | S35: 2043 | T35: 2044 | U35: 2045
A36: Year index i | C36: 0 | D36: 1 | E36: 2 | F36: 3 | G36: 4 | H36: 5 | I36: 6 | J36: 7 | K36: 8 | L36: 9 | M36: 10 | N36: 11 | O36: 12 | P36: 13 | Q36: 14 | R36: 15 | S36: 16 | T36: 17 | U36: 18
A37: RESPIRATORY FRANCHISE
A38: COVID (Spikevax, mNEXSPIKE, partnerships) | B38: $B | C38: =Drivers!$D$60*$C$5 -> 1.5725 | D38: =Drivers!$E$60*$C$5 -> 1.445 | E38: =Drivers!$F$60*$C$5 -> 1.3175 | F38: =Drivers!$G$60*$C$5 -> 1.2325 | G38: =Drivers!$H$60*$C$5 -> 1.173 | H38: =Drivers!$I$60*$C$5 -> 1.105 | I38: =H38*(1+Drivers!$C$61) -> 1.0829 | J38: =I38*(1+Drivers!$C$61) -> 1.061242 | K38: =J38*(1+Drivers!$C$61) -> 1.0400172 | L38: =K38*(1+Drivers!$C$61) -> 1.0192168 | M38: =L38*(1+Drivers!$C$61) -> 0.99883248 | N38: =M38*(1+Drivers!$C$61) -> 0.97885583 | O38: =N38*(1+Drivers!$C$61) -> 0.95927871 | P38: =O38*(1+Drivers!$C$61) -> 0.94009314 | ... U38: =T38*(1+Drivers!$C$61) -> 0.84976974
A39: Flu (mFLUSIVA) | B39: $B | C39: =Drivers!$C$62*IF((C$35-Drivers!$C$63)<0,0,MIN(((C$35-Drivers!$C$63)+1)/Drivers!$C$64,1))*$C$6 -> 0.096 | D39: =Drivers!$C$62*IF((D$35-Drivers!$C$63)<0,0,MIN(((D$35-Drivers!$C$63)+1)/Drivers!$C$64,1))*$C$6 -> 0.192 | E39: =Drivers!$C$62*IF((E$35-Drivers!$C$63)<0,0,MIN(((E$35-Drivers!$C$63)+1)/Drivers!$C$64,1))*$C$6 -> 0.288 | F39: =Drivers!$C$62*IF((F$35-Drivers!$C$63)<0,0,MIN(((F$35-Drivers!$C$63)+1)/Drivers!$C$64,1))*$C$6 -> 0.384 | G39: =Drivers!$C$62*IF((G$35-Drivers!$C$63)<0,0,MIN(((G$35-Drivers!$C$63)+1)/Drivers!$C$64,1))*$C$6 -> 0.48 | H39: =Drivers!$C$62*IF((H$35-Drivers!$C$63)<0,0,MIN(((H$35-Drivers!$C$63)+1)/Drivers!$C$64,1))*$C$6 -> 0.48 | I39: =Drivers!$C$62*IF((I$35-Drivers!$C$63)<0,0,MIN(((I$35-Drivers!$C$63)+1)/Drivers!$C$64,1))*$C$6 -> 0.48 | J39: =Drivers!$C$62*IF((J$35-Drivers!$C$63)<0,0,MIN(((J$35-Drivers!$C$63)+1)/Drivers!$C$64,1))*$C$6 -> 0.48 | ... U39: =Drivers!$C$62*IF((U$35-Drivers!$C$63)<0,0,MIN(((U$35-Drivers!$C$63)+1)/Drivers!$C$64,1))*$C$6 -> 0.48
A40: Flu+COVID combo (mCOMBRIAX) | B40: $B | C40: =Drivers!$C$65*IF((C$35-Drivers!$C$66)<0,0,MIN(((C$35-Drivers!$C$66)+1)/Drivers!$C$67,1))*$C$7*((1-Drivers!$C$69)+Drivers!$C$69*Drivers!$C$68) -> 0.14028 | D40: =Drivers!$C$65*IF((D$35-Drivers!$C$66)<0,0,MIN(((D$35-Drivers!$C$66)+1)/Drivers!$C$67,1))*$C$7*((1-Drivers!$C$69)+Drivers!$C$69*Drivers!$C$68) -> 0.28056 | E40: =Drivers!$C$65*IF((E$35-Drivers!$C$66)<0,0,MIN(((E$35-Drivers!$C$66)+1)/Drivers!$C$67,1))*$C$7*((1-Drivers!$C$69)+Drivers!$C$69*Drivers!$C$68) -> 0.42084 | F40: =Drivers!$C$65*IF((F$35-Drivers!$C$66)<0,0,MIN(((F$35-Drivers!$C$66)+1)/Drivers!$C$67,1))*$C$7*((1-Drivers!$C$69)+Drivers!$C$69*Drivers!$C$68) -> 0.56112 | G40: =Drivers!$C$65*IF((G$35-Drivers!$C$66)<0,0,MIN(((G$35-Drivers!$C$66)+1)/Drivers!$C$67,1))*$C$7*((1-Drivers!$C$69)+Drivers!$C$69*Drivers!$C$68) -> 0.7014 | H40: =Drivers!$C$65*IF((H$35-Drivers!$C$66)<0,0,MIN(((H$35-Drivers!$C$66)+1)/Drivers!$C$67,1))*$C$7*((1-Drivers!$C$69)+Drivers!$C$69*Drivers!$C$68) -> 0.7014 | I40: =Drivers!$C$65*IF((I$35-Drivers!$C$66)<0,0,MIN(((I$35-Drivers!$C$66)+1)/Drivers!$C$67,1))*$C$7*((1-Drivers!$C$69)+Drivers!$C$69*Drivers!$C$68) -> 0.7014 | J40: =Drivers!$C$65*IF((J$35-Drivers!$C$66)<0,0,MIN(((J$35-Drivers!$C$66)+1)/Drivers!$C$67,1))*$C$7*((1-Drivers!$C$69)+Drivers!$C$69*Drivers!$C$68) -> 0.7014 | ... U40: =Drivers!$C$65*IF((U$35-Drivers!$C$66)<0,0,MIN(((U$35-Drivers!$C$66)+1)/Drivers!$C$67,1))*$C$7*((1-Drivers!$C$69)+Drivers!$C$69*Drivers!$C$68) -> 0.7014
A41: RSV (mRESVIA) | B41: $B | C41: =Drivers!$C$70*MIN((C$35-2026)/3,1) -> 0.05 | D41: =Drivers!$C$70*MIN((D$35-2026)/3,1) -> 0.1 | E41: =Drivers!$C$70*MIN((E$35-2026)/3,1) -> 0.15 | F41: =Drivers!$C$70*MIN((F$35-2026)/3,1) -> 0.15 | G41: =Drivers!$C$70*MIN((G$35-2026)/3,1) -> 0.15 | H41: =Drivers!$C$70*MIN((H$35-2026)/3,1) -> 0.15 | I41: =Drivers!$C$70*MIN((I$35-2026)/3,1) -> 0.15 | J41: =Drivers!$C$70*MIN((J$35-2026)/3,1) -> 0.15 | ... U41: =Drivers!$C$70*MIN((U$35-2026)/3,1) -> 0.15
A42: Norovirus (risk-adjusted) | B42: $B | C42: =$C$8*Drivers!$C$71*IF((C$35-Drivers!$C$72)<0,0,MIN(((C$35-Drivers!$C$72)+1)/Drivers!$C$73,1)) -> 0 | D42: =$C$8*Drivers!$C$71*IF((D$35-Drivers!$C$72)<0,0,MIN(((D$35-Drivers!$C$72)+1)/Drivers!$C$73,1)) -> 0 | E42: =$C$8*Drivers!$C$71*IF((E$35-Drivers!$C$72)<0,0,MIN(((E$35-Drivers!$C$72)+1)/Drivers!$C$73,1)) -> 0.048 | F42: =$C$8*Drivers!$C$71*IF((F$35-Drivers!$C$72)<0,0,MIN(((F$35-Drivers!$C$72)+1)/Drivers!$C$73,1)) -> 0.096 | G42: =$C$8*Drivers!$C$71*IF((G$35-Drivers!$C$72)<0,0,MIN(((G$35-Drivers!$C$72)+1)/Drivers!$C$73,1)) -> 0.144 | H42: =$C$8*Drivers!$C$71*IF((H$35-Drivers!$C$72)<0,0,MIN(((H$35-Drivers!$C$72)+1)/Drivers!$C$73,1)) -> 0.192 | I42: =$C$8*Drivers!$C$71*IF((I$35-Drivers!$C$72)<0,0,MIN(((I$35-Drivers!$C$72)+1)/Drivers!$C$73,1)) -> 0.24 | J42: =$C$8*Drivers!$C$71*IF((J$35-Drivers!$C$72)<0,0,MIN(((J$35-Drivers!$C$72)+1)/Drivers!$C$73,1)) -> 0.24 | ... U42: =$C$8*Drivers!$C$71*IF((U$35-Drivers!$C$72)<0,0,MIN(((U$35-Drivers!$C$72)+1)/Drivers!$C$73,1)) -> 0.24
A43: Other revenue | B43: $B | C43: =Drivers!$C$74 -> 0.15 | D43: =Drivers!$C$74 -> 0.15 | E43: =Drivers!$C$74 -> 0.15 | F43: =Drivers!$C$74 -> 0.15 | G43: =Drivers!$C$74 -> 0.15 | H43: =Drivers!$C$74 -> 0.15 | I43: =Drivers!$C$74 -> 0.15 | J43: =Drivers!$C$74 -> 0.15 | ... U43: =Drivers!$C$74 -> 0.15
A44: Respiratory revenue | B44: $B | C44: =SUM(C38:C43) -> 2.00878 | D44: =SUM(D38:D43) -> 2.16756 | E44: =SUM(E38:E43) -> 2.37434 | F44: =SUM(F38:F43) -> 2.57362 | G44: =SUM(G38:G43) -> 2.7984 | H44: =SUM(H38:H43) -> 2.7784 | I44: =SUM(I38:I43) -> 2.8043 | J44: =SUM(J38:J43) -> 2.782642 | ... U44: =SUM(U38:U43) -> 2.5711697
A45: Gross margin | B45: % | C45: =Drivers!$D$75+$C$9 -> 0.62 | D45: =Drivers!$E$75+$C$9 -> 0.66 | E45: =Drivers!$F$75+$C$9 -> 0.69 | F45: =Drivers!$G$75+$C$9 -> 0.71 | G45: =Drivers!$H$75+$C$9 -> 0.72 | H45: =Drivers!$I$75+$C$9 -> 0.73 | I45: =Drivers!$I$75+$C$9 -> 0.73 | J45: =Drivers!$I$75+$C$9 -> 0.73 | K45: =Drivers!$I$75+$C$9 -> 0.73 | L45: =Drivers!$I$75+$C$9 -> 0.73 | M45: =Drivers!$I$75+$C$9 -> 0.73 | N45: =Drivers!$I$75+$C$9 -> 0.73 | O45: =Drivers!$I$75+$C$9 -> 0.73 | ... U45: =Drivers!$I$75+$C$9 -> 0.73
A46: Flu + combo revenue | B46: $B | C46: =C39+C40 -> 0.23628 | D46: =D39+D40 -> 0.47256 | E46: =E39+E40 -> 0.70884 | F46: =F39+F40 -> 0.94512 | G46: =G39+G40 -> 1.1814 | H46: =H39+H40 -> 1.1814 | I46: =I39+I40 -> 1.1814 | J46: =J39+J40 -> 1.1814 | ... U46: =U39+U40 -> 1.1814
A47: Blackstone sales milestones paid | B47: $B | C47: =MIN(Drivers!$C$77-0,Drivers!$C$78*C46) -> 0.0189024 | D47: =MIN(Drivers!$C$77-C48,Drivers!$C$78*D46) -> 0.0378048 | E47: =MIN(Drivers!$C$77-D48,Drivers!$C$78*E46) -> 0.0567072 | F47: =MIN(Drivers!$C$77-E48,Drivers!$C$78*F46) -> 0.0756096 | G47: =MIN(Drivers!$C$77-F48,Drivers!$C$78*G46) -> 0.094512 | H47: =MIN(Drivers!$C$77-G48,Drivers!$C$78*H46) -> 0.094512 | I47: =MIN(Drivers!$C$77-H48,Drivers!$C$78*I46) -> 0.094512 | J47: =MIN(Drivers!$C$77-I48,Drivers!$C$78*J46) -> 0.094512 | K47: =MIN(Drivers!$C$77-J48,Drivers!$C$78*K46) -> 0.094512 | ... U47: =MIN(Drivers!$C$77-T48,Drivers!$C$78*U46) -> 0
A48: Blackstone milestones cumulative | B48: $B | C48: =C47 -> 0.0189024 | D48: =C48+D47 -> 0.0567072 | E48: =D48+E47 -> 0.1134144 | F48: =E48+F47 -> 0.189024 | G48: =F48+G47 -> 0.283536 | H48: =G48+H47 -> 0.378048 | I48: =H48+I47 -> 0.47256 | J48: =I48+J47 -> 0.567072 | K48: =J48+K47 -> 0.661584 | ... U48: =T48+U47 -> 0.75
A49: Blackstone royalty + milestones | B49: $B | C49: =Drivers!$C$76*C46+C47 -> 0.0248094 | D49: =Drivers!$C$76*D46+D47 -> 0.0496188 | E49: =Drivers!$C$76*E46+E47 -> 0.0744282 | F49: =Drivers!$C$76*F46+F47 -> 0.0992376 | G49: =Drivers!$C$76*G46+G47 -> 0.124047 | H49: =Drivers!$C$76*H46+H47 -> 0.124047 | I49: =Drivers!$C$76*I46+I47 -> 0.124047 | J49: =Drivers!$C$76*J46+J47 -> 0.124047 | ... U49: =Drivers!$C$76*U46+U47 -> 0.029535
A50: Respiratory S&M | B50: $B | C50: =MAX(Drivers!$C$80,Drivers!$C$79*C44) -> 0.4 | D50: =MAX(Drivers!$C$80,Drivers!$C$79*D44) -> 0.4 | E50: =MAX(Drivers!$C$80,Drivers!$C$79*E44) -> 0.4 | F50: =MAX(Drivers!$C$80,Drivers!$C$79*F44) -> 0.4 | G50: =MAX(Drivers!$C$80,Drivers!$C$79*G44) -> 0.4 | H50: =MAX(Drivers!$C$80,Drivers!$C$79*H44) -> 0.4 | I50: =MAX(Drivers!$C$80,Drivers!$C$79*I44) -> 0.4 | J50: =MAX(Drivers!$C$80,Drivers!$C$79*J44) -> 0.4 | ... U50: =MAX(Drivers!$C$80,Drivers!$C$79*U44) -> 0.4
A51: Respiratory R&D | B51: $B | C51: =Drivers!$D$81 -> 0.75 | D51: =Drivers!$E$81 -> 0.62 | E51: =Drivers!$F$81 -> 0.55 | F51: =Drivers!$G$81 -> 0.5 | G51: =Drivers!$H$81 -> 0.48 | H51: =Drivers!$I$81 -> 0.46 | I51: =H51*1.02 -> 0.4692 | J51: =I51*1.02 -> 0.478584 | K51: =J51*1.02 -> 0.48815568 | L51: =K51*1.02 -> 0.49791879 | M51: =L51*1.02 -> 0.50787717 | N51: =M51*1.02 -> 0.51803471 | O51: =N51*1.02 -> 0.52839541 | P51: =O51*1.02 -> 0.53896332 | ... U51: =T51*1.02 -> 0.59505905
A52: Respiratory contribution | B52: $B | C52: =C44*C45-C49-C50-C51 -> 0.0706342 | D52: =D44*D45-D49-D50-D51 -> 0.3609708 | E52: =E44*E45-E49-E50-E51 -> 0.6138664 | F52: =F44*F45-F49-F50-F51 -> 0.8280326 | G52: =G44*G45-G49-G50-G51 -> 1.010801 | H52: =H44*H45-H49-H50-H51 -> 1.044185 | I52: =I44*I45-I49-I50-I51 -> 1.053892 | J52: =J44*J45-J49-J50-J51 -> 1.0286977 | ... U52: =U44*U45-U49-U50-U51 -> 0.85235986
A53: INTISMERAN (risk-adjusted global sales; Moderna books 50% of profit pool)
A54: Adjuvant melanoma IIB-IV (INTerpath-001) | B54: $B | C54: =$D$24*$C$15*IF((C$35-$C$24)<0,0,IF((C$35-$C$24)>=7,1,INDEX(Drivers!$D$86:$J$86,(C$35-$C$24)+1)))*IF((C$35-$C$24)<Drivers!$C$87,1,Drivers!$C$88*Drivers!$C$89^((C$35-$C$24)-Drivers!$C$87))*$E$24 -> 0 | D54: =$D$24*$C$15*IF((D$35-$C$24)<0,0,IF((D$35-$C$24)>=7,1,INDEX(Drivers!$D$86:$J$86,(D$35-$C$24)+1)))*IF((D$35-$C$24)<Drivers!$C$87,1,Drivers!$C$88*Drivers!$C$89^((D$35-$C$24)-Drivers!$C$87))*$E$24 -> 0.0765 | E54: =$D$24*$C$15*IF((E$35-$C$24)<0,0,IF((E$35-$C$24)>=7,1,INDEX(Drivers!$D$86:$J$86,(E$35-$C$24)+1)))*IF((E$35-$C$24)<Drivers!$C$87,1,Drivers!$C$88*Drivers!$C$89^((E$35-$C$24)-Drivers!$C$87))*$E$24 -> 0.2390625 | F54: =$D$24*$C$15*IF((F$35-$C$24)<0,0,IF((F$35-$C$24)>=7,1,INDEX(Drivers!$D$86:$J$86,(F$35-$C$24)+1)))*IF((F$35-$C$24)<Drivers!$C$87,1,Drivers!$C$88*Drivers!$C$89^((F$35-$C$24)-Drivers!$C$87))*$E$24 -> 0.4303125 | G54: =$D$24*$C$15*IF((G$35-$C$24)<0,0,IF((G$35-$C$24)>=7,1,INDEX(Drivers!$D$86:$J$86,(G$35-$C$24)+1)))*IF((G$35-$C$24)<Drivers!$C$87,1,Drivers!$C$88*Drivers!$C$89^((G$35-$C$24)-Drivers!$C$87))*$E$24 -> 0.6215625 | H54: =$D$24*$C$15*IF((H$35-$C$24)<0,0,IF((H$35-$C$24)>=7,1,INDEX(Drivers!$D$86:$J$86,(H$35-$C$24)+1)))*IF((H$35-$C$24)<Drivers!$C$87,1,Drivers!$C$88*Drivers!$C$89^((H$35-$C$24)-Drivers!$C$87))*$E$24 -> 0.784125 | I54: =$D$24*$C$15*IF((I$35-$C$24)<0,0,IF((I$35-$C$24)>=7,1,INDEX(Drivers!$D$86:$J$86,(I$35-$C$24)+1)))*IF((I$35-$C$24)<Drivers!$C$87,1,Drivers!$C$88*Drivers!$C$89^((I$35-$C$24)-Drivers!$C$87))*$E$24 -> 0.8893125 | J54: =$D$24*$C$15*IF((J$35-$C$24)<0,0,IF((J$35-$C$24)>=7,1,INDEX(Drivers!$D$86:$J$86,(J$35-$C$24)+1)))*IF((J$35-$C$24)<Drivers!$C$87,1,Drivers!$C$88*Drivers!$C$89^((J$35-$C$24)-Drivers!$C$87))*$E$24 -> 0.95625 | ... U54: =$D$24*$C$15*IF((U$35-$C$24)<0,0,IF((U$35-$C$24)>=7,1,INDEX(Drivers!$D$86:$J$86,(U$35-$C$24)+1)))*IF((U$35-$C$24)<Drivers!$C$87,1,Drivers!$C$88*Drivers!$C$89^((U$35-$C$24)-Drivers!$C$87))*$E$24 -> 0.65693153
A55: Adjuvant NSCLC II-IIIB (INTerpath-002) | B55: $B | C55: =$D$25*$C$15*IF((C$35-$C$25)<0,0,IF((C$35-$C$25)>=7,1,INDEX(Drivers!$D$86:$J$86,(C$35-$C$25)+1)))*IF((C$35-$C$25)<Drivers!$C$87,1,Drivers!$C$88*Drivers!$C$89^((C$35-$C$25)-Drivers!$C$87))*$E$25 -> 0 | D55: =$D$25*$C$15*IF((D$35-$C$25)<0,0,IF((D$35-$C$25)>=7,1,INDEX(Drivers!$D$86:$J$86,(D$35-$C$25)+1)))*IF((D$35-$C$25)<Drivers!$C$87,1,Drivers!$C$88*Drivers!$C$89^((D$35-$C$25)-Drivers!$C$87))*$E$25 -> 0 | E55: =$D$25*$C$15*IF((E$35-$C$25)<0,0,IF((E$35-$C$25)>=7,1,INDEX(Drivers!$D$86:$J$86,(E$35-$C$25)+1)))*IF((E$35-$C$25)<Drivers!$C$87,1,Drivers!$C$88*Drivers!$C$89^((E$35-$C$25)-Drivers!$C$87))*$E$25 -> 0 | F55: =$D$25*$C$15*IF((F$35-$C$25)<0,0,IF((F$35-$C$25)>=7,1,INDEX(Drivers!$D$86:$J$86,(F$35-$C$25)+1)))*IF((F$35-$C$25)<Drivers!$C$87,1,Drivers!$C$88*Drivers!$C$89^((F$35-$C$25)-Drivers!$C$87))*$E$25 -> 0 | G55: =$D$25*$C$15*IF((G$35-$C$25)<0,0,IF((G$35-$C$25)>=7,1,INDEX(Drivers!$D$86:$J$86,(G$35-$C$25)+1)))*IF((G$35-$C$25)<Drivers!$C$87,1,Drivers!$C$88*Drivers!$C$89^((G$35-$C$25)-Drivers!$C$87))*$E$25 -> 0.06048 | H55: =$D$25*$C$15*IF((H$35-$C$25)<0,0,IF((H$35-$C$25)>=7,1,INDEX(Drivers!$D$86:$J$86,(H$35-$C$25)+1)))*IF((H$35-$C$25)<Drivers!$C$87,1,Drivers!$C$88*Drivers!$C$89^((H$35-$C$25)-Drivers!$C$87))*$E$25 -> 0.189 | I55: =$D$25*$C$15*IF((I$35-$C$25)<0,0,IF((I$35-$C$25)>=7,1,INDEX(Drivers!$D$86:$J$86,(I$35-$C$25)+1)))*IF((I$35-$C$25)<Drivers!$C$87,1,Drivers!$C$88*Drivers!$C$89^((I$35-$C$25)-Drivers!$C$87))*$E$25 -> 0.3402 | J55: =$D$25*$C$15*IF((J$35-$C$25)<0,0,IF((J$35-$C$25)>=7,1,INDEX(Drivers!$D$86:$J$86,(J$35-$C$25)+1)))*IF((J$35-$C$25)<Drivers!$C$87,1,Drivers!$C$88*Drivers!$C$89^((J$35-$C$25)-Drivers!$C$87))*$E$25 -> 0.4914 | ... U55: =$D$25*$C$15*IF((U$35-$C$25)<0,0,IF((U$35-$C$25)>=7,1,INDEX(Drivers!$D$86:$J$86,(U$35-$C$25)+1)))*IF((U$35-$C$25)<Drivers!$C$87,1,Drivers!$C$88*Drivers!$C$89^((U$35-$C$25)-Drivers!$C$87))*$E$25 -> 0.56905632
A56: Post-neoadjuvant non-pCR NSCLC (INTerpath-009) | B56: $B | C56: =$D$26*$C$15*IF((C$35-$C$26)<0,0,IF((C$35-$C$26)>=7,1,INDEX(Drivers!$D$86:$J$86,(C$35-$C$26)+1)))*IF((C$35-$C$26)<Drivers!$C$87,1,Drivers!$C$88*Drivers!$C$89^((C$35-$C$26)-Drivers!$C$87))*$E$26 -> 0 | D56: =$D$26*$C$15*IF((D$35-$C$26)<0,0,IF((D$35-$C$26)>=7,1,INDEX(Drivers!$D$86:$J$86,(D$35-$C$26)+1)))*IF((D$35-$C$26)<Drivers!$C$87,1,Drivers!$C$88*Drivers!$C$89^((D$35-$C$26)-Drivers!$C$87))*$E$26 -> 0 | E56: =$D$26*$C$15*IF((E$35-$C$26)<0,0,IF((E$35-$C$26)>=7,1,INDEX(Drivers!$D$86:$J$86,(E$35-$C$26)+1)))*IF((E$35-$C$26)<Drivers!$C$87,1,Drivers!$C$88*Drivers!$C$89^((E$35-$C$26)-Drivers!$C$87))*$E$26 -> 0 | F56: =$D$26*$C$15*IF((F$35-$C$26)<0,0,IF((F$35-$C$26)>=7,1,INDEX(Drivers!$D$86:$J$86,(F$35-$C$26)+1)))*IF((F$35-$C$26)<Drivers!$C$87,1,Drivers!$C$88*Drivers!$C$89^((F$35-$C$26)-Drivers!$C$87))*$E$26 -> 0 | G56: =$D$26*$C$15*IF((G$35-$C$26)<0,0,IF((G$35-$C$26)>=7,1,INDEX(Drivers!$D$86:$J$86,(G$35-$C$26)+1)))*IF((G$35-$C$26)<Drivers!$C$87,1,Drivers!$C$88*Drivers!$C$89^((G$35-$C$26)-Drivers!$C$87))*$E$26 -> 0 | H56: =$D$26*$C$15*IF((H$35-$C$26)<0,0,IF((H$35-$C$26)>=7,1,INDEX(Drivers!$D$86:$J$86,(H$35-$C$26)+1)))*IF((H$35-$C$26)<Drivers!$C$87,1,Drivers!$C$88*Drivers!$C$89^((H$35-$C$26)-Drivers!$C$87))*$E$26 -> 0 | I56: =$D$26*$C$15*IF((I$35-$C$26)<0,0,IF((I$35-$C$26)>=7,1,INDEX(Drivers!$D$86:$J$86,(I$35-$C$26)+1)))*IF((I$35-$C$26)<Drivers!$C$87,1,Drivers!$C$88*Drivers!$C$89^((I$35-$C$26)-Drivers!$C$87))*$E$26 -> 0 | J56: =$D$26*$C$15*IF((J$35-$C$26)<0,0,IF((J$35-$C$26)>=7,1,INDEX(Drivers!$D$86:$J$86,(J$35-$C$26)+1)))*IF((J$35-$C$26)<Drivers!$C$87,1,Drivers!$C$88*Drivers!$C$89^((J$35-$C$26)-Drivers!$C$87))*$E$26 -> 0.02016 | ... U56: =$D$26*$C$15*IF((U$35-$C$26)<0,0,IF((U$35-$C$26)>=7,1,INDEX(Drivers!$D$86:$J$86,(U$35-$C$26)+1)))*IF((U$35-$C$26)<Drivers!$C$87,1,Drivers!$C$88*Drivers!$C$89^((U$35-$C$26)-Drivers!$C$87))*$E$26 -> 0.252
A57: Resected stage I NSCLC (INTerpath-014) | B57: $B | C57: =$D$27*$C$15*IF((C$35-$C$27)<0,0,IF((C$35-$C$27)>=7,1,INDEX(Drivers!$D$86:$J$86,(C$35-$C$27)+1)))*IF((C$35-$C$27)<Drivers!$C$87,1,Drivers!$C$88*Drivers!$C$89^((C$35-$C$27)-Drivers!$C$87))*$E$27 -> 0 | D57: =$D$27*$C$15*IF((D$35-$C$27)<0,0,IF((D$35-$C$27)>=7,1,INDEX(Drivers!$D$86:$J$86,(D$35-$C$27)+1)))*IF((D$35-$C$27)<Drivers!$C$87,1,Drivers!$C$88*Drivers!$C$89^((D$35-$C$27)-Drivers!$C$87))*$E$27 -> 0 | E57: =$D$27*$C$15*IF((E$35-$C$27)<0,0,IF((E$35-$C$27)>=7,1,INDEX(Drivers!$D$86:$J$86,(E$35-$C$27)+1)))*IF((E$35-$C$27)<Drivers!$C$87,1,Drivers!$C$88*Drivers!$C$89^((E$35-$C$27)-Drivers!$C$87))*$E$27 -> 0 | F57: =$D$27*$C$15*IF((F$35-$C$27)<0,0,IF((F$35-$C$27)>=7,1,INDEX(Drivers!$D$86:$J$86,(F$35-$C$27)+1)))*IF((F$35-$C$27)<Drivers!$C$87,1,Drivers!$C$88*Drivers!$C$89^((F$35-$C$27)-Drivers!$C$87))*$E$27 -> 0 | G57: =$D$27*$C$15*IF((G$35-$C$27)<0,0,IF((G$35-$C$27)>=7,1,INDEX(Drivers!$D$86:$J$86,(G$35-$C$27)+1)))*IF((G$35-$C$27)<Drivers!$C$87,1,Drivers!$C$88*Drivers!$C$89^((G$35-$C$27)-Drivers!$C$87))*$E$27 -> 0 | H57: =$D$27*$C$15*IF((H$35-$C$27)<0,0,IF((H$35-$C$27)>=7,1,INDEX(Drivers!$D$86:$J$86,(H$35-$C$27)+1)))*IF((H$35-$C$27)<Drivers!$C$87,1,Drivers!$C$88*Drivers!$C$89^((H$35-$C$27)-Drivers!$C$87))*$E$27 -> 0 | I57: =$D$27*$C$15*IF((I$35-$C$27)<0,0,IF((I$35-$C$27)>=7,1,INDEX(Drivers!$D$86:$J$86,(I$35-$C$27)+1)))*IF((I$35-$C$27)<Drivers!$C$87,1,Drivers!$C$88*Drivers!$C$89^((I$35-$C$27)-Drivers!$C$87))*$E$27 -> 0 | J57: =$D$27*$C$15*IF((J$35-$C$27)<0,0,IF((J$35-$C$27)>=7,1,INDEX(Drivers!$D$86:$J$86,(J$35-$C$27)+1)))*IF((J$35-$C$27)<Drivers!$C$87,1,Drivers!$C$88*Drivers!$C$89^((J$35-$C$27)-Drivers!$C$87))*$E$27 -> 0 | ... U57: =$D$27*$C$15*IF((U$35-$C$27)<0,0,IF((U$35-$C$27)>=7,1,INDEX(Drivers!$D$86:$J$86,(U$35-$C$27)+1)))*IF((U$35-$C$27)<Drivers!$C$87,1,Drivers!$C$88*Drivers!$C$89^((U$35-$C$27)-Drivers!$C$87))*$E$27 -> 0.3675
A58: Adjuvant RCC (INTerpath-004) | B58: $B | C58: =$D$28*$C$15*IF((C$35-$C$28)<0,0,IF((C$35-$C$28)>=7,1,INDEX(Drivers!$D$86:$J$86,(C$35-$C$28)+1)))*IF((C$35-$C$28)<Drivers!$C$87,1,Drivers!$C$88*Drivers!$C$89^((C$35-$C$28)-Drivers!$C$87))*$E$28 -> 0 | D58: =$D$28*$C$15*IF((D$35-$C$28)<0,0,IF((D$35-$C$28)>=7,1,INDEX(Drivers!$D$86:$J$86,(D$35-$C$28)+1)))*IF((D$35-$C$28)<Drivers!$C$87,1,Drivers!$C$88*Drivers!$C$89^((D$35-$C$28)-Drivers!$C$87))*$E$28 -> 0 | E58: =$D$28*$C$15*IF((E$35-$C$28)<0,0,IF((E$35-$C$28)>=7,1,INDEX(Drivers!$D$86:$J$86,(E$35-$C$28)+1)))*IF((E$35-$C$28)<Drivers!$C$87,1,Drivers!$C$88*Drivers!$C$89^((E$35-$C$28)-Drivers!$C$87))*$E$28 -> 0 | F58: =$D$28*$C$15*IF((F$35-$C$28)<0,0,IF((F$35-$C$28)>=7,1,INDEX(Drivers!$D$86:$J$86,(F$35-$C$28)+1)))*IF((F$35-$C$28)<Drivers!$C$87,1,Drivers!$C$88*Drivers!$C$89^((F$35-$C$28)-Drivers!$C$87))*$E$28 -> 0 | G58: =$D$28*$C$15*IF((G$35-$C$28)<0,0,IF((G$35-$C$28)>=7,1,INDEX(Drivers!$D$86:$J$86,(G$35-$C$28)+1)))*IF((G$35-$C$28)<Drivers!$C$87,1,Drivers!$C$88*Drivers!$C$89^((G$35-$C$28)-Drivers!$C$87))*$E$28 -> 0.01008 | H58: =$D$28*$C$15*IF((H$35-$C$28)<0,0,IF((H$35-$C$28)>=7,1,INDEX(Drivers!$D$86:$J$86,(H$35-$C$28)+1)))*IF((H$35-$C$28)<Drivers!$C$87,1,Drivers!$C$88*Drivers!$C$89^((H$35-$C$28)-Drivers!$C$87))*$E$28 -> 0.0315 | I58: =$D$28*$C$15*IF((I$35-$C$28)<0,0,IF((I$35-$C$28)>=7,1,INDEX(Drivers!$D$86:$J$86,(I$35-$C$28)+1)))*IF((I$35-$C$28)<Drivers!$C$87,1,Drivers!$C$88*Drivers!$C$89^((I$35-$C$28)-Drivers!$C$87))*$E$28 -> 0.0567 | J58: =$D$28*$C$15*IF((J$35-$C$28)<0,0,IF((J$35-$C$28)>=7,1,INDEX(Drivers!$D$86:$J$86,(J$35-$C$28)+1)))*IF((J$35-$C$28)<Drivers!$C$87,1,Drivers!$C$88*Drivers!$C$89^((J$35-$C$28)-Drivers!$C$87))*$E$28 -> 0.0819 | ... U58: =$D$28*$C$15*IF((U$35-$C$28)<0,0,IF((U$35-$C$28)>=7,1,INDEX(Drivers!$D$86:$J$86,(U$35-$C$28)+1)))*IF((U$35-$C$28)<Drivers!$C$87,1,Drivers!$C$88*Drivers!$C$89^((U$35-$C$28)-Drivers!$C$87))*$E$28 -> 0.09484272
A59: MIBC adjuvant (INTerpath-005) | B59: $B | C59: =$D$29*$C$15*IF((C$35-$C$29)<0,0,IF((C$35-$C$29)>=7,1,INDEX(Drivers!$D$86:$J$86,(C$35-$C$29)+1)))*IF((C$35-$C$29)<Drivers!$C$87,1,Drivers!$C$88*Drivers!$C$89^((C$35-$C$29)-Drivers!$C$87))*$E$29 -> 0 | D59: =$D$29*$C$15*IF((D$35-$C$29)<0,0,IF((D$35-$C$29)>=7,1,INDEX(Drivers!$D$86:$J$86,(D$35-$C$29)+1)))*IF((D$35-$C$29)<Drivers!$C$87,1,Drivers!$C$88*Drivers!$C$89^((D$35-$C$29)-Drivers!$C$87))*$E$29 -> 0 | E59: =$D$29*$C$15*IF((E$35-$C$29)<0,0,IF((E$35-$C$29)>=7,1,INDEX(Drivers!$D$86:$J$86,(E$35-$C$29)+1)))*IF((E$35-$C$29)<Drivers!$C$87,1,Drivers!$C$88*Drivers!$C$89^((E$35-$C$29)-Drivers!$C$87))*$E$29 -> 0 | F59: =$D$29*$C$15*IF((F$35-$C$29)<0,0,IF((F$35-$C$29)>=7,1,INDEX(Drivers!$D$86:$J$86,(F$35-$C$29)+1)))*IF((F$35-$C$29)<Drivers!$C$87,1,Drivers!$C$88*Drivers!$C$89^((F$35-$C$29)-Drivers!$C$87))*$E$29 -> 0 | G59: =$D$29*$C$15*IF((G$35-$C$29)<0,0,IF((G$35-$C$29)>=7,1,INDEX(Drivers!$D$86:$J$86,(G$35-$C$29)+1)))*IF((G$35-$C$29)<Drivers!$C$87,1,Drivers!$C$88*Drivers!$C$89^((G$35-$C$29)-Drivers!$C$87))*$E$29 -> 0 | H59: =$D$29*$C$15*IF((H$35-$C$29)<0,0,IF((H$35-$C$29)>=7,1,INDEX(Drivers!$D$86:$J$86,(H$35-$C$29)+1)))*IF((H$35-$C$29)<Drivers!$C$87,1,Drivers!$C$88*Drivers!$C$89^((H$35-$C$29)-Drivers!$C$87))*$E$29 -> 0 | I59: =$D$29*$C$15*IF((I$35-$C$29)<0,0,IF((I$35-$C$29)>=7,1,INDEX(Drivers!$D$86:$J$86,(I$35-$C$29)+1)))*IF((I$35-$C$29)<Drivers!$C$87,1,Drivers!$C$88*Drivers!$C$89^((I$35-$C$29)-Drivers!$C$87))*$E$29 -> 0.00672 | J59: =$D$29*$C$15*IF((J$35-$C$29)<0,0,IF((J$35-$C$29)>=7,1,INDEX(Drivers!$D$86:$J$86,(J$35-$C$29)+1)))*IF((J$35-$C$29)<Drivers!$C$87,1,Drivers!$C$88*Drivers!$C$89^((J$35-$C$29)-Drivers!$C$87))*$E$29 -> 0.021 | ... U59: =$D$29*$C$15*IF((U$35-$C$29)<0,0,IF((U$35-$C$29)>=7,1,INDEX(Drivers!$D$86:$J$86,(U$35-$C$29)+1)))*IF((U$35-$C$29)<Drivers!$C$87,1,Drivers!$C$88*Drivers!$C$89^((U$35-$C$29)-Drivers!$C$87))*$E$29 -> 0.0672
A60: NMIBC + BCG (INTerpath-011) | B60: $B | C60: =$D$30*$C$15*IF((C$35-$C$30)<0,0,IF((C$35-$C$30)>=7,1,INDEX(Drivers!$D$86:$J$86,(C$35-$C$30)+1)))*IF((C$35-$C$30)<Drivers!$C$87,1,Drivers!$C$88*Drivers!$C$89^((C$35-$C$30)-Drivers!$C$87))*$E$30 -> 0 | D60: =$D$30*$C$15*IF((D$35-$C$30)<0,0,IF((D$35-$C$30)>=7,1,INDEX(Drivers!$D$86:$J$86,(D$35-$C$30)+1)))*IF((D$35-$C$30)<Drivers!$C$87,1,Drivers!$C$88*Drivers!$C$89^((D$35-$C$30)-Drivers!$C$87))*$E$30 -> 0 | E60: =$D$30*$C$15*IF((E$35-$C$30)<0,0,IF((E$35-$C$30)>=7,1,INDEX(Drivers!$D$86:$J$86,(E$35-$C$30)+1)))*IF((E$35-$C$30)<Drivers!$C$87,1,Drivers!$C$88*Drivers!$C$89^((E$35-$C$30)-Drivers!$C$87))*$E$30 -> 0 | F60: =$D$30*$C$15*IF((F$35-$C$30)<0,0,IF((F$35-$C$30)>=7,1,INDEX(Drivers!$D$86:$J$86,(F$35-$C$30)+1)))*IF((F$35-$C$30)<Drivers!$C$87,1,Drivers!$C$88*Drivers!$C$89^((F$35-$C$30)-Drivers!$C$87))*$E$30 -> 0 | G60: =$D$30*$C$15*IF((G$35-$C$30)<0,0,IF((G$35-$C$30)>=7,1,INDEX(Drivers!$D$86:$J$86,(G$35-$C$30)+1)))*IF((G$35-$C$30)<Drivers!$C$87,1,Drivers!$C$88*Drivers!$C$89^((G$35-$C$30)-Drivers!$C$87))*$E$30 -> 0 | H60: =$D$30*$C$15*IF((H$35-$C$30)<0,0,IF((H$35-$C$30)>=7,1,INDEX(Drivers!$D$86:$J$86,(H$35-$C$30)+1)))*IF((H$35-$C$30)<Drivers!$C$87,1,Drivers!$C$88*Drivers!$C$89^((H$35-$C$30)-Drivers!$C$87))*$E$30 -> 0 | I60: =$D$30*$C$15*IF((I$35-$C$30)<0,0,IF((I$35-$C$30)>=7,1,INDEX(Drivers!$D$86:$J$86,(I$35-$C$30)+1)))*IF((I$35-$C$30)<Drivers!$C$87,1,Drivers!$C$88*Drivers!$C$89^((I$35-$C$30)-Drivers!$C$87))*$E$30 -> 0 | J60: =$D$30*$C$15*IF((J$35-$C$30)<0,0,IF((J$35-$C$30)>=7,1,INDEX(Drivers!$D$86:$J$86,(J$35-$C$30)+1)))*IF((J$35-$C$30)<Drivers!$C$87,1,Drivers!$C$88*Drivers!$C$89^((J$35-$C$30)-Drivers!$C$87))*$E$30 -> 0.00504 | ... U60: =$D$30*$C$15*IF((U$35-$C$30)<0,0,IF((U$35-$C$30)>=7,1,INDEX(Drivers!$D$86:$J$86,(U$35-$C$30)+1)))*IF((U$35-$C$30)<Drivers!$C$87,1,Drivers!$C$88*Drivers!$C$89^((U$35-$C$30)-Drivers!$C$87))*$E$30 -> 0.063
A61: 1L advanced melanoma (INTerpath-012) | B61: $B | C61: =$D$31*$C$15*IF((C$35-$C$31)<0,0,IF((C$35-$C$31)>=7,1,INDEX(Drivers!$D$86:$J$86,(C$35-$C$31)+1)))*IF((C$35-$C$31)<Drivers!$C$87,1,Drivers!$C$88*Drivers!$C$89^((C$35-$C$31)-Drivers!$C$87))*$E$31 -> 0 | D61: =$D$31*$C$15*IF((D$35-$C$31)<0,0,IF((D$35-$C$31)>=7,1,INDEX(Drivers!$D$86:$J$86,(D$35-$C$31)+1)))*IF((D$35-$C$31)<Drivers!$C$87,1,Drivers!$C$88*Drivers!$C$89^((D$35-$C$31)-Drivers!$C$87))*$E$31 -> 0 | E61: =$D$31*$C$15*IF((E$35-$C$31)<0,0,IF((E$35-$C$31)>=7,1,INDEX(Drivers!$D$86:$J$86,(E$35-$C$31)+1)))*IF((E$35-$C$31)<Drivers!$C$87,1,Drivers!$C$88*Drivers!$C$89^((E$35-$C$31)-Drivers!$C$87))*$E$31 -> 0 | F61: =$D$31*$C$15*IF((F$35-$C$31)<0,0,IF((F$35-$C$31)>=7,1,INDEX(Drivers!$D$86:$J$86,(F$35-$C$31)+1)))*IF((F$35-$C$31)<Drivers!$C$87,1,Drivers!$C$88*Drivers!$C$89^((F$35-$C$31)-Drivers!$C$87))*$E$31 -> 0 | G61: =$D$31*$C$15*IF((G$35-$C$31)<0,0,IF((G$35-$C$31)>=7,1,INDEX(Drivers!$D$86:$J$86,(G$35-$C$31)+1)))*IF((G$35-$C$31)<Drivers!$C$87,1,Drivers!$C$88*Drivers!$C$89^((G$35-$C$31)-Drivers!$C$87))*$E$31 -> 0.005376 | H61: =$D$31*$C$15*IF((H$35-$C$31)<0,0,IF((H$35-$C$31)>=7,1,INDEX(Drivers!$D$86:$J$86,(H$35-$C$31)+1)))*IF((H$35-$C$31)<Drivers!$C$87,1,Drivers!$C$88*Drivers!$C$89^((H$35-$C$31)-Drivers!$C$87))*$E$31 -> 0.0168 | I61: =$D$31*$C$15*IF((I$35-$C$31)<0,0,IF((I$35-$C$31)>=7,1,INDEX(Drivers!$D$86:$J$86,(I$35-$C$31)+1)))*IF((I$35-$C$31)<Drivers!$C$87,1,Drivers!$C$88*Drivers!$C$89^((I$35-$C$31)-Drivers!$C$87))*$E$31 -> 0.03024 | J61: =$D$31*$C$15*IF((J$35-$C$31)<0,0,IF((J$35-$C$31)>=7,1,INDEX(Drivers!$D$86:$J$86,(J$35-$C$31)+1)))*IF((J$35-$C$31)<Drivers!$C$87,1,Drivers!$C$88*Drivers!$C$89^((J$35-$C$31)-Drivers!$C$87))*$E$31 -> 0.04368 | ... U61: =$D$31*$C$15*IF((U$35-$C$31)<0,0,IF((U$35-$C$31)>=7,1,INDEX(Drivers!$D$86:$J$86,(U$35-$C$31)+1)))*IF((U$35-$C$31)<Drivers!$C$87,1,Drivers!$C$88*Drivers!$C$89^((U$35-$C$31)-Drivers!$C$87))*$E$31 -> 0.050582784
A62: 1L metastatic squamous NSCLC (INTerpath-013) | B62: $B | C62: =$D$32*$C$15*IF((C$35-$C$32)<0,0,IF((C$35-$C$32)>=7,1,INDEX(Drivers!$D$86:$J$86,(C$35-$C$32)+1)))*IF((C$35-$C$32)<Drivers!$C$87,1,Drivers!$C$88*Drivers!$C$89^((C$35-$C$32)-Drivers!$C$87))*$E$32 -> 0 | D62: =$D$32*$C$15*IF((D$35-$C$32)<0,0,IF((D$35-$C$32)>=7,1,INDEX(Drivers!$D$86:$J$86,(D$35-$C$32)+1)))*IF((D$35-$C$32)<Drivers!$C$87,1,Drivers!$C$88*Drivers!$C$89^((D$35-$C$32)-Drivers!$C$87))*$E$32 -> 0 | E62: =$D$32*$C$15*IF((E$35-$C$32)<0,0,IF((E$35-$C$32)>=7,1,INDEX(Drivers!$D$86:$J$86,(E$35-$C$32)+1)))*IF((E$35-$C$32)<Drivers!$C$87,1,Drivers!$C$88*Drivers!$C$89^((E$35-$C$32)-Drivers!$C$87))*$E$32 -> 0 | F62: =$D$32*$C$15*IF((F$35-$C$32)<0,0,IF((F$35-$C$32)>=7,1,INDEX(Drivers!$D$86:$J$86,(F$35-$C$32)+1)))*IF((F$35-$C$32)<Drivers!$C$87,1,Drivers!$C$88*Drivers!$C$89^((F$35-$C$32)-Drivers!$C$87))*$E$32 -> 0 | G62: =$D$32*$C$15*IF((G$35-$C$32)<0,0,IF((G$35-$C$32)>=7,1,INDEX(Drivers!$D$86:$J$86,(G$35-$C$32)+1)))*IF((G$35-$C$32)<Drivers!$C$87,1,Drivers!$C$88*Drivers!$C$89^((G$35-$C$32)-Drivers!$C$87))*$E$32 -> 0 | H62: =$D$32*$C$15*IF((H$35-$C$32)<0,0,IF((H$35-$C$32)>=7,1,INDEX(Drivers!$D$86:$J$86,(H$35-$C$32)+1)))*IF((H$35-$C$32)<Drivers!$C$87,1,Drivers!$C$88*Drivers!$C$89^((H$35-$C$32)-Drivers!$C$87))*$E$32 -> 0.006048 | I62: =$D$32*$C$15*IF((I$35-$C$32)<0,0,IF((I$35-$C$32)>=7,1,INDEX(Drivers!$D$86:$J$86,(I$35-$C$32)+1)))*IF((I$35-$C$32)<Drivers!$C$87,1,Drivers!$C$88*Drivers!$C$89^((I$35-$C$32)-Drivers!$C$87))*$E$32 -> 0.0189 | J62: =$D$32*$C$15*IF((J$35-$C$32)<0,0,IF((J$35-$C$32)>=7,1,INDEX(Drivers!$D$86:$J$86,(J$35-$C$32)+1)))*IF((J$35-$C$32)<Drivers!$C$87,1,Drivers!$C$88*Drivers!$C$89^((J$35-$C$32)-Drivers!$C$87))*$E$32 -> 0.03402 | ... U62: =$D$32*$C$15*IF((U$35-$C$32)<0,0,IF((U$35-$C$32)>=7,1,INDEX(Drivers!$D$86:$J$86,(U$35-$C$32)+1)))*IF((U$35-$C$32)<Drivers!$C$87,1,Drivers!$C$88*Drivers!$C$89^((U$35-$C$32)-Drivers!$C$87))*$E$32 -> 0.0586656
A63: Other solid tumours - future INT indications (pr | B63: $B | C63: =$D$33*$C$15*IF((C$35-$C$33)<0,0,IF((C$35-$C$33)>=7,1,INDEX(Drivers!$D$86:$J$86,(C$35-$C$33)+1)))*IF((C$35-$C$33)<Drivers!$C$87,1,Drivers!$C$88*Drivers!$C$89^((C$35-$C$33)-Drivers!$C$87))*$E$33 -> 0 | D63: =$D$33*$C$15*IF((D$35-$C$33)<0,0,IF((D$35-$C$33)>=7,1,INDEX(Drivers!$D$86:$J$86,(D$35-$C$33)+1)))*IF((D$35-$C$33)<Drivers!$C$87,1,Drivers!$C$88*Drivers!$C$89^((D$35-$C$33)-Drivers!$C$87))*$E$33 -> 0 | E63: =$D$33*$C$15*IF((E$35-$C$33)<0,0,IF((E$35-$C$33)>=7,1,INDEX(Drivers!$D$86:$J$86,(E$35-$C$33)+1)))*IF((E$35-$C$33)<Drivers!$C$87,1,Drivers!$C$88*Drivers!$C$89^((E$35-$C$33)-Drivers!$C$87))*$E$33 -> 0 | F63: =$D$33*$C$15*IF((F$35-$C$33)<0,0,IF((F$35-$C$33)>=7,1,INDEX(Drivers!$D$86:$J$86,(F$35-$C$33)+1)))*IF((F$35-$C$33)<Drivers!$C$87,1,Drivers!$C$88*Drivers!$C$89^((F$35-$C$33)-Drivers!$C$87))*$E$33 -> 0 | G63: =$D$33*$C$15*IF((G$35-$C$33)<0,0,IF((G$35-$C$33)>=7,1,INDEX(Drivers!$D$86:$J$86,(G$35-$C$33)+1)))*IF((G$35-$C$33)<Drivers!$C$87,1,Drivers!$C$88*Drivers!$C$89^((G$35-$C$33)-Drivers!$C$87))*$E$33 -> 0 | H63: =$D$33*$C$15*IF((H$35-$C$33)<0,0,IF((H$35-$C$33)>=7,1,INDEX(Drivers!$D$86:$J$86,(H$35-$C$33)+1)))*IF((H$35-$C$33)<Drivers!$C$87,1,Drivers!$C$88*Drivers!$C$89^((H$35-$C$33)-Drivers!$C$87))*$E$33 -> 0 | I63: =$D$33*$C$15*IF((I$35-$C$33)<0,0,IF((I$35-$C$33)>=7,1,INDEX(Drivers!$D$86:$J$86,(I$35-$C$33)+1)))*IF((I$35-$C$33)<Drivers!$C$87,1,Drivers!$C$88*Drivers!$C$89^((I$35-$C$33)-Drivers!$C$87))*$E$33 -> 0 | J63: =$D$33*$C$15*IF((J$35-$C$33)<0,0,IF((J$35-$C$33)>=7,1,INDEX(Drivers!$D$86:$J$86,(J$35-$C$33)+1)))*IF((J$35-$C$33)<Drivers!$C$87,1,Drivers!$C$88*Drivers!$C$89^((J$35-$C$33)-Drivers!$C$87))*$E$33 -> 0 | ... U63: =$D$33*$C$15*IF((U$35-$C$33)<0,0,IF((U$35-$C$33)>=7,1,INDEX(Drivers!$D$86:$J$86,(U$35-$C$33)+1)))*IF((U$35-$C$33)<Drivers!$C$87,1,Drivers!$C$88*Drivers!$C$89^((U$35-$C$33)-Drivers!$C$87))*$E$33 -> 0.252
A64: INT global sales (risk-adjusted) | B64: $B | C64: =SUM(C54:C63) -> 0 | D64: =SUM(D54:D63) -> 0.0765 | E64: =SUM(E54:E63) -> 0.2390625 | F64: =SUM(F54:F63) -> 0.4303125 | G64: =SUM(G54:G63) -> 0.6974985 | H64: =SUM(H54:H63) -> 1.027473 | I64: =SUM(I54:I63) -> 1.3420725 | J64: =SUM(J54:J63) -> 1.65345 | ... U64: =SUM(U54:U63) -> 2.431779
A65: Profit-pool margin | B65: % | C65: =IF((C$35-$C$24)<0,0,Drivers!$C$90+($C$16-Drivers!$C$90)*MIN((C$35-$C$24)/Drivers!$C$91,1)) -> 0 | D65: =IF((D$35-$C$24)<0,0,Drivers!$C$90+($C$16-Drivers!$C$90)*MIN((D$35-$C$24)/Drivers!$C$91,1)) -> 0.2 | E65: =IF((E$35-$C$24)<0,0,Drivers!$C$90+($C$16-Drivers!$C$90)*MIN((E$35-$C$24)/Drivers!$C$91,1)) -> 0.27 | F65: =IF((F$35-$C$24)<0,0,Drivers!$C$90+($C$16-Drivers!$C$90)*MIN((F$35-$C$24)/Drivers!$C$91,1)) -> 0.34 | G65: =IF((G$35-$C$24)<0,0,Drivers!$C$90+($C$16-Drivers!$C$90)*MIN((G$35-$C$24)/Drivers!$C$91,1)) -> 0.41 | H65: =IF((H$35-$C$24)<0,0,Drivers!$C$90+($C$16-Drivers!$C$90)*MIN((H$35-$C$24)/Drivers!$C$91,1)) -> 0.48 | I65: =IF((I$35-$C$24)<0,0,Drivers!$C$90+($C$16-Drivers!$C$90)*MIN((I$35-$C$24)/Drivers!$C$91,1)) -> 0.55 | J65: =IF((J$35-$C$24)<0,0,Drivers!$C$90+($C$16-Drivers!$C$90)*MIN((J$35-$C$24)/Drivers!$C$91,1)) -> 0.55 | ... U65: =IF((U$35-$C$24)<0,0,Drivers!$C$90+($C$16-Drivers!$C$90)*MIN((U$35-$C$24)/Drivers!$C$91,1)) -> 0.55
A66: Moderna 50% share of profit pool | B66: $B | C66: =Drivers!$C$85*C64*C65 -> 0 | D66: =Drivers!$C$85*D64*D65 -> 0.00765 | E66: =Drivers!$C$85*E64*E65 -> 0.032273438 | F66: =Drivers!$C$85*F64*F65 -> 0.073153125 | G66: =Drivers!$C$85*G64*G65 -> 0.14298719 | H66: =Drivers!$C$85*H64*H65 -> 0.24659352 | I66: =Drivers!$C$85*I64*I65 -> 0.36906994 | J66: =Drivers!$C$85*J64*J65 -> 0.45469875 | ... U66: =Drivers!$C$85*U64*U65 -> 0.66873921
A67: Moderna share of INT development | B67: $B | C67: =Drivers!$D$92 -> 0.4 | D67: =Drivers!$E$92 -> 0.4 | E67: =Drivers!$F$92 -> 0.4 | F67: =Drivers!$G$92 -> 0.4 | G67: =Drivers!$H$92 -> 0.35 | H67: =Drivers!$I$92 -> 0.35 | I67: =Drivers!$J$92 -> 0.3 | J67: =Drivers!$K$92 -> 0.25 | K67: =Drivers!$C$93 -> 0.2 | L67: =Drivers!$C$93 -> 0.2 | M67: =Drivers!$C$93 -> 0.2 | N67: =Drivers!$C$93 -> 0.2 | O67: =Drivers!$C$93 -> 0.2 | P67: =Drivers!$C$93 -> 0.2 | Q67: =Drivers!$C$93 -> 0.2 | R67: =Drivers!$C$93 -> 0.2 | ... U67: =Drivers!$C$93 -> 0.2
A68: INT contribution | B68: $B | C68: =C66-C67 -> -0.4 | D68: =D66-D67 -> -0.39235 | E68: =E66-E67 -> -0.36772656 | F68: =F66-F67 -> -0.32684687 | G68: =G66-G67 -> -0.20701281 | H68: =H66-H67 -> -0.10340648 | I68: =I66-I67 -> 0.069069938 | J68: =J66-J67 -> 0.20469875 | ... U68: =U66-U67 -> 0.46873921
A69: OTHER PIPELINE
A70: mRNA-4359 sales (risk-adjusted) | B70: $B | C70: =Drivers!$C$107*Drivers!$C$108*IF((C$35-Drivers!$C$109)<0,0,IF((C$35-Drivers!$C$109)>=7,1,INDEX(Drivers!$D$86:$J$86,(C$35-Drivers!$C$109)+1)))*IF((C$35-Drivers!$C$109)<Drivers!$C$87,1,Drivers!$C$88*Drivers!$C$89^((C$35-Drivers!$C$109)-Drivers!$C$87)) -> 0 | D70: =Drivers!$C$107*Drivers!$C$108*IF((D$35-Drivers!$C$109)<0,0,IF((D$35-Drivers!$C$109)>=7,1,INDEX(Drivers!$D$86:$J$86,(D$35-Drivers!$C$109)+1)))*IF((D$35-Drivers!$C$109)<Drivers!$C$87,1,Drivers!$C$88*Drivers!$C$89^((D$35-Drivers!$C$109)-Drivers!$C$87)) -> 0 | E70: =Drivers!$C$107*Drivers!$C$108*IF((E$35-Drivers!$C$109)<0,0,IF((E$35-Drivers!$C$109)>=7,1,INDEX(Drivers!$D$86:$J$86,(E$35-Drivers!$C$109)+1)))*IF((E$35-Drivers!$C$109)<Drivers!$C$87,1,Drivers!$C$88*Drivers!$C$89^((E$35-Drivers!$C$109)-Drivers!$C$87)) -> 0 | F70: =Drivers!$C$107*Drivers!$C$108*IF((F$35-Drivers!$C$109)<0,0,IF((F$35-Drivers!$C$109)>=7,1,INDEX(Drivers!$D$86:$J$86,(F$35-Drivers!$C$109)+1)))*IF((F$35-Drivers!$C$109)<Drivers!$C$87,1,Drivers!$C$88*Drivers!$C$89^((F$35-Drivers!$C$109)-Drivers!$C$87)) -> 0 | G70: =Drivers!$C$107*Drivers!$C$108*IF((G$35-Drivers!$C$109)<0,0,IF((G$35-Drivers!$C$109)>=7,1,INDEX(Drivers!$D$86:$J$86,(G$35-Drivers!$C$109)+1)))*IF((G$35-Drivers!$C$109)<Drivers!$C$87,1,Drivers!$C$88*Drivers!$C$89^((G$35-Drivers!$C$109)-Drivers!$C$87)) -> 0.016 | H70: =Drivers!$C$107*Drivers!$C$108*IF((H$35-Drivers!$C$109)<0,0,IF((H$35-Drivers!$C$109)>=7,1,INDEX(Drivers!$D$86:$J$86,(H$35-Drivers!$C$109)+1)))*IF((H$35-Drivers!$C$109)<Drivers!$C$87,1,Drivers!$C$88*Drivers!$C$89^((H$35-Drivers!$C$109)-Drivers!$C$87)) -> 0.05 | I70: =Drivers!$C$107*Drivers!$C$108*IF((I$35-Drivers!$C$109)<0,0,IF((I$35-Drivers!$C$109)>=7,1,INDEX(Drivers!$D$86:$J$86,(I$35-Drivers!$C$109)+1)))*IF((I$35-Drivers!$C$109)<Drivers!$C$87,1,Drivers!$C$88*Drivers!$C$89^((I$35-Drivers!$C$109)-Drivers!$C$87)) -> 0.09 | J70: =Drivers!$C$107*Drivers!$C$108*IF((J$35-Drivers!$C$109)<0,0,IF((J$35-Drivers!$C$109)>=7,1,INDEX(Drivers!$D$86:$J$86,(J$35-Drivers!$C$109)+1)))*IF((J$35-Drivers!$C$109)<Drivers!$C$87,1,Drivers!$C$88*Drivers!$C$89^((J$35-Drivers!$C$109)-Drivers!$C$87)) -> 0.13 | ... U70: =Drivers!$C$107*Drivers!$C$108*IF((U$35-Drivers!$C$109)<0,0,IF((U$35-Drivers!$C$109)>=7,1,INDEX(Drivers!$D$86:$J$86,(U$35-Drivers!$C$109)+1)))*IF((U$35-Drivers!$C$109)<Drivers!$C$87,1,Drivers!$C$88*Drivers!$C$89^((U$35-Drivers!$C$109)-Drivers!$C$87)) -> 0.150544
A71: mRNA-4359 development | B71: $B | C71: =Drivers!$D$111 -> 0.12 | D71: =Drivers!$E$111+Drivers!$C$112*Drivers!$C$113/3 -> 0.19083333 | E71: =Drivers!$F$111+Drivers!$C$112*Drivers!$C$113/3 -> 0.19083333 | F71: =Drivers!$G$111+Drivers!$C$112*Drivers!$C$113/3 -> 0.14083333 | G71: =Drivers!$H$111 -> 0.08 | H71: =0 -> 0 | I71: =0 -> 0 | J71: =0 -> 0 | K71: =0 -> 0 | L71: =0 -> 0 | M71: =0 -> 0 | N71: =0 -> 0 | O71: =0 -> 0 | ... U71: =0 -> 0
A72: mRNA-4359 contribution | B72: $B | C72: =C70*IF((C$35-Drivers!$C$109)<0,0,0.1+(Drivers!$C$110-0.1)*MIN((C$35-Drivers!$C$109)/5,1))-C71 -> -0.12 | D72: =D70*IF((D$35-Drivers!$C$109)<0,0,0.1+(Drivers!$C$110-0.1)*MIN((D$35-Drivers!$C$109)/5,1))-D71 -> -0.19083333 | E72: =E70*IF((E$35-Drivers!$C$109)<0,0,0.1+(Drivers!$C$110-0.1)*MIN((E$35-Drivers!$C$109)/5,1))-E71 -> -0.19083333 | F72: =F70*IF((F$35-Drivers!$C$109)<0,0,0.1+(Drivers!$C$110-0.1)*MIN((F$35-Drivers!$C$109)/5,1))-F71 -> -0.14083333 | G72: =G70*IF((G$35-Drivers!$C$109)<0,0,0.1+(Drivers!$C$110-0.1)*MIN((G$35-Drivers!$C$109)/5,1))-G71 -> -0.0784 | H72: =H70*IF((H$35-Drivers!$C$109)<0,0,0.1+(Drivers!$C$110-0.1)*MIN((H$35-Drivers!$C$109)/5,1))-H71 -> 0.0085 | I72: =I70*IF((I$35-Drivers!$C$109)<0,0,0.1+(Drivers!$C$110-0.1)*MIN((I$35-Drivers!$C$109)/5,1))-I71 -> 0.0216 | J72: =J70*IF((J$35-Drivers!$C$109)<0,0,0.1+(Drivers!$C$110-0.1)*MIN((J$35-Drivers!$C$109)/5,1))-J71 -> 0.0403 | ... U72: =U70*IF((U$35-Drivers!$C$109)<0,0,0.1+(Drivers!$C$110-0.1)*MIN((U$35-Drivers!$C$109)/5,1))-U71 -> 0.0677448
A73: PA sales (Recordati, risk-adjusted) | B73: $B | C73: =Drivers!$C$114*Drivers!$C$115*IF((C$35-Drivers!$C$116)<0,0,MIN(((C$35-Drivers!$C$116)+1)/5,1)) -> 0 | D73: =Drivers!$C$114*Drivers!$C$115*IF((D$35-Drivers!$C$116)<0,0,MIN(((D$35-Drivers!$C$116)+1)/5,1)) -> 0.044 | E73: =Drivers!$C$114*Drivers!$C$115*IF((E$35-Drivers!$C$116)<0,0,MIN(((E$35-Drivers!$C$116)+1)/5,1)) -> 0.088 | F73: =Drivers!$C$114*Drivers!$C$115*IF((F$35-Drivers!$C$116)<0,0,MIN(((F$35-Drivers!$C$116)+1)/5,1)) -> 0.132 | G73: =Drivers!$C$114*Drivers!$C$115*IF((G$35-Drivers!$C$116)<0,0,MIN(((G$35-Drivers!$C$116)+1)/5,1)) -> 0.176 | H73: =Drivers!$C$114*Drivers!$C$115*IF((H$35-Drivers!$C$116)<0,0,MIN(((H$35-Drivers!$C$116)+1)/5,1)) -> 0.22 | I73: =Drivers!$C$114*Drivers!$C$115*IF((I$35-Drivers!$C$116)<0,0,MIN(((I$35-Drivers!$C$116)+1)/5,1)) -> 0.22 | J73: =Drivers!$C$114*Drivers!$C$115*IF((J$35-Drivers!$C$116)<0,0,MIN(((J$35-Drivers!$C$116)+1)/5,1)) -> 0.22 | ... U73: =Drivers!$C$114*Drivers!$C$115*IF((U$35-Drivers!$C$116)<0,0,MIN(((U$35-Drivers!$C$116)+1)/5,1)) -> 0.22
A74: MMA sales (risk-adjusted) | B74: $B | C74: =Drivers!$C$120*Drivers!$C$121*IF((C$35-Drivers!$C$122)<0,0,MIN(((C$35-Drivers!$C$122)+1)/5,1)) -> 0 | D74: =Drivers!$C$120*Drivers!$C$121*IF((D$35-Drivers!$C$122)<0,0,MIN(((D$35-Drivers!$C$122)+1)/5,1)) -> 0 | E74: =Drivers!$C$120*Drivers!$C$121*IF((E$35-Drivers!$C$122)<0,0,MIN(((E$35-Drivers!$C$122)+1)/5,1)) -> 0 | F74: =Drivers!$C$120*Drivers!$C$121*IF((F$35-Drivers!$C$122)<0,0,MIN(((F$35-Drivers!$C$122)+1)/5,1)) -> 0 | G74: =Drivers!$C$120*Drivers!$C$121*IF((G$35-Drivers!$C$122)<0,0,MIN(((G$35-Drivers!$C$122)+1)/5,1)) -> 0.016 | H74: =Drivers!$C$120*Drivers!$C$121*IF((H$35-Drivers!$C$122)<0,0,MIN(((H$35-Drivers!$C$122)+1)/5,1)) -> 0.032 | I74: =Drivers!$C$120*Drivers!$C$121*IF((I$35-Drivers!$C$122)<0,0,MIN(((I$35-Drivers!$C$122)+1)/5,1)) -> 0.048 | J74: =Drivers!$C$120*Drivers!$C$121*IF((J$35-Drivers!$C$122)<0,0,MIN(((J$35-Drivers!$C$122)+1)/5,1)) -> 0.064 | ... U74: =Drivers!$C$120*Drivers!$C$121*IF((U$35-Drivers!$C$122)<0,0,MIN(((U$35-Drivers!$C$122)+1)/5,1)) -> 0.08
A75: CF royalty (risk-adjusted) | B75: $B | C75: =Drivers!$C$125*Drivers!$C$126*IF((C$35-Drivers!$C$127)<0,0,MIN(((C$35-Drivers!$C$127)+1)/5,1))*Drivers!$C$128 -> 0 | D75: =Drivers!$C$125*Drivers!$C$126*IF((D$35-Drivers!$C$127)<0,0,MIN(((D$35-Drivers!$C$127)+1)/5,1))*Drivers!$C$128 -> 0 | E75: =Drivers!$C$125*Drivers!$C$126*IF((E$35-Drivers!$C$127)<0,0,MIN(((E$35-Drivers!$C$127)+1)/5,1))*Drivers!$C$128 -> 0 | F75: =Drivers!$C$125*Drivers!$C$126*IF((F$35-Drivers!$C$127)<0,0,MIN(((F$35-Drivers!$C$127)+1)/5,1))*Drivers!$C$128 -> 0 | G75: =Drivers!$C$125*Drivers!$C$126*IF((G$35-Drivers!$C$127)<0,0,MIN(((G$35-Drivers!$C$127)+1)/5,1))*Drivers!$C$128 -> 0.0016 | H75: =Drivers!$C$125*Drivers!$C$126*IF((H$35-Drivers!$C$127)<0,0,MIN(((H$35-Drivers!$C$127)+1)/5,1))*Drivers!$C$128 -> 0.0032 | I75: =Drivers!$C$125*Drivers!$C$126*IF((I$35-Drivers!$C$127)<0,0,MIN(((I$35-Drivers!$C$127)+1)/5,1))*Drivers!$C$128 -> 0.0048 | J75: =Drivers!$C$125*Drivers!$C$126*IF((J$35-Drivers!$C$127)<0,0,MIN(((J$35-Drivers!$C$127)+1)/5,1))*Drivers!$C$128 -> 0.0064 | ... U75: =Drivers!$C$125*Drivers!$C$126*IF((U$35-Drivers!$C$127)<0,0,MIN(((U$35-Drivers!$C$127)+1)/5,1))*Drivers!$C$128 -> 0.008
A76: Rare disease & royalties contribution | B76: $B | C76: =C73*Drivers!$C$117+Drivers!$C$114*(Drivers!$C$118*(C$35=Drivers!$C$116)+Drivers!$C$119*(C$35=Drivers!$C$116+3))+C74*Drivers!$C$123-Drivers!$C$124*Drivers!$C$114*AND(C$35>=2027,C$35<=2030)+C75 -> -0.044 | D76: =D73*Drivers!$C$117+Drivers!$C$114*(Drivers!$C$118*(D$35=Drivers!$C$116)+Drivers!$C$119*(D$35=Drivers!$C$116+3))+D74*Drivers!$C$123-Drivers!$C$124*Drivers!$C$114*AND(D$35>=2027,D$35<=2030)+D75 -> 0.0231 | E76: =E73*Drivers!$C$117+Drivers!$C$114*(Drivers!$C$118*(E$35=Drivers!$C$116)+Drivers!$C$119*(E$35=Drivers!$C$116+3))+E74*Drivers!$C$123-Drivers!$C$124*Drivers!$C$114*AND(E$35>=2027,E$35<=2030)+E75 -> -0.0308 | F76: =F73*Drivers!$C$117+Drivers!$C$114*(Drivers!$C$118*(F$35=Drivers!$C$116)+Drivers!$C$119*(F$35=Drivers!$C$116+3))+F74*Drivers!$C$123-Drivers!$C$124*Drivers!$C$114*AND(F$35>=2027,F$35<=2030)+F75 -> -0.0242 | G76: =G73*Drivers!$C$117+Drivers!$C$114*(Drivers!$C$118*(G$35=Drivers!$C$116)+Drivers!$C$119*(G$35=Drivers!$C$116+3))+G74*Drivers!$C$123-Drivers!$C$124*Drivers!$C$114*AND(G$35>=2027,G$35<=2030)+G75 -> 0.091 | H76: =H73*Drivers!$C$117+Drivers!$C$114*(Drivers!$C$118*(H$35=Drivers!$C$116)+Drivers!$C$119*(H$35=Drivers!$C$116+3))+H74*Drivers!$C$123-Drivers!$C$124*Drivers!$C$114*AND(H$35>=2027,H$35<=2030)+H75 -> 0.0522 | I76: =I73*Drivers!$C$117+Drivers!$C$114*(Drivers!$C$118*(I$35=Drivers!$C$116)+Drivers!$C$119*(I$35=Drivers!$C$116+3))+I74*Drivers!$C$123-Drivers!$C$124*Drivers!$C$114*AND(I$35>=2027,I$35<=2030)+I75 -> 0.0618 | J76: =J73*Drivers!$C$117+Drivers!$C$114*(Drivers!$C$118*(J$35=Drivers!$C$116)+Drivers!$C$119*(J$35=Drivers!$C$116+3))+J74*Drivers!$C$123-Drivers!$C$124*Drivers!$C$114*AND(J$35>=2027,J$35<=2030)+J75 -> 0.0714 | ... U76: =U73*Drivers!$C$117+Drivers!$C$114*(Drivers!$C$118*(U$35=Drivers!$C$116)+Drivers!$C$119*(U$35=Drivers!$C$116+3))+U74*Drivers!$C$123-Drivers!$C$124*Drivers!$C$114*AND(U$35>=2027,U$35<=2030)+U75 -> 0.081
A77: CORPORATE, TAX & FREE CASH FLOW
A78: Corporate G&A | B78: $B | C78: =Drivers!$C$129*(1+Drivers!$C$130)^C$36 -> 0.42 | D78: =Drivers!$C$129*(1+Drivers!$C$130)^D$36 -> 0.4284 | E78: =Drivers!$C$129*(1+Drivers!$C$130)^E$36 -> 0.436968 | F78: =Drivers!$C$129*(1+Drivers!$C$130)^F$36 -> 0.44570736 | G78: =Drivers!$C$129*(1+Drivers!$C$130)^G$36 -> 0.45462151 | H78: =Drivers!$C$129*(1+Drivers!$C$130)^H$36 -> 0.46371394 | I78: =Drivers!$C$129*(1+Drivers!$C$130)^I$36 -> 0.47298822 | J78: =Drivers!$C$129*(1+Drivers!$C$130)^J$36 -> 0.48244798 | ... U78: =Drivers!$C$129*(1+Drivers!$C$130)^U$36 -> 0.59986342
A79: Unallocated R&D (before scenario multiplier) | B79: $B | C79: =Drivers!$D$131 -> 1.2 | D79: =Drivers!$E$131 -> 1.15 | E79: =Drivers!$F$131 -> 1.12 | F79: =Drivers!$G$131 -> 1.1 | G79: =Drivers!$H$131 -> 1.1 | H79: =Drivers!$I$131 -> 1.1 | I79: =H79*(1+Drivers!$C$132) -> 1.122 | J79: =I79*(1+Drivers!$C$132) -> 1.14444 | K79: =J79*(1+Drivers!$C$132) -> 1.1673288 | L79: =K79*(1+Drivers!$C$132) -> 1.1906754 | M79: =L79*(1+Drivers!$C$132) -> 1.2144889 | N79: =M79*(1+Drivers!$C$132) -> 1.2387787 | O79: =N79*(1+Drivers!$C$132) -> 1.2635542 | P79: =O79*(1+Drivers!$C$132) -> 1.2888253 | ... U79: =T79*(1+Drivers!$C$132) -> 1.4229673
A80: Unallocated R&D | B80: $B | C80: =C79*$C$17 -> 1.02 | D80: =D79*$C$17 -> 0.9775 | E80: =E79*$C$17 -> 0.952 | F80: =F79*$C$17 -> 0.935 | G80: =G79*$C$17 -> 0.935 | H80: =H79*$C$17 -> 0.935 | I80: =I79*$C$17 -> 0.9537 | J80: =J79*$C$17 -> 0.972774 | ... U80: =U79*$C$17 -> 1.2095222
A81: Attributable revenue (resp + 50% INT + other) | B81: $B | C81: =C44+Drivers!$C$85*C64+C70+C74+C73*Drivers!$C$117+C75 -> 2.00878 | D81: =D44+Drivers!$C$85*D64+D70+D74+D73*Drivers!$C$117+D75 -> 2.21241 | E81: =E44+Drivers!$C$85*E64+E70+E74+E73*Drivers!$C$117+E75 -> 2.5070713 | F81: =F44+Drivers!$C$85*F64+F70+F74+F73*Drivers!$C$117+F75 -> 2.8085763 | G81: =G44+Drivers!$C$85*G64+G70+G74+G73*Drivers!$C$117+G75 -> 3.2071493 | H81: =H44+Drivers!$C$85*H64+H70+H74+H73*Drivers!$C$117+H75 -> 3.4103365 | I81: =I44+Drivers!$C$85*I64+I70+I74+I73*Drivers!$C$117+I75 -> 3.6511362 | J81: =J44+Drivers!$C$85*J64+J70+J74+J73*Drivers!$C$117+J75 -> 3.842767 | ... U81: =U44+Drivers!$C$85*U64+U70+U74+U73*Drivers!$C$117+U75 -> 4.0586032
A82: Capex | B82: $B | C82: =Drivers!$D$134 -> 0.3 | D82: =Drivers!$E$134 -> 0.25 | E82: =Drivers!$F$134 -> 0.25 | F82: =Drivers!$G$134 -> 0.25 | G82: =Drivers!$H$134 -> 0.25 | H82: =Drivers!$I$134 -> 0.25 | I82: =Drivers!$C$135*I81 -> 0.14604545 | J82: =Drivers!$C$135*J81 -> 0.15371068 | K82: =Drivers!$C$135*K81 -> 0.16085357 | L82: =Drivers!$C$135*L81 -> 0.16694913 | M82: =Drivers!$C$135*M81 -> 0.17221256 | N82: =Drivers!$C$135*N81 -> 0.17525313 | O82: =Drivers!$C$135*O81 -> 0.17738695 | P82: =Drivers!$C$135*P81 -> 0.17459843 | ... U82: =Drivers!$C$135*U81 -> 0.16234413
A83: D&A | B83: $B | C83: =Drivers!$C$136 -> 0.23 | D83: =Drivers!$C$136 -> 0.23 | E83: =Drivers!$C$136 -> 0.23 | F83: =Drivers!$C$136 -> 0.23 | G83: =Drivers!$C$136 -> 0.23 | H83: =Drivers!$C$136 -> 0.23 | I83: =0.8*I82 -> 0.11683636 | J83: =0.8*J82 -> 0.12296854 | K83: =0.8*K82 -> 0.12868285 | L83: =0.8*L82 -> 0.13355931 | M83: =0.8*M82 -> 0.13777005 | N83: =0.8*N82 -> 0.14020251 | O83: =0.8*O82 -> 0.14190956 | P83: =0.8*P82 -> 0.13967874 | ... U83: =0.8*U82 -> 0.1298753
A84: Increase in working capital | B84: $B | C84: =Drivers!$C$82*(C81-Drivers!$C$35) -> -0.003122 | D84: =Drivers!$C$82*(D81-C81) -> 0.020363 | E84: =Drivers!$C$82*(E81-D81) -> 0.029466125 | F84: =Drivers!$C$82*(F81-E81) -> 0.0301505 | G84: =Drivers!$C$82*(G81-F81) -> 0.0398573 | H84: =Drivers!$C$82*(H81-G81) -> 0.020318725 | I84: =Drivers!$C$82*(I81-H81) -> 0.024079975 | J84: =Drivers!$C$82*(J81-I81) -> 0.019163075 | K84: =Drivers!$C$82*(K81-J81) -> 0.017857216 | ... U84: =Drivers!$C$82*(U81-T81) -> -0.0052512863
A85: EBIT | B85: $B | C85: =C52+C68+C72+C76-C78-C80 -> -1.9333658 | D85: =D52+D68+D72+D76-D78-D80 -> -1.6050125 | E85: =E52+E68+E72+E76-E78-E80 -> -1.3644615 | F85: =F52+F68+F72+F76-F78-F80 -> -1.044555 | G85: =G52+G68+G72+G76-G78-G80 -> -0.57323331 | H85: =H52+H68+H72+H76-H78-H80 -> -0.39723542 | I85: =I52+I68+I72+I76-I78-I80 -> -0.22032628 | J85: =J52+J68+J72+J76-J78-J80 -> -0.11012557 | ... U85: =U52+U68+U72+U76-U78-U80 -> -0.33954175
A86: NOL pool - opening | B86: $B | C86: =Drivers!$C$32 -> 12.5 | D86: =C89 -> 14.433366 | E86: =D89 -> 16.038378 | F86: =E89 -> 17.40284 | G86: =F89 -> 18.447395 | H86: =G89 -> 19.020628 | I86: =H89 -> 19.417864 | J86: =I89 -> 19.63819 | K86: =J89 -> 19.748315 | ... U86: =T89 -> 19.741455
A87: NOL used | B87: $B | C87: =IF(C85>0,MIN(C86,Drivers!$C$33*C85),0) -> 0 | D87: =IF(D85>0,MIN(D86,Drivers!$C$33*D85),0) -> 0 | E87: =IF(E85>0,MIN(E86,Drivers!$C$33*E85),0) -> 0 | F87: =IF(F85>0,MIN(F86,Drivers!$C$33*F85),0) -> 0 | G87: =IF(G85>0,MIN(G86,Drivers!$C$33*G85),0) -> 0 | H87: =IF(H85>0,MIN(H86,Drivers!$C$33*H85),0) -> 0 | I87: =IF(I85>0,MIN(I86,Drivers!$C$33*I85),0) -> 0 | J87: =IF(J85>0,MIN(J86,Drivers!$C$33*J85),0) -> 0 | ... U87: =IF(U85>0,MIN(U86,Drivers!$C$33*U85),0) -> 0
A88: Cash taxes | B88: $B | C88: =IF(C85>0,Drivers!$C$31*(C85-C87),0) -> 0 | D88: =IF(D85>0,Drivers!$C$31*(D85-D87),0) -> 0 | E88: =IF(E85>0,Drivers!$C$31*(E85-E87),0) -> 0 | F88: =IF(F85>0,Drivers!$C$31*(F85-F87),0) -> 0 | G88: =IF(G85>0,Drivers!$C$31*(G85-G87),0) -> 0 | H88: =IF(H85>0,Drivers!$C$31*(H85-H87),0) -> 0 | I88: =IF(I85>0,Drivers!$C$31*(I85-I87),0) -> 0 | J88: =IF(J85>0,Drivers!$C$31*(J85-J87),0) -> 0 | ... U88: =IF(U85>0,Drivers!$C$31*(U85-U87),0) -> 0
A89: NOL pool - closing | B89: $B | C89: =C86-C87+IF(C85<0,-C85,0) -> 14.433366 | D89: =D86-D87+IF(D85<0,-D85,0) -> 16.038378 | E89: =E86-E87+IF(E85<0,-E85,0) -> 17.40284 | F89: =F86-F87+IF(F85<0,-F85,0) -> 18.447395 | G89: =G86-G87+IF(G85<0,-G85,0) -> 19.020628 | H89: =H86-H87+IF(H85<0,-H85,0) -> 19.417864 | I89: =I86-I87+IF(I85<0,-I85,0) -> 19.63819 | J89: =J86-J87+IF(J85<0,-J85,0) -> 19.748315 | ... U89: =U86-U87+IF(U85<0,-U85,0) -> 20.080996
A90: Free cash flow to firm | B90: $B | C90: =C85-C88-(C82-C83)-C84 -> -2.0002438 | D90: =D85-D88-(D82-D83)-D84 -> -1.6453755 | E90: =E85-E88-(E82-E83)-E84 -> -1.4139276 | F90: =F85-F88-(F82-F83)-F84 -> -1.0947055 | G90: =G85-G88-(G82-G83)-G84 -> -0.63309061 | H90: =H85-H88-(H82-H83)-H84 -> -0.43755414 | I90: =I85-I88-(I82-I83)-I84 -> -0.27361534 | J90: =J85-J88-(J82-J83)-J84 -> -0.16003078 | ... U90: =U85-U88-(U82-U83)-U84 -> -0.36675929
A91: Discount period (mid-year, from 9/30/26) | B91: yrs | C91: =0.25+C$36+0.5 -> 0.75 | D91: =0.25+D$36+0.5 -> 1.75 | E91: =0.25+E$36+0.5 -> 2.75 | F91: =0.25+F$36+0.5 -> 3.75 | G91: =0.25+G$36+0.5 -> 4.75 | H91: =0.25+H$36+0.5 -> 5.75 | I91: =0.25+I$36+0.5 -> 6.75 | J91: =0.25+J$36+0.5 -> 7.75 | ... U91: =0.25+U$36+0.5 -> 18.75
A92: Discount factor | B92: x | C92: =(1+$C$19)^(-C91) -> 0.92829219 | D92: =(1+$C$19)^(-D91) -> 0.84061595 | E92: =(1+$C$19)^(-E91) -> 0.76122063 | F92: =(1+$C$19)^(-F91) -> 0.68932413 | G92: =(1+$C$19)^(-G91) -> 0.62421817 | H92: =(1+$C$19)^(-H91) -> 0.56526141 | I92: =(1+$C$19)^(-I91) -> 0.51187305 | J92: =(1+$C$19)^(-J91) -> 0.46352716 | ... U92: =(1+$C$19)^(-U91) -> 0.15563863
A93: PV of FCFF | B93: $B | C93: =C90*C92 -> -1.8568107 | D93: =D90*D92 -> -1.3831289 | E93: =E90*E92 -> -1.0763109 | F93: =F90*F92 -> -0.75460689 | G93: =G90*G92 -> -0.39518667 | H93: =H90*H92 -> -0.24733247 | I93: =I90*I92 -> -0.14005632 | J93: =J90*J92 -> -0.074178614 | ... U93: =U90*U92 -> -0.057081913
A94: R&D creating future pipeline (credit base) | B94: $B | C94: =IF(C$35<=2032,Drivers!$C$133*C80,C80) -> 0.357 | D94: =IF(D$35<=2032,Drivers!$C$133*D80,D80) -> 0.342125 | E94: =IF(E$35<=2032,Drivers!$C$133*E80,E80) -> 0.3332 | F94: =IF(F$35<=2032,Drivers!$C$133*F80,F80) -> 0.32725 | G94: =IF(G$35<=2032,Drivers!$C$133*G80,G80) -> 0.32725 | H94: =IF(H$35<=2032,Drivers!$C$133*H80,H80) -> 0.32725 | I94: =IF(I$35<=2032,Drivers!$C$133*I80,I80) -> 0.9537 | J94: =IF(J$35<=2032,Drivers!$C$133*J80,J80) -> 0.972774 | ... U94: =IF(U$35<=2032,Drivers!$C$133*U80,U80) -> 1.2095222
A96: VALUATION
A97: PV of Q4-2026 stub FCF | C97: =Drivers!$C$34*(1+$C$19)^(-0.125) -> -0.45433056
A98: PV of FCFF 2027-2045 | C98: =SUM(C93:U93) -> -5.9977027
A99: Terminal value at end-2045 | C99: =U90*(1+$C$20)/($C$19-$C$20) -> -3.1766553
A100: PV of terminal value | C100: =$C$99*(1+$C$19)^(-19.25) -> -0.47048301
A101: PV of pipeline-creating R&D (incl. terminal) | C101: =SUMPRODUCT(C94:U94,C92:U92)+U94*(1+$C$20)/($C$19-$C$20)*(1+$C$19)^(-19.25) -> 7.1562207
A102: Unidentified future pipeline (credit) | C102: =$C$18*$C$101*(1-Drivers!$C$31) -> 2.8982694
A103: Enterprise value | C103: =$C$97+$C$98+$C$100+$C$102 -> -4.0242469
...

Sheet M_Base
A1: M_Base - scenario model (Assumptions as listed: melanoma launch 2027, US net ~$300k, $2.8B global peak; other indications at stated PoS; respiratory bottom-up.)
A2: Scenario index (1=Failure..5=Blue-sky) | C2: 3
A4: Scenario levers (green = pulled from Drivers)
A5: COVID revenue multiplier | C5: =INDEX(Drivers!$D$39:$H$39,$C$2) -> 1
A6: Flu (mFLUSIVA) peak multiplier | C6: =INDEX(Drivers!$D$40:$H$40,$C$2) -> 1
A7: Flu+COVID combo peak multiplier | C7: =INDEX(Drivers!$D$41:$H$41,$C$2) -> 1
A8: Norovirus PoS | C8: =INDEX(Drivers!$D$42:$H$42,$C$2) -> 0.3
A9: Respiratory gross-margin shift | C9: =INDEX(Drivers!$D$43:$H$43,$C$2) -> 0
A10: INT melanoma PoS | C10: =INDEX(Drivers!$D$44:$H$44,$C$2) -> 0.88
A11: INT melanoma peak global sales ($B, before price factor) | C11: =INDEX(Drivers!$D$45:$H$45,$C$2) -> 2.8
A12: INT melanoma launch year | C12: =INDEX(Drivers!$D$46:$H$46,$C$2) -> 2027
A13: INT other-indication PoS multiplier (>=10 => all 100%) | C13: =INDEX(Drivers!$D$47:$H$47,$C$2) -> 1
A14: INT other-indication peak multiplier | C14: =INDEX(Drivers!$D$48:$H$48,$C$2) -> 1
A15: INT price factor (1.0 = US net ~$300k) | C15: =INDEX(Drivers!$D$49:$H$49,$C$2) -> 1
A16: INT mature profit-pool margin | C16: =INDEX(Drivers!$D$50:$H$50,$C$2) -> 0.55
A17: Unallocated R&D multiplier | C17: =INDEX(Drivers!$D$51:$H$51,$C$2) -> 1
A18: Future-pipeline credit factor | C18: =INDEX(Drivers!$D$52:$H$52,$C$2) -> 0.75
A19: WACC | C19: =INDEX(Drivers!$D$53:$H$53,$C$2) -> 0.1043
A20: Terminal growth | C20: =INDEX(Drivers!$D$54:$H$54,$C$2) -> 0
A21: Other patent litigation (expected cost) | C21: =INDEX(Drivers!$D$55:$H$55,$C$2) -> 0.5
A22: INT indications: scenario-adjusted launch / peak / PoS
A23: Indication | C23: Launch | D23: Peak | E23: PoS
A24: =Drivers!$B$95 -> Adjuvant melanoma IIB-IV (INTerpath-001) | C24: =$C$12 -> 2027 | D24: =$C$11 -> 2.8 | E24: =$C$10 -> 0.88
A25: =Drivers!$B$96 -> Adjuvant NSCLC II-IIIB (INTerpath-002) | C25: =Drivers!$D$96 -> 2031 | D25: =Drivers!$E$96*$C$14 -> 4 | E25: =MIN(Drivers!$F$96*$C$13,IF($C$13>=10,1,0.95)) -> 0.45
A26: =Drivers!$B$97 -> Post-neoadjuvant non-pCR NSCLC (INTerpath-009) | C26: =Drivers!$D$97 -> 2034 | D26: =Drivers!$E$97*$C$14 -> 1.5 | E26: =MIN(Drivers!$F$97*$C$13,IF($C$13>=10,1,0.95)) -> 0.4
A27: =Drivers!$B$98 -> Resected stage I NSCLC (INTerpath-014) | C27: =Drivers!$D$98 -> 2035 | D27: =Drivers!$E$98*$C$14 -> 2.5 | E27: =MIN(Drivers!$F$98*$C$13,IF($C$13>=10,1,0.95)) -> 0.35
A28: =Drivers!$B$99 -> Adjuvant RCC (INTerpath-004) | C28: =Drivers!$D$99 -> 2031 | D28: =Drivers!$E$99*$C$14 -> 1.2 | E28: =MIN(Drivers!$F$99*$C$13,IF($C$13>=10,1,0.95)) -> 0.25
A29: =Drivers!$B$100 -> MIBC adjuvant (INTerpath-005) | C29: =Drivers!$D$100 -> 2033 | D29: =Drivers!$E$100*$C$14 -> 1 | E29: =MIN(Drivers!$F$100*$C$13,IF($C$13>=10,1,0.95)) -> 0.2
A30: =Drivers!$B$101 -> NMIBC + BCG (INTerpath-011) | C30: =Drivers!$D$101 -> 2034 | D30: =Drivers!$E$101*$C$14 -> 1 | E30: =MIN(Drivers!$F$101*$C$13,IF($C$13>=10,1,0.95)) -> 0.15
A31: =Drivers!$B$102 -> 1L advanced melanoma (INTerpath-012) | C31: =Drivers!$D$102 -> 2031 | D31: =Drivers!$E$102*$C$14 -> 0.8 | E31: =MIN(Drivers!$F$102*$C$13,IF($C$13>=10,1,0.95)) -> 0.2
A32: =Drivers!$B$103 -> 1L metastatic squamous NSCLC (INTerpath-013) | C32: =Drivers!$D$103 -> 2032 | D32: =Drivers!$E$103*$C$14 -> 1.2 | E32: =MIN(Drivers!$F$103*$C$13,IF($C$13>=10,1,0.95)) -> 0.15
A33: =Drivers!$B$104 -> Other solid tumours - future INT indications (pre-Ph2) | C33: =Drivers!$D$104 -> 2035 | D33: =Drivers!$E$104*$C$14 -> 6 | E33: =MIN(Drivers!$F$104*$C$13,IF($C$13>=10,1,0.95)) -> 0.1
A35: Year | B35: unit | C35: 2027 | D35: 2028 | E35: 2029 | F35: 2030 | G35: 2031 | H35: 2032 | I35: 2033 | J35: 2034 | K35: 2035 | L35: 2036 | M35: 2037 | N35: 2038 | O35: 2039 | P35: 2040 | Q35: 2041 | R35: 2042 | S35: 2043 | T35: 2044 | U35: 2045
A36: Year index i | C36: 0 | D36: 1 | E36: 2 | F36: 3 | G36: 4 | H36: 5 | I36: 6 | J36: 7 | K36: 8 | L36: 9 | M36: 10 | N36: 11 | O36: 12 | P36: 13 | Q36: 14 | R36: 15 | S36: 16 | T36: 17 | U36: 18
A37: RESPIRATORY FRANCHISE
A38: COVID (Spikevax, mNEXSPIKE, partnerships) | B38: $B | C38: =Drivers!$D$60*$C$5 -> 1.85 | D38: =Drivers!$E$60*$C$5 -> 1.7 | E38: =Drivers!$F$60*$C$5 -> 1.55 | F38: =Drivers!$G$60*$C$5 -> 1.45 | G38: =Drivers!$H$60*$C$5 -> 1.38 | H38: =Drivers!$I$60*$C$5 -> 1.3 | I38: =H38*(1+Drivers!$C$61) -> 1.274 | J38: =I38*(1+Drivers!$C$61) -> 1.24852 | K38: =J38*(1+Drivers!$C$61) -> 1.2235496 | L38: =K38*(1+Drivers!$C$61) -> 1.1990786 | M38: =L38*(1+Drivers!$C$61) -> 1.175097 | N38: =M38*(1+Drivers!$C$61) -> 1.1515951 | O38: =N38*(1+Drivers!$C$61) -> 1.1285632 | P38: =O38*(1+Drivers!$C$61) -> 1.1059919 | ... U38: =T38*(1+Drivers!$C$61) -> 0.99972911
A39: Flu (mFLUSIVA) | B39: $B | C39: =Drivers!$C$62*IF((C$35-Drivers!$C$63)<0,0,MIN(((C$35-Drivers!$C$63)+1)/Drivers!$C$64,1))*$C$6 -> 0.16 | D39: =Drivers!$C$62*IF((D$35-Drivers!$C$63)<0,0,MIN(((D$35-Drivers!$C$63)+1)/Drivers!$C$64,1))*$C$6 -> 0.32 | E39: =Drivers!$C$62*IF((E$35-Drivers!$C$63)<0,0,MIN(((E$35-Drivers!$C$63)+1)/Drivers!$C$64,1))*$C$6 -> 0.48 | F39: =Drivers!$C$62*IF((F$35-Drivers!$C$63)<0,0,MIN(((F$35-Drivers!$C$63)+1)/Drivers!$C$64,1))*$C$6 -> 0.64 | G39: =Drivers!$C$62*IF((G$35-Drivers!$C$63)<0,0,MIN(((G$35-Drivers!$C$63)+1)/Drivers!$C$64,1))*$C$6 -> 0.8 | H39: =Drivers!$C$62*IF((H$35-Drivers!$C$63)<0,0,MIN(((H$35-Drivers!$C$63)+1)/Drivers!$C$64,1))*$C$6 -> 0.8 | I39: =Drivers!$C$62*IF((I$35-Drivers!$C$63)<0,0,MIN(((I$35-Drivers!$C$63)+1)/Drivers!$C$64,1))*$C$6 -> 0.8 | J39: =Drivers!$C$62*IF((J$35-Drivers!$C$63)<0,0,MIN(((J$35-Drivers!$C$63)+1)/Drivers!$C$64,1))*$C$6 -> 0.8 | ... U39: =Drivers!$C$62*IF((U$35-Drivers!$C$63)<0,0,MIN(((U$35-Drivers!$C$63)+1)/Drivers!$C$64,1))*$C$6 -> 0.8
A40: Flu+COVID combo (mCOMBRIAX) | B40: $B | C40: =Drivers!$C$65*IF((C$35-Drivers!$C$66)<0,0,MIN(((C$35-Drivers!$C$66)+1)/Drivers!$C$67,1))*$C$7*((1-Drivers!$C$69)+Drivers!$C$69*Drivers!$C$68) -> 0.2338 | D40: =Drivers!$C$65*IF((D$35-Drivers!$C$66)<0,0,MIN(((D$35-Drivers!$C$66)+1)/Drivers!$C$67,1))*$C$7*((1-Drivers!$C$69)+Drivers!$C$69*Drivers!$C$68) -> 0.4676 | E40: =Drivers!$C$65*IF((E$35-Drivers!$C$66)<0,0,MIN(((E$35-Drivers!$C$66)+1)/Drivers!$C$67,1))*$C$7*((1-Drivers!$C$69)+Drivers!$C$69*Drivers!$C$68) -> 0.7014 | F40: =Drivers!$C$65*IF((F$35-Drivers!$C$66)<0,0,MIN(((F$35-Drivers!$C$66)+1)/Drivers!$C$67,1))*$C$7*((1-Drivers!$C$69)+Drivers!$C$69*Drivers!$C$68) -> 0.9352 | G40: =Drivers!$C$65*IF((G$35-Drivers!$C$66)<0,0,MIN(((G$35-Drivers!$C$66)+1)/Drivers!$C$67,1))*$C$7*((1-Drivers!$C$69)+Drivers!$C$69*Drivers!$C$68) -> 1.169 | H40: =Drivers!$C$65*IF((H$35-Drivers!$C$66)<0,0,MIN(((H$35-Drivers!$C$66)+1)/Drivers!$C$67,1))*$C$7*((1-Drivers!$C$69)+Drivers!$C$69*Drivers!$C$68) -> 1.169 | I40: =Drivers!$C$65*IF((I$35-Drivers!$C$66)<0,0,MIN(((I$35-Drivers!$C$66)+1)/Drivers!$C$67,1))*$C$7*((1-Drivers!$C$69)+Drivers!$C$69*Drivers!$C$68) -> 1.169 | J40: =Drivers!$C$65*IF((J$35-Drivers!$C$66)<0,0,MIN(((J$35-Drivers!$C$66)+1)/Drivers!$C$67,1))*$C$7*((1-Drivers!$C$69)+Drivers!$C$69*Drivers!$C$68) -> 1.169 | ... U40: =Drivers!$C$65*IF((U$35-Drivers!$C$66)<0,0,MIN(((U$35-Drivers!$C$66)+1)/Drivers!$C$67,1))*$C$7*((1-Drivers!$C$69)+Drivers!$C$69*Drivers!$C$68) -> 1.169
A41: RSV (mRESVIA) | B41: $B | C41: =Drivers!$C$70*MIN((C$35-2026)/3,1) -> 0.05 | D41: =Drivers!$C$70*MIN((D$35-2026)/3,1) -> 0.1 | E41: =Drivers!$C$70*MIN((E$35-2026)/3,1) -> 0.15 | F41: =Drivers!$C$70*MIN((F$35-2026)/3,1) -> 0.15 | G41: =Drivers!$C$70*MIN((G$35-2026)/3,1) -> 0.15 | H41: =Drivers!$C$70*MIN((H$35-2026)/3,1) -> 0.15 | I41: =Drivers!$C$70*MIN((I$35-2026)/3,1) -> 0.15 | J41: =Drivers!$C$70*MIN((J$35-2026)/3,1) -> 0.15 | ... U41: =Drivers!$C$70*MIN((U$35-2026)/3,1) -> 0.15
A42: Norovirus (risk-adjusted) | B42: $B | C42: =$C$8*Drivers!$C$71*IF((C$35-Drivers!$C$72)<0,0,MIN(((C$35-Drivers!$C$72)+1)/Drivers!$C$73,1)) -> 0 | D42: =$C$8*Drivers!$C$71*IF((D$35-Drivers!$C$72)<0,0,MIN(((D$35-Drivers!$C$72)+1)/Drivers!$C$73,1)) -> 0 | E42: =$C$8*Drivers!$C$71*IF((E$35-Drivers!$C$72)<0,0,MIN(((E$35-Drivers!$C$72)+1)/Drivers!$C$73,1)) -> 0.072 | F42: =$C$8*Drivers!$C$71*IF((F$35-Drivers!$C$72)<0,0,MIN(((F$35-Drivers!$C$72)+1)/Drivers!$C$73,1)) -> 0.144 | G42: =$C$8*Drivers!$C$71*IF((G$35-Drivers!$C$72)<0,0,MIN(((G$35-Drivers!$C$72)+1)/Drivers!$C$73,1)) -> 0.216 | H42: =$C$8*Drivers!$C$71*IF((H$35-Drivers!$C$72)<0,0,MIN(((H$35-Drivers!$C$72)+1)/Drivers!$C$73,1)) -> 0.288 | I42: =$C$8*Drivers!$C$71*IF((I$35-Drivers!$C$72)<0,0,MIN(((I$35-Drivers!$C$72)+1)/Drivers!$C$73,1)) -> 0.36 | J42: =$C$8*Drivers!$C$71*IF((J$35-Drivers!$C$72)<0,0,MIN(((J$35-Drivers!$C$72)+1)/Drivers!$C$73,1)) -> 0.36 | ... U42: =$C$8*Drivers!$C$71*IF((U$35-Drivers!$C$72)<0,0,MIN(((U$35-Drivers!$C$72)+1)/Drivers!$C$73,1)) -> 0.36
A43: Other revenue | B43: $B | C43: =Drivers!$C$74 -> 0.15 | D43: =Drivers!$C$74 -> 0.15 | E43: =Drivers!$C$74 -> 0.15 | F43: =Drivers!$C$74 -> 0.15 | G43: =Drivers!$C$74 -> 0.15 | H43: =Drivers!$C$74 -> 0.15 | I43: =Drivers!$C$74 -> 0.15 | J43: =Drivers!$C$74 -> 0.15 | ... U43: =Drivers!$C$74 -> 0.15
A44: Respiratory revenue | B44: $B | C44: =SUM(C38:C43) -> 2.4438 | D44: =SUM(D38:D43) -> 2.7376 | E44: =SUM(E38:E43) -> 3.1034 | F44: =SUM(F38:F43) -> 3.4692 | G44: =SUM(G38:G43) -> 3.865 | H44: =SUM(H38:H43) -> 3.857 | I44: =SUM(I38:I43) -> 3.903 | J44: =SUM(J38:J43) -> 3.87752 | ... U44: =SUM(U38:U43) -> 3.6287291
A45: Gross margin | B45: % | C45: =Drivers!$D$75+$C$9 -> 0.64 | D45: =Drivers!$E$75+$C$9 -> 0.68 | E45: =Drivers!$F$75+$C$9 -> 0.71 | F45: =Drivers!$G$75+$C$9 -> 0.73 | G45: =Drivers!$H$75+$C$9 -> 0.74 | H45: =Drivers!$I$75+$C$9 -> 0.75 | I45: =Drivers!$I$75+$C$9 -> 0.75 | J45: =Drivers!$I$75+$C$9 -> 0.75 | K45: =Drivers!$I$75+$C$9 -> 0.75 | L45: =Drivers!$I$75+$C$9 -> 0.75 | M45: =Drivers!$I$75+$C$9 -> 0.75 | N45: =Drivers!$I$75+$C$9 -> 0.75 | O45: =Drivers!$I$75+$C$9 -> 0.75 | ... U45: =Drivers!$I$75+$C$9 -> 0.75
A46: Flu + combo revenue | B46: $B | C46: =C39+C40 -> 0.3938 | D46: =D39+D40 -> 0.7876 | E46: =E39+E40 -> 1.1814 | F46: =F39+F40 -> 1.5752 | G46: =G39+G40 -> 1.969 | H46: =H39+H40 -> 1.969 | I46: =I39+I40 -> 1.969 | J46: =J39+J40 -> 1.969 | ... U46: =U39+U40 -> 1.969
A47: Blackstone sales milestones paid | B47: $B | C47: =MIN(Drivers!$C$77-0,Drivers!$C$78*C46) -> 0.031504 | D47: =MIN(Drivers!$C$77-C48,Drivers!$C$78*D46) -> 0.063008 | E47: =MIN(Drivers!$C$77-D48,Drivers!$C$78*E46) -> 0.094512 | F47: =MIN(Drivers!$C$77-E48,Drivers!$C$78*F46) -> 0.126016 | G47: =MIN(Drivers!$C$77-F48,Drivers!$C$78*G46) -> 0.15752 | H47: =MIN(Drivers!$C$77-G48,Drivers!$C$78*H46) -> 0.15752 | I47: =MIN(Drivers!$C$77-H48,Drivers!$C$78*I46) -> 0.11992 | J47: =MIN(Drivers!$C$77-I48,Drivers!$C$78*J46) -> 0 | K47: =MIN(Drivers!$C$77-J48,Drivers!$C$78*K46) -> 0 | ... U47: =MIN(Drivers!$C$77-T48,Drivers!$C$78*U46) -> 0
A48: Blackstone milestones cumulative | B48: $B | C48: =C47 -> 0.031504 | D48: =C48+D47 -> 0.094512 | E48: =D48+E47 -> 0.189024 | F48: =E48+F47 -> 0.31504 | G48: =F48+G47 -> 0.47256 | H48: =G48+H47 -> 0.63008 | I48: =H48+I47 -> 0.75 | J48: =I48+J47 -> 0.75 | K48: =J48+K47 -> 0.75 | ... U48: =T48+U47 -> 0.75
A49: Blackstone royalty + milestones | B49: $B | C49: =Drivers!$C$76*C46+C47 -> 0.041349 | D49: =Drivers!$C$76*D46+D47 -> 0.082698 | E49: =Drivers!$C$76*E46+E47 -> 0.124047 | F49: =Drivers!$C$76*F46+F47 -> 0.165396 | G49: =Drivers!$C$76*G46+G47 -> 0.206745 | H49: =Drivers!$C$76*H46+H47 -> 0.206745 | I49: =Drivers!$C$76*I46+I47 -> 0.169145 | J49: =Drivers!$C$76*J46+J47 -> 0.049225 | ... U49: =Drivers!$C$76*U46+U47 -> 0.049225
A50: Respiratory S&M | B50: $B | C50: =MAX(Drivers!$C$80,Drivers!$C$79*C44) -> 0.4 | D50: =MAX(Drivers!$C$80,Drivers!$C$79*D44) -> 0.4 | E50: =MAX(Drivers!$C$80,Drivers!$C$79*E44) -> 0.434476 | F50: =MAX(Drivers!$C$80,Drivers!$C$79*F44) -> 0.485688 | G50: =MAX(Drivers!$C$80,Drivers!$C$79*G44) -> 0.5411 | H50: =MAX(Drivers!$C$80,Drivers!$C$79*H44) -> 0.53998 | I50: =MAX(Drivers!$C$80,Drivers!$C$79*I44) -> 0.54642 | J50: =MAX(Drivers!$C$80,Drivers!$C$79*J44) -> 0.5428528 | ... U50: =MAX(Drivers!$C$80,Drivers!$C$79*U44) -> 0.50802207
A51: Respiratory R&D | B51: $B | C51: =Drivers!$D$81 -> 0.75 | D51: =Drivers!$E$81 -> 0.62 | E51: =Drivers!$F$81 -> 0.55 | F51: =Drivers!$G$81 -> 0.5 | G51: =Drivers!$H$81 -> 0.48 | H51: =Drivers!$I$81 -> 0.46 | I51: =H51*1.02 -> 0.4692 | J51: =I51*1.02 -> 0.478584 | K51: =J51*1.02 -> 0.48815568 | L51: =K51*1.02 -> 0.49791879 | M51: =L51*1.02 -> 0.50787717 | N51: =M51*1.02 -> 0.51803471 | O51: =N51*1.02 -> 0.52839541 | P51: =O51*1.02 -> 0.53896332 | ... U51: =T51*1.02 -> 0.59505905
A52: Respiratory contribution | B52: $B | C52: =C44*C45-C49-C50-C51 -> 0.372683 | D52: =D44*D45-D49-D50-D51 -> 0.75887 | E52: =E44*E45-E49-E50-E51 -> 1.094891 | F52: =F44*F45-F49-F50-F51 -> 1.381432 | G52: =G44*G45-G49-G50-G51 -> 1.632255 | H52: =H44*H45-H49-H50-H51 -> 1.686025 | I52: =I44*I45-I49-I50-I51 -> 1.742485 | J52: =J44*J45-J49-J50-J51 -> 1.8374782 | ... U52: =U44*U45-U49-U50-U51 -> 1.5692407
A53: INTISMERAN (risk-adjusted global sales; Moderna books 50% of profit pool)
A54: Adjuvant melanoma IIB-IV (INTerpath-001) | B54: $B | C54: =$D$24*$C$15*IF((C$35-$C$24)<0,0,IF((C$35-$C$24)>=7,1,INDEX(Drivers!$D$86:$J$86,(C$35-$C$24)+1)))*IF((C$35-$C$24)<Drivers!$C$87,1,Drivers!$C$88*Drivers!$C$89^((C$35-$C$24)-Drivers!$C$87))*$E$24 -> 0.19712 | D54: =$D$24*$C$15*IF((D$35-$C$24)<0,0,IF((D$35-$C$24)>=7,1,INDEX(Drivers!$D$86:$J$86,(D$35-$C$24)+1)))*IF((D$35-$C$24)<Drivers!$C$87,1,Drivers!$C$88*Drivers!$C$89^((D$35-$C$24)-Drivers!$C$87))*$E$24 -> 0.616 | E54: =$D$24*$C$15*IF((E$35-$C$24)<0,0,IF((E$35-$C$24)>=7,1,INDEX(Drivers!$D$86:$J$86,(E$35-$C$24)+1)))*IF((E$35-$C$24)<Drivers!$C$87,1,Drivers!$C$88*Drivers!$C$89^((E$35-$C$24)-Drivers!$C$87))*$E$24 -> 1.1088 | F54: =$D$24*$C$15*IF((F$35-$C$24)<0,0,IF((F$35-$C$24)>=7,1,INDEX(Drivers!$D$86:$J$86,(F$35-$C$24)+1)))*IF((F$35-$C$24)<Drivers!$C$87,1,Drivers!$C$88*Drivers!$C$89^((F$35-$C$24)-Drivers!$C$87))*$E$24 -> 1.6016 | G54: =$D$24*$C$15*IF((G$35-$C$24)<0,0,IF((G$35-$C$24)>=7,1,INDEX(Drivers!$D$86:$J$86,(G$35-$C$24)+1)))*IF((G$35-$C$24)<Drivers!$C$87,1,Drivers!$C$88*Drivers!$C$89^((G$35-$C$24)-Drivers!$C$87))*$E$24 -> 2.02048 | H54: =$D$24*$C$15*IF((H$35-$C$24)<0,0,IF((H$35-$C$24)>=7,1,INDEX(Drivers!$D$86:$J$86,(H$35-$C$24)+1)))*IF((H$35-$C$24)<Drivers!$C$87,1,Drivers!$C$88*Drivers!$C$89^((H$35-$C$24)-Drivers!$C$87))*$E$24 -> 2.29152 | I54: =$D$24*$C$15*IF((I$35-$C$24)<0,0,IF((I$35-$C$24)>=7,1,INDEX(Drivers!$D$86:$J$86,(I$35-$C$24)+1)))*IF((I$35-$C$24)<Drivers!$C$87,1,Drivers!$C$88*Drivers!$C$89^((I$35-$C$24)-Drivers!$C$87))*$E$24 -> 2.464 | J54: =$D$24*$C$15*IF((J$35-$C$24)<0,0,IF((J$35-$C$24)>=7,1,INDEX(Drivers!$D$86:$J$86,(J$35-$C$24)+1)))*IF((J$35-$C$24)<Drivers!$C$87,1,Drivers!$C$88*Drivers!$C$89^((J$35-$C$24)-Drivers!$C$87))*$E$24 -> 2.464 | ... U54: =$D$24*$C$15*IF((U$35-$C$24)<0,0,IF((U$35-$C$24)>=7,1,INDEX(Drivers!$D$86:$J$86,(U$35-$C$24)+1)))*IF((U$35-$C$24)<Drivers!$C$87,1,Drivers!$C$88*Drivers!$C$89^((U$35-$C$24)-Drivers!$C$87))*$E$24 -> 1.6419544
A55: Adjuvant NSCLC II-IIIB (INTerpath-002) | B55: $B | C55: =$D$25*$C$15*IF((C$35-$C$25)<0,0,IF((C$35-$C$25)>=7,1,INDEX(Drivers!$D$86:$J$86,(C$35-$C$25)+1)))*IF((C$35-$C$25)<Drivers!$C$87,1,Drivers!$C$88*Drivers!$C$89^((C$35-$C$25)-Drivers!$C$87))*$E$25 -> 0 | D55: =$D$25*$C$15*IF((D$35-$C$25)<0,0,IF((D$35-$C$25)>=7,1,INDEX(Drivers!$D$86:$J$86,(D$35-$C$25)+1)))*IF((D$35-$C$25)<Drivers!$C$87,1,Drivers!$C$88*Drivers!$C$89^((D$35-$C$25)-Drivers!$C$87))*$E$25 -> 0 | E55: =$D$25*$C$15*IF((E$35-$C$25)<0,0,IF((E$35-$C$25)>=7,1,INDEX(Drivers!$D$86:$J$86,(E$35-$C$25)+1)))*IF((E$35-$C$25)<Drivers!$C$87,1,Drivers!$C$88*Drivers!$C$89^((E$35-$C$25)-Drivers!$C$87))*$E$25 -> 0 | F55: =$D$25*$C$15*IF((F$35-$C$25)<0,0,IF((F$35-$C$25)>=7,1,INDEX(Drivers!$D$86:$J$86,(F$35-$C$25)+1)))*IF((F$35-$C$25)<Drivers!$C$87,1,Drivers!$C$88*Drivers!$C$89^((F$35-$C$25)-Drivers!$C$87))*$E$25 -> 0 | G55: =$D$25*$C$15*IF((G$35-$C$25)<0,0,IF((G$35-$C$25)>=7,1,INDEX(Drivers!$D$86:$J$86,(G$35-$C$25)+1)))*IF((G$35-$C$25)<Drivers!$C$87,1,Drivers!$C$88*Drivers!$C$89^((G$35-$C$25)-Drivers!$C$87))*$E$25 -> 0.144 | H55: =$D$25*$C$15*IF((H$35-$C$25)<0,0,IF((H$35-$C$25)>=7,1,INDEX(Drivers!$D$86:$J$86,(H$35-$C$25)+1)))*IF((H$35-$C$25)<Drivers!$C$87,1,Drivers!$C$88*Drivers!$C$89^((H$35-$C$25)-Drivers!$C$87))*$E$25 -> 0.45 | I55: =$D$25*$C$15*IF((I$35-$C$25)<0,0,IF((I$35-$C$25)>=7,1,INDEX(Drivers!$D$86:$J$86,(I$35-$C$25)+1)))*IF((I$35-$C$25)<Drivers!$C$87,1,Drivers!$C$88*Drivers!$C$89^((I$35-$C$25)-Drivers!$C$87))*$E$25 -> 0.81 | J55: =$D$25*$C$15*IF((J$35-$C$25)<0,0,IF((J$35-$C$25)>=7,1,INDEX(Drivers!$D$86:$J$86,(J$35-$C$25)+1)))*IF((J$35-$C$25)<Drivers!$C$87,1,Drivers!$C$88*Drivers!$C$89^((J$35-$C$25)-Drivers!$C$87))*$E$25 -> 1.17 | ... U55: =$D$25*$C$15*IF((U$35-$C$25)<0,0,IF((U$35-$C$25)>=7,1,INDEX(Drivers!$D$86:$J$86,(U$35-$C$25)+1)))*IF((U$35-$C$25)<Drivers!$C$87,1,Drivers!$C$88*Drivers!$C$89^((U$35-$C$25)-Drivers!$C$87))*$E$25 -> 1.354896
A56: Post-neoadjuvant non-pCR NSCLC (INTerpath-009) | B56: $B | C56: =$D$26*$C$15*IF((C$35-$C$26)<0,0,IF((C$35-$C$26)>=7,1,INDEX(Drivers!$D$86:$J$86,(C$35-$C$26)+1)))*IF((C$35-$C$26)<Drivers!$C$87,1,Drivers!$C$88*Drivers!$C$89^((C$35-$C$26)-Drivers!$C$87))*$E$26 -> 0 | D56: =$D$26*$C$15*IF((D$35-$C$26)<0,0,IF((D$35-$C$26)>=7,1,INDEX(Drivers!$D$86:$J$86,(D$35-$C$26)+1)))*IF((D$35-$C$26)<Drivers!$C$87,1,Drivers!$C$88*Drivers!$C$89^((D$35-$C$26)-Drivers!$C$87))*$E$26 -> 0 | E56: =$D$26*$C$15*IF((E$35-$C$26)<0,0,IF((E$35-$C$26)>=7,1,INDEX(Drivers!$D$86:$J$86,(E$35-$C$26)+1)))*IF((E$35-$C$26)<Drivers!$C$87,1,Drivers!$C$88*Drivers!$C$89^((E$35-$C$26)-Drivers!$C$87))*$E$26 -> 0 | F56: =$D$26*$C$15*IF((F$35-$C$26)<0,0,IF((F$35-$C$26)>=7,1,INDEX(Drivers!$D$86:$J$86,(F$35-$C$26)+1)))*IF((F$35-$C$26)<Drivers!$C$87,1,Drivers!$C$88*Drivers!$C$89^((F$35-$C$26)-Drivers!$C$87))*$E$26 -> 0 | G56: =$D$26*$C$15*IF((G$35-$C$26)<0,0,IF((G$35-$C$26)>=7,1,INDEX(Drivers!$D$86:$J$86,(G$35-$C$26)+1)))*IF((G$35-$C$26)<Drivers!$C$87,1,Drivers!$C$88*Drivers!$C$89^((G$35-$C$26)-Drivers!$C$87))*$E$26 -> 0 | H56: =$D$26*$C$15*IF((H$35-$C$26)<0,0,IF((H$35-$C$26)>=7,1,INDEX(Drivers!$D$86:$J$86,(H$35-$C$26)+1)))*IF((H$35-$C$26)<Drivers!$C$87,1,Drivers!$C$88*Drivers!$C$89^((H$35-$C$26)-Drivers!$C$87))*$E$26 -> 0 | I56: =$D$26*$C$15*IF((I$35-$C$26)<0,0,IF((I$35-$C$26)>=7,1,INDEX(Drivers!$D$86:$J$86,(I$35-$C$26)+1)))*IF((I$35-$C$26)<Drivers!$C$87,1,Drivers!$C$88*Drivers!$C$89^((I$35-$C$26)-Drivers!$C$87))*$E$26 -> 0 | J56: =$D$26*$C$15*IF((J$35-$C$26)<0,0,IF((J$35-$C$26)>=7,1,INDEX(Drivers!$D$86:$J$86,(J$35-$C$26)+1)))*IF((J$35-$C$26)<Drivers!$C$87,1,Drivers!$C$88*Drivers!$C$89^((J$35-$C$26)-Drivers!$C$87))*$E$26 -> 0.048 | ... U56: =$D$26*$C$15*IF((U$35-$C$26)<0,0,IF((U$35-$C$26)>=7,1,INDEX(Drivers!$D$86:$J$86,(U$35-$C$26)+1)))*IF((U$35-$C$26)<Drivers!$C$87,1,Drivers!$C$88*Drivers!$C$89^((U$35-$C$26)-Drivers!$C$87))*$E$26 -> 0.6
A57: Resected stage I NSCLC (INTerpath-014) | B57: $B | C57: =$D$27*$C$15*IF((C$35-$C$27)<0,0,IF((C$35-$C$27)>=7,1,INDEX(Drivers!$D$86:$J$86,(C$35-$C$27)+1)))*IF((C$35-$C$27)<Drivers!$C$87,1,Drivers!$C$88*Drivers!$C$89^((C$35-$C$27)-Drivers!$C$87))*$E$27 -> 0 | D57: =$D$27*$C$15*IF((D$35-$C$27)<0,0,IF((D$35-$C$27)>=7,1,INDEX(Drivers!$D$86:$J$86,(D$35-$C$27)+1)))*IF((D$35-$C$27)<Drivers!$C$87,1,Drivers!$C$88*Drivers!$C$89^((D$35-$C$27)-Drivers!$C$87))*$E$27 -> 0 | E57: =$D$27*$C$15*IF((E$35-$C$27)<0,0,IF((E$35-$C$27)>=7,1,INDEX(Drivers!$D$86:$J$86,(E$35-$C$27)+1)))*IF((E$35-$C$27)<Drivers!$C$87,1,Drivers!$C$88*Drivers!$C$89^((E$35-$C$27)-Drivers!$C$87))*$E$27 -> 0 | F57: =$D$27*$C$15*IF((F$35-$C$27)<0,0,IF((F$35-$C$27)>=7,1,INDEX(Drivers!$D$86:$J$86,(F$35-$C$27)+1)))*IF((F$35-$C$27)<Drivers!$C$87,1,Drivers!$C$88*Drivers!$C$89^((F$35-$C$27)-Drivers!$C$87))*$E$27 -> 0 | G57: =$D$27*$C$15*IF((G$35-$C$27)<0,0,IF((G$35-$C$27)>=7,1,INDEX(Drivers!$D$86:$J$86,(G$35-$C$27)+1)))*IF((G$35-$C$27)<Drivers!$C$87,1,Drivers!$C$88*Drivers!$C$89^((G$35-$C$27)-Drivers!$C$87))*$E$27 -> 0 | H57: =$D$27*$C$15*IF((H$35-$C$27)<0,0,IF((H$35-$C$27)>=7,1,INDEX(Drivers!$D$86:$J$86,(H$35-$C$27)+1)))*IF((H$35-$C$27)<Drivers!$C$87,1,Drivers!$C$88*Drivers!$C$89^((H$35-$C$27)-Drivers!$C$87))*$E$27 -> 0 | I57: =$D$27*$C$15*IF((I$35-$C$27)<0,0,IF((I$35-$C$27)>=7,1,INDEX(Drivers!$D$86:$J$86,(I$35-$C$27)+1)))*IF((I$35-$C$27)<Drivers!$C$87,1,Drivers!$C$88*Drivers!$C$89^((I$35-$C$27)-Drivers!$C$87))*$E$27 -> 0 | J57: =$D$27*$C$15*IF((J$35-$C$27)<0,0,IF((J$35-$C$27)>=7,1,INDEX(Drivers!$D$86:$J$86,(J$35-$C$27)+1)))*IF((J$35-$C$27)<Drivers!$C$87,1,Drivers!$C$88*Drivers!$C$89^((J$35-$C$27)-Drivers!$C$87))*$E$27 -> 0 | ... U57: =$D$27*$C$15*IF((U$35-$C$27)<0,0,IF((U$35-$C$27)>=7,1,INDEX(Drivers!$D$86:$J$86,(U$35-$C$27)+1)))*IF((U$35-$C$27)<Drivers!$C$87,1,Drivers!$C$88*Drivers!$C$89^((U$35-$C$27)-Drivers!$C$87))*$E$27 -> 0.875
A58: Adjuvant RCC (INTerpath-004) | B58: $B | C58: =$D$28*$C$15*IF((C$35-$C$28)<0,0,IF((C$35-$C$28)>=7,1,INDEX(Drivers!$D$86:$J$86,(C$35-$C$28)+1)))*IF((C$35-$C$28)<Drivers!$C$87,1,Drivers!$C$88*Drivers!$C$89^((C$35-$C$28)-Drivers!$C$87))*$E$28 -> 0 | D58: =$D$28*$C$15*IF((D$35-$C$28)<0,0,IF((D$35-$C$28)>=7,1,INDEX(Drivers!$D$86:$J$86,(D$35-$C$28)+1)))*IF((D$35-$C$28)<Drivers!$C$87,1,Drivers!$C$88*Drivers!$C$89^((D$35-$C$28)-Drivers!$C$87))*$E$28 -> 0 | E58: =$D$28*$C$15*IF((E$35-$C$28)<0,0,IF((E$35-$C$28)>=7,1,INDEX(Drivers!$D$86:$J$86,(E$35-$C$28)+1)))*IF((E$35-$C$28)<Drivers!$C$87,1,Drivers!$C$88*Drivers!$C$89^((E$35-$C$28)-Drivers!$C$87))*$E$28 -> 0 | F58: =$D$28*$C$15*IF((F$35-$C$28)<0,0,IF((F$35-$C$28)>=7,1,INDEX(Drivers!$D$86:$J$86,(F$35-$C$28)+1)))*IF((F$35-$C$28)<Drivers!$C$87,1,Drivers!$C$88*Drivers!$C$89^((F$35-$C$28)-Drivers!$C$87))*$E$28 -> 0 | G58: =$D$28*$C$15*IF((G$35-$C$28)<0,0,IF((G$35-$C$28)>=7,1,INDEX(Drivers!$D$86:$J$86,(G$35-$C$28)+1)))*IF((G$35-$C$28)<Drivers!$C$87,1,Drivers!$C$88*Drivers!$C$89^((G$35-$C$28)-Drivers!$C$87))*$E$28 -> 0.024 | H58: =$D$28*$C$15*IF((H$35-$C$28)<0,0,IF((H$35-$C$28)>=7,1,INDEX(Drivers!$D$86:$J$86,(H$35-$C$28)+1)))*IF((H$35-$C$28)<Drivers!$C$87,1,Drivers!$C$88*Drivers!$C$89^((H$35-$C$28)-Drivers!$C$87))*$E$28 -> 0.075 | I58: =$D$28*$C$15*IF((I$35-$C$28)<0,0,IF((I$35-$C$28)>=7,1,INDEX(Drivers!$D$86:$J$86,(I$35-$C$28)+1)))*IF((I$35-$C$28)<Drivers!$C$87,1,Drivers!$C$88*Drivers!$C$89^((I$35-$C$28)-Drivers!$C$87))*$E$28 -> 0.135 | J58: =$D$28*$C$15*IF((J$35-$C$28)<0,0,IF((J$35-$C$28)>=7,1,INDEX(Drivers!$D$86:$J$86,(J$35-$C$28)+1)))*IF((J$35-$C$28)<Drivers!$C$87,1,Drivers!$C$88*Drivers!$C$89^((J$35-$C$28)-Drivers!$C$87))*$E$28 -> 0.195 | ... U58: =$D$28*$C$15*IF((U$35-$C$28)<0,0,IF((U$35-$C$28)>=7,1,INDEX(Drivers!$D$86:$J$86,(U$35-$C$28)+1)))*IF((U$35-$C$28)<Drivers!$C$87,1,Drivers!$C$88*Drivers!$C$89^((U$35-$C$28)-Drivers!$C$87))*$E$28 -> 0.225816
A59: MIBC adjuvant (INTerpath-005) | B59: $B | C59: =$D$29*$C$15*IF((C$35-$C$29)<0,0,IF((C$35-$C$29)>=7,1,INDEX(Drivers!$D$86:$J$86,(C$35-$C$29)+1)))*IF((C$35-$C$29)<Drivers!$C$87,1,Drivers!$C$88*Drivers!$C$89^((C$35-$C$29)-Drivers!$C$87))*$E$29 -> 0 | D59: =$D$29*$C$15*IF((D$35-$C$29)<0,0,IF((D$35-$C$29)>=7,1,INDEX(Drivers!$D$86:$J$86,(D$35-$C$29)+1)))*IF((D$35-$C$29)<Drivers!$C$87,1,Drivers!$C$88*Drivers!$C$89^((D$35-$C$29)-Drivers!$C$87))*$E$29 -> 0 | E59: =$D$29*$C$15*IF((E$35-$C$29)<0,0,IF((E$35-$C$29)>=7,1,INDEX(Drivers!$D$86:$J$86,(E$35-$C$29)+1)))*IF((E$35-$C$29)<Drivers!$C$87,1,Drivers!$C$88*Drivers!$C$89^((E$35-$C$29)-Drivers!$C$87))*$E$29 -> 0 | F59: =$D$29*$C$15*IF((F$35-$C$29)<0,0,IF((F$35-$C$29)>=7,1,INDEX(Drivers!$D$86:$J$86,(F$35-$C$29)+1)))*IF((F$35-$C$29)<Drivers!$C$87,1,Drivers!$C$88*Drivers!$C$89^((F$35-$C$29)-Drivers!$C$87))*$E$29 -> 0 | G59: =$D$29*$C$15*IF((G$35-$C$29)<0,0,IF((G$35-$C$29)>=7,1,INDEX(Drivers!$D$86:$J$86,(G$35-$C$29)+1)))*IF((G$35-$C$29)<Drivers!$C$87,1,Drivers!$C$88*Drivers!$C$89^((G$35-$C$29)-Drivers!$C$87))*$E$29 -> 0 | H59: =$D$29*$C$15*IF((H$35-$C$29)<0,0,IF((H$35-$C$29)>=7,1,INDEX(Drivers!$D$86:$J$86,(H$35-$C$29)+1)))*IF((H$35-$C$29)<Drivers!$C$87,1,Drivers!$C$88*Drivers!$C$89^((H$35-$C$29)-Drivers!$C$87))*$E$29 -> 0 | I59: =$D$29*$C$15*IF((I$35-$C$29)<0,0,IF((I$35-$C$29)>=7,1,INDEX(Drivers!$D$86:$J$86,(I$35-$C$29)+1)))*IF((I$35-$C$29)<Drivers!$C$87,1,Drivers!$C$88*Drivers!$C$89^((I$35-$C$29)-Drivers!$C$87))*$E$29 -> 0.016 | J59: =$D$29*$C$15*IF((J$35-$C$29)<0,0,IF((J$35-$C$29)>=7,1,INDEX(Drivers!$D$86:$J$86,(J$35-$C$29)+1)))*IF((J$35-$C$29)<Drivers!$C$87,1,Drivers!$C$88*Drivers!$C$89^((J$35-$C$29)-Drivers!$C$87))*$E$29 -> 0.05 | ... U59: =$D$29*$C$15*IF((U$35-$C$29)<0,0,IF((U$35-$C$29)>=7,1,INDEX(Drivers!$D$86:$J$86,(U$35-$C$29)+1)))*IF((U$35-$C$29)<Drivers!$C$87,1,Drivers!$C$88*Drivers!$C$89^((U$35-$C$29)-Drivers!$C$87))*$E$29 -> 0.16
A60: NMIBC + BCG (INTerpath-011) | B60: $B | C60: =$D$30*$C$15*IF((C$35-$C$30)<0,0,IF((C$35-$C$30)>=7,1,INDEX(Drivers!$D$86:$J$86,(C$35-$C$30)+1)))*IF((C$35-$C$30)<Drivers!$C$87,1,Drivers!$C$88*Drivers!$C$89^((C$35-$C$30)-Drivers!$C$87))*$E$30 -> 0 | D60: =$D$30*$C$15*IF((D$35-$C$30)<0,0,IF((D$35-$C$30)>=7,1,INDEX(Drivers!$D$86:$J$86,(D$35-$C$30)+1)))*IF((D$35-$C$30)<Drivers!$C$87,1,Drivers!$C$88*Drivers!$C$89^((D$35-$C$30)-Drivers!$C$87))*$E$30 -> 0 | E60: =$D$30*$C$15*IF((E$35-$C$30)<0,0,IF((E$35-$C$30)>=7,1,INDEX(Drivers!$D$86:$J$86,(E$35-$C$30)+1)))*IF((E$35-$C$30)<Drivers!$C$87,1,Drivers!$C$88*Drivers!$C$89^((E$35-$C$30)-Drivers!$C$87))*$E$30 -> 0 | F60: =$D$30*$C$15*IF((F$35-$C$30)<0,0,IF((F$35-$C$30)>=7,1,INDEX(Drivers!$D$86:$J$86,(F$35-$C$30)+1)))*IF((F$35-$C$30)<Drivers!$C$87,1,Drivers!$C$88*Drivers!$C$89^((F$35-$C$30)-Drivers!$C$87))*$E$30 -> 0 | G60: =$D$30*$C$15*IF((G$35-$C$30)<0,0,IF((G$35-$C$30)>=7,1,INDEX(Drivers!$D$86:$J$86,(G$35-$C$30)+1)))*IF((G$35-$C$30)<Drivers!$C$87,1,Drivers!$C$88*Drivers!$C$89^((G$35-$C$30)-Drivers!$C$87))*$E$30 -> 0 | H60: =$D$30*$C$15*IF((H$35-$C$30)<0,0,IF((H$35-$C$30)>=7,1,INDEX(Drivers!$D$86:$J$86,(H$35-$C$30)+1)))*IF((H$35-$C$30)<Drivers!$C$87,1,Drivers!$C$88*Drivers!$C$89^((H$35-$C$30)-Drivers!$C$87))*$E$30 -> 0 | I60: =$D$30*$C$15*IF((I$35-$C$30)<0,0,IF((I$35-$C$30)>=7,1,INDEX(Drivers!$D$86:$J$86,(I$35-$C$30)+1)))*IF((I$35-$C$30)<Drivers!$C$87,1,Drivers!$C$88*Drivers!$C$89^((I$35-$C$30)-Drivers!$C$87))*$E$30 -> 0 | J60: =$D$30*$C$15*IF((J$35-$C$30)<0,0,IF((J$35-$C$30)>=7,1,INDEX(Drivers!$D$86:$J$86,(J$35-$C$30)+1)))*IF((J$35-$C$30)<Drivers!$C$87,1,Drivers!$C$88*Drivers!$C$89^((J$35-$C$30)-Drivers!$C$87))*$E$30 -> 0.012 | ... U60: =$D$30*$C$15*IF((U$35-$C$30)<0,0,IF((U$35-$C$30)>=7,1,INDEX(Drivers!$D$86:$J$86,(U$35-$C$30)+1)))*IF((U$35-$C$30)<Drivers!$C$87,1,Drivers!$C$88*Drivers!$C$89^((U$35-$C$30)-Drivers!$C$87))*$E$30 -> 0.15
A61: 1L advanced melanoma (INTerpath-012) | B61: $B | C61: =$D$31*$C$15*IF((C$35-$C$31)<0,0,IF((C$35-$C$31)>=7,1,INDEX(Drivers!$D$86:$J$86,(C$35-$C$31)+1)))*IF((C$35-$C$31)<Drivers!$C$87,1,Drivers!$C$88*Drivers!$C$89^((C$35-$C$31)-Drivers!$C$87))*$E$31 -> 0 | D61: =$D$31*$C$15*IF((D$35-$C$31)<0,0,IF((D$35-$C$31)>=7,1,INDEX(Drivers!$D$86:$J$86,(D$35-$C$31)+1)))*IF((D$35-$C$31)<Drivers!$C$87,1,Drivers!$C$88*Drivers!$C$89^((D$35-$C$31)-Drivers!$C$87))*$E$31 -> 0 | E61: =$D$31*$C$15*IF((E$35-$C$31)<0,0,IF((E$35-$C$31)>=7,1,INDEX(Drivers!$D$86:$J$86,(E$35-$C$31)+1)))*IF((E$35-$C$31)<Drivers!$C$87,1,Drivers!$C$88*Drivers!$C$89^((E$35-$C$31)-Drivers!$C$87))*$E$31 -> 0 | F61: =$D$31*$C$15*IF((F$35-$C$31)<0,0,IF((F$35-$C$31)>=7,1,INDEX(Drivers!$D$86:$J$86,(F$35-$C$31)+1)))*IF((F$35-$C$31)<Drivers!$C$87,1,Drivers!$C$88*Drivers!$C$89^((F$35-$C$31)-Drivers!$C$87))*$E$31 -> 0 | G61: =$D$31*$C$15*IF((G$35-$C$31)<0,0,IF((G$35-$C$31)>=7,1,INDEX(Drivers!$D$86:$J$86,(G$35-$C$31)+1)))*IF((G$35-$C$31)<Drivers!$C$87,1,Drivers!$C$88*Drivers!$C$89^((G$35-$C$31)-Drivers!$C$87))*$E$31 -> 0.0128 | H61: =$D$31*$C$15*IF((H$35-$C$31)<0,0,IF((H$35-$C$31)>=7,1,INDEX(Drivers!$D$86:$J$86,(H$35-$C$31)+1)))*IF((H$35-$C$31)<Drivers!$C$87,1,Drivers!$C$88*Drivers!$C$89^((H$35-$C$31)-Drivers!$C$87))*$E$31 -> 0.04 | I61: =$D$31*$C$15*IF((I$35-$C$31)<0,0,IF((I$35-$C$31)>=7,1,INDEX(Drivers!$D$86:$J$86,(I$35-$C$31)+1)))*IF((I$35-$C$31)<Drivers!$C$87,1,Drivers!$C$88*Drivers!$C$89^((I$35-$C$31)-Drivers!$C$87))*$E$31 -> 0.072 | J61: =$D$31*$C$15*IF((J$35-$C$31)<0,0,IF((J$35-$C$31)>=7,1,INDEX(Drivers!$D$86:$J$86,(J$35-$C$31)+1)))*IF((J$35-$C$31)<Drivers!$C$87,1,Drivers!$C$88*Drivers!$C$89^((J$35-$C$31)-Drivers!$C$87))*$E$31 -> 0.104 | ... U61: =$D$31*$C$15*IF((U$35-$C$31)<0,0,IF((U$35-$C$31)>=7,1,INDEX(Drivers!$D$86:$J$86,(U$35-$C$31)+1)))*IF((U$35-$C$31)<Drivers!$C$87,1,Drivers!$C$88*Drivers!$C$89^((U$35-$C$31)-Drivers!$C$87))*$E$31 -> 0.1204352
A62: 1L metastatic squamous NSCLC (INTerpath-013) | B62: $B | C62: =$D$32*$C$15*IF((C$35-$C$32)<0,0,IF((C$35-$C$32)>=7,1,INDEX(Drivers!$D$86:$J$86,(C$35-$C$32)+1)))*IF((C$35-$C$32)<Drivers!$C$87,1,Drivers!$C$88*Drivers!$C$89^((C$35-$C$32)-Drivers!$C$87))*$E$32 -> 0 | D62: =$D$32*$C$15*IF((D$35-$C$32)<0,0,IF((D$35-$C$32)>=7,1,INDEX(Drivers!$D$86:$J$86,(D$35-$C$32)+1)))*IF((D$35-$C$32)<Drivers!$C$87,1,Drivers!$C$88*Drivers!$C$89^((D$35-$C$32)-Drivers!$C$87))*$E$32 -> 0 | E62: =$D$32*$C$15*IF((E$35-$C$32)<0,0,IF((E$35-$C$32)>=7,1,INDEX(Drivers!$D$86:$J$86,(E$35-$C$32)+1)))*IF((E$35-$C$32)<Drivers!$C$87,1,Drivers!$C$88*Drivers!$C$89^((E$35-$C$32)-Drivers!$C$87))*$E$32 -> 0 | F62: =$D$32*$C$15*IF((F$35-$C$32)<0,0,IF((F$35-$C$32)>=7,1,INDEX(Drivers!$D$86:$J$86,(F$35-$C$32)+1)))*IF((F$35-$C$32)<Drivers!$C$87,1,Drivers!$C$88*Drivers!$C$89^((F$35-$C$32)-Drivers!$C$87))*$E$32 -> 0 | G62: =$D$32*$C$15*IF((G$35-$C$32)<0,0,IF((G$35-$C$32)>=7,1,INDEX(Drivers!$D$86:$J$86,(G$35-$C$32)+1)))*IF((G$35-$C$32)<Drivers!$C$87,1,Drivers!$C$88*Drivers!$C$89^((G$35-$C$32)-Drivers!$C$87))*$E$32 -> 0 | H62: =$D$32*$C$15*IF((H$35-$C$32)<0,0,IF((H$35-$C$32)>=7,1,INDEX(Drivers!$D$86:$J$86,(H$35-$C$32)+1)))*IF((H$35-$C$32)<Drivers!$C$87,1,Drivers!$C$88*Drivers!$C$89^((H$35-$C$32)-Drivers!$C$87))*$E$32 -> 0.0144 | I62: =$D$32*$C$15*IF((I$35-$C$32)<0,0,IF((I$35-$C$32)>=7,1,INDEX(Drivers!$D$86:$J$86,(I$35-$C$32)+1)))*IF((I$35-$C$32)<Drivers!$C$87,1,Drivers!$C$88*Drivers!$C$89^((I$35-$C$32)-Drivers!$C$87))*$E$32 -> 0.045 | J62: =$D$32*$C$15*IF((J$35-$C$32)<0,0,IF((J$35-$C$32)>=7,1,INDEX(Drivers!$D$86:$J$86,(J$35-$C$32)+1)))*IF((J$35-$C$32)<Drivers!$C$87,1,Drivers!$C$88*Drivers!$C$89^((J$35-$C$32)-Drivers!$C$87))*$E$32 -> 0.081 | ... U62: =$D$32*$C$15*IF((U$35-$C$32)<0,0,IF((U$35-$C$32)>=7,1,INDEX(Drivers!$D$86:$J$86,(U$35-$C$32)+1)))*IF((U$35-$C$32)<Drivers!$C$87,1,Drivers!$C$88*Drivers!$C$89^((U$35-$C$32)-Drivers!$C$87))*$E$32 -> 0.13968
A63: Other solid tumours - future INT indications (pr | B63: $B | C63: =$D$33*$C$15*IF((C$35-$C$33)<0,0,IF((C$35-$C$33)>=7,1,INDEX(Drivers!$D$86:$J$86,(C$35-$C$33)+1)))*IF((C$35-$C$33)<Drivers!$C$87,1,Drivers!$C$88*Drivers!$C$89^((C$35-$C$33)-Drivers!$C$87))*$E$33 -> 0 | D63: =$D$33*$C$15*IF((D$35-$C$33)<0,0,IF((D$35-$C$33)>=7,1,INDEX(Drivers!$D$86:$J$86,(D$35-$C$33)+1)))*IF((D$35-$C$33)<Drivers!$C$87,1,Drivers!$C$88*Drivers!$C$89^((D$35-$C$33)-Drivers!$C$87))*$E$33 -> 0 | E63: =$D$33*$C$15*IF((E$35-$C$33)<0,0,IF((E$35-$C$33)>=7,1,INDEX(Drivers!$D$86:$J$86,(E$35-$C$33)+1)))*IF((E$35-$C$33)<Drivers!$C$87,1,Drivers!$C$88*Drivers!$C$89^((E$35-$C$33)-Drivers!$C$87))*$E$33 -> 0 | F63: =$D$33*$C$15*IF((F$35-$C$33)<0,0,IF((F$35-$C$33)>=7,1,INDEX(Drivers!$D$86:$J$86,(F$35-$C$33)+1)))*IF((F$35-$C$33)<Drivers!$C$87,1,Drivers!$C$88*Drivers!$C$89^((F$35-$C$33)-Drivers!$C$87))*$E$33 -> 0 | G63: =$D$33*$C$15*IF((G$35-$C$33)<0,0,IF((G$35-$C$33)>=7,1,INDEX(Drivers!$D$86:$J$86,(G$35-$C$33)+1)))*IF((G$35-$C$33)<Drivers!$C$87,1,Drivers!$C$88*Drivers!$C$89^((G$35-$C$33)-Drivers!$C$87))*$E$33 -> 0 | H63: =$D$33*$C$15*IF((H$35-$C$33)<0,0,IF((H$35-$C$33)>=7,1,INDEX(Drivers!$D$86:$J$86,(H$35-$C$33)+1)))*IF((H$35-$C$33)<Drivers!$C$87,1,Drivers!$C$88*Drivers!$C$89^((H$35-$C$33)-Drivers!$C$87))*$E$33 -> 0 | I63: =$D$33*$C$15*IF((I$35-$C$33)<0,0,IF((I$35-$C$33)>=7,1,INDEX(Drivers!$D$86:$J$86,(I$35-$C$33)+1)))*IF((I$35-$C$33)<Drivers!$C$87,1,Drivers!$C$88*Drivers!$C$89^((I$35-$C$33)-Drivers!$C$87))*$E$33 -> 0 | J63: =$D$33*$C$15*IF((J$35-$C$33)<0,0,IF((J$35-$C$33)>=7,1,INDEX(Drivers!$D$86:$J$86,(J$35-$C$33)+1)))*IF((J$35-$C$33)<Drivers!$C$87,1,Drivers!$C$88*Drivers!$C$89^((J$35-$C$33)-Drivers!$C$87))*$E$33 -> 0 | ... U63: =$D$33*$C$15*IF((U$35-$C$33)<0,0,IF((U$35-$C$33)>=7,1,INDEX(Drivers!$D$86:$J$86,(U$35-$C$33)+1)))*IF((U$35-$C$33)<Drivers!$C$87,1,Drivers!$C$88*Drivers!$C$89^((U$35-$C$33)-Drivers!$C$87))*$E$33 -> 0.6
A64: INT global sales (risk-adjusted) | B64: $B | C64: =SUM(C54:C63) -> 0.19712 | D64: =SUM(D54:D63) -> 0.616 | E64: =SUM(E54:E63) -> 1.1088 | F64: =SUM(F54:F63) -> 1.6016 | G64: =SUM(G54:G63) -> 2.20128 | H64: =SUM(H54:H63) -> 2.87092 | I64: =SUM(I54:I63) -> 3.542 | J64: =SUM(J54:J63) -> 4.124 | ... U64: =SUM(U54:U63) -> 5.8677816
A65: Profit-pool margin | B65: % | C65: =IF((C$35-$C$24)<0,0,Drivers!$C$90+($C$16-Drivers!$C$90)*MIN((C$35-$C$24)/Drivers!$C$91,1)) -> 0.2 | D65: =IF((D$35-$C$24)<0,0,Drivers!$C$90+($C$16-Drivers!$C$90)*MIN((D$35-$C$24)/Drivers!$C$91,1)) -> 0.27 | E65: =IF((E$35-$C$24)<0,0,Drivers!$C$90+($C$16-Drivers!$C$90)*MIN((E$35-$C$24)/Drivers!$C$91,1)) -> 0.34 | F65: =IF((F$35-$C$24)<0,0,Drivers!$C$90+($C$16-Drivers!$C$90)*MIN((F$35-$C$24)/Drivers!$C$91,1)) -> 0.41 | G65: =IF((G$35-$C$24)<0,0,Drivers!$C$90+($C$16-Drivers!$C$90)*MIN((G$35-$C$24)/Drivers!$C$91,1)) -> 0.48 | H65: =IF((H$35-$C$24)<0,0,Drivers!$C$90+($C$16-Drivers!$C$90)*MIN((H$35-$C$24)/Drivers!$C$91,1)) -> 0.55 | I65: =IF((I$35-$C$24)<0,0,Drivers!$C$90+($C$16-Drivers!$C$90)*MIN((I$35-$C$24)/Drivers!$C$91,1)) -> 0.55 | J65: =IF((J$35-$C$24)<0,0,Drivers!$C$90+($C$16-Drivers!$C$90)*MIN((J$35-$C$24)/Drivers!$C$91,1)) -> 0.55 | ... U65: =IF((U$35-$C$24)<0,0,Drivers!$C$90+($C$16-Drivers!$C$90)*MIN((U$35-$C$24)/Drivers!$C$91,1)) -> 0.55
A66: Moderna 50% share of profit pool | B66: $B | C66: =Drivers!$C$85*C64*C65 -> 0.019712 | D66: =Drivers!$C$85*D64*D65 -> 0.08316 | E66: =Drivers!$C$85*E64*E65 -> 0.188496 | F66: =Drivers!$C$85*F64*F65 -> 0.328328 | G66: =Drivers!$C$85*G64*G65 -> 0.5283072 | H66: =Drivers!$C$85*H64*H65 -> 0.789503 | I66: =Drivers!$C$85*I64*I65 -> 0.97405 | J66: =Drivers!$C$85*J64*J65 -> 1.1341 | ... U66: =Drivers!$C$85*U64*U65 -> 1.6136399
A67: Moderna share of INT development | B67: $B | C67: =Drivers!$D$92 -> 0.4 | D67: =Drivers!$E$92 -> 0.4 | E67: =Drivers!$F$92 -> 0.4 | F67: =Drivers!$G$92 -> 0.4 | G67: =Drivers!$H$92 -> 0.35 | H67: =Drivers!$I$92 -> 0.35 | I67: =Drivers!$J$92 -> 0.3 | J67: =Drivers!$K$92 -> 0.25 | K67: =Drivers!$C$93 -> 0.2 | L67: =Drivers!$C$93 -> 0.2 | M67: =Drivers!$C$93 -> 0.2 | N67: =Drivers!$C$93 -> 0.2 | O67: =Drivers!$C$93 -> 0.2 | P67: =Drivers!$C$93 -> 0.2 | Q67: =Drivers!$C$93 -> 0.2 | R67: =Drivers!$C$93 -> 0.2 | ... U67: =Drivers!$C$93 -> 0.2
A68: INT contribution | B68: $B | C68: =C66-C67 -> -0.380288 | D68: =D66-D67 -> -0.31684 | E68: =E66-E67 -> -0.211504 | F68: =F66-F67 -> -0.071672 | G68: =G66-G67 -> 0.1783072 | H68: =H66-H67 -> 0.439503 | I68: =I66-I67 -> 0.67405 | J68: =J66-J67 -> 0.8841 | ... U68: =U66-U67 -> 1.4136399
A69: OTHER PIPELINE
A70: mRNA-4359 sales (risk-adjusted) | B70: $B | C70: =Drivers!$C$107*Drivers!$C$108*IF((C$35-Drivers!$C$109)<0,0,IF((C$35-Drivers!$C$109)>=7,1,INDEX(Drivers!$D$86:$J$86,(C$35-Drivers!$C$109)+1)))*IF((C$35-Drivers!$C$109)<Drivers!$C$87,1,Drivers!$C$88*Drivers!$C$89^((C$35-Drivers!$C$109)-Drivers!$C$87)) -> 0 | D70: =Drivers!$C$107*Drivers!$C$108*IF((D$35-Drivers!$C$109)<0,0,IF((D$35-Drivers!$C$109)>=7,1,INDEX(Drivers!$D$86:$J$86,(D$35-Drivers!$C$109)+1)))*IF((D$35-Drivers!$C$109)<Drivers!$C$87,1,Drivers!$C$88*Drivers!$C$89^((D$35-Drivers!$C$109)-Drivers!$C$87)) -> 0 | E70: =Drivers!$C$107*Drivers!$C$108*IF((E$35-Drivers!$C$109)<0,0,IF((E$35-Drivers!$C$109)>=7,1,INDEX(Drivers!$D$86:$J$86,(E$35-Drivers!$C$109)+1)))*IF((E$35-Drivers!$C$109)<Drivers!$C$87,1,Drivers!$C$88*Drivers!$C$89^((E$35-Drivers!$C$109)-Drivers!$C$87)) -> 0 | F70: =Drivers!$C$107*Drivers!$C$108*IF((F$35-Drivers!$C$109)<0,0,IF((F$35-Drivers!$C$109)>=7,1,INDEX(Drivers!$D$86:$J$86,(F$35-Drivers!$C$109)+1)))*IF((F$35-Drivers!$C$109)<Drivers!$C$87,1,Drivers!$C$88*Drivers!$C$89^((F$35-Drivers!$C$109)-Drivers!$C$87)) -> 0 | G70: =Drivers!$C$107*Drivers!$C$108*IF((G$35-Drivers!$C$109)<0,0,IF((G$35-Drivers!$C$109)>=7,1,INDEX(Drivers!$D$86:$J$86,(G$35-Drivers!$C$109)+1)))*IF((G$35-Drivers!$C$109)<Drivers!$C$87,1,Drivers!$C$88*Drivers!$C$89^((G$35-Drivers!$C$109)-Drivers!$C$87)) -> 0.016 | H70: =Drivers!$C$107*Drivers!$C$108*IF((H$35-Drivers!$C$109)<0,0,IF((H$35-Drivers!$C$109)>=7,1,INDEX(Drivers!$D$86:$J$86,(H$35-Drivers!$C$109)+1)))*IF((H$35-Drivers!$C$109)<Drivers!$C$87,1,Drivers!$C$88*Drivers!$C$89^((H$35-Drivers!$C$109)-Drivers!$C$87)) -> 0.05 | I70: =Drivers!$C$107*Drivers!$C$108*IF((I$35-Drivers!$C$109)<0,0,IF((I$35-Drivers!$C$109)>=7,1,INDEX(Drivers!$D$86:$J$86,(I$35-Drivers!$C$109)+1)))*IF((I$35-Drivers!$C$109)<Drivers!$C$87,1,Drivers!$C$88*Drivers!$C$89^((I$35-Drivers!$C$109)-Drivers!$C$87)) -> 0.09 | J70: =Drivers!$C$107*Drivers!$C$108*IF((J$35-Drivers!$C$109)<0,0,IF((J$35-Drivers!$C$109)>=7,1,INDEX(Drivers!$D$86:$J$86,(J$35-Drivers!$C$109)+1)))*IF((J$35-Drivers!$C$109)<Drivers!$C$87,1,Drivers!$C$88*Drivers!$C$89^((J$35-Drivers!$C$109)-Drivers!$C$87)) -> 0.13 | ... U70: =Drivers!$C$107*Drivers!$C$108*IF((U$35-Drivers!$C$109)<0,0,IF((U$35-Drivers!$C$109)>=7,1,INDEX(Drivers!$D$86:$J$86,(U$35-Drivers!$C$109)+1)))*IF((U$35-Drivers!$C$109)<Drivers!$C$87,1,Drivers!$C$88*Drivers!$C$89^((U$35-Drivers!$C$109)-Drivers!$C$87)) -> 0.150544
A71: mRNA-4359 development | B71: $B | C71: =Drivers!$D$111 -> 0.12 | D71: =Drivers!$E$111+Drivers!$C$112*Drivers!$C$113/3 -> 0.19083333 | E71: =Drivers!$F$111+Drivers!$C$112*Drivers!$C$113/3 -> 0.19083333 | F71: =Drivers!$G$111+Drivers!$C$112*Drivers!$C$113/3 -> 0.14083333 | G71: =Drivers!$H$111 -> 0.08 | H71: =0 -> 0 | I71: =0 -> 0 | J71: =0 -> 0 | K71: =0 -> 0 | L71: =0 -> 0 | M71: =0 -> 0 | N71: =0 -> 0 | O71: =0 -> 0 | ... U71: =0 -> 0
A72: mRNA-4359 contribution | B72: $B | C72: =C70*IF((C$35-Drivers!$C$109)<0,0,0.1+(Drivers!$C$110-0.1)*MIN((C$35-Drivers!$C$109)/5,1))-C71 -> -0.12 | D72: =D70*IF((D$35-Drivers!$C$109)<0,0,0.1+(Drivers!$C$110-0.1)*MIN((D$35-Drivers!$C$109)/5,1))-D71 -> -0.19083333 | E72: =E70*IF((E$35-Drivers!$C$109)<0,0,0.1+(Drivers!$C$110-0.1)*MIN((E$35-Drivers!$C$109)/5,1))-E71 -> -0.19083333 | F72: =F70*IF((F$35-Drivers!$C$109)<0,0,0.1+(Drivers!$C$110-0.1)*MIN((F$35-Drivers!$C$109)/5,1))-F71 -> -0.14083333 | G72: =G70*IF((G$35-Drivers!$C$109)<0,0,0.1+(Drivers!$C$110-0.1)*MIN((G$35-Drivers!$C$109)/5,1))-G71 -> -0.0784 | H72: =H70*IF((H$35-Drivers!$C$109)<0,0,0.1+(Drivers!$C$110-0.1)*MIN((H$35-Drivers!$C$109)/5,1))-H71 -> 0.0085 | I72: =I70*IF((I$35-Drivers!$C$109)<0,0,0.1+(Drivers!$C$110-0.1)*MIN((I$35-Drivers!$C$109)/5,1))-I71 -> 0.0216 | J72: =J70*IF((J$35-Drivers!$C$109)<0,0,0.1+(Drivers!$C$110-0.1)*MIN((J$35-Drivers!$C$109)/5,1))-J71 -> 0.0403 | ... U72: =U70*IF((U$35-Drivers!$C$109)<0,0,0.1+(Drivers!$C$110-0.1)*MIN((U$35-Drivers!$C$109)/5,1))-U71 -> 0.0677448
A73: PA sales (Recordati, risk-adjusted) | B73: $B | C73: =Drivers!$C$114*Drivers!$C$115*IF((C$35-Drivers!$C$116)<0,0,MIN(((C$35-Drivers!$C$116)+1)/5,1)) -> 0 | D73: =Drivers!$C$114*Drivers!$C$115*IF((D$35-Drivers!$C$116)<0,0,MIN(((D$35-Drivers!$C$116)+1)/5,1)) -> 0.044 | E73: =Drivers!$C$114*Drivers!$C$115*IF((E$35-Drivers!$C$116)<0,0,MIN(((E$35-Drivers!$C$116)+1)/5,1)) -> 0.088 | F73: =Drivers!$C$114*Drivers!$C$115*IF((F$35-Drivers!$C$116)<0,0,MIN(((F$35-Drivers!$C$116)+1)/5,1)) -> 0.132 | G73: =Drivers!$C$114*Drivers!$C$115*IF((G$35-Drivers!$C$116)<0,0,MIN(((G$35-Drivers!$C$116)+1)/5,1)) -> 0.176 | H73: =Drivers!$C$114*Drivers!$C$115*IF((H$35-Drivers!$C$116)<0,0,MIN(((H$35-Drivers!$C$116)+1)/5,1)) -> 0.22 | I73: =Drivers!$C$114*Drivers!$C$115*IF((I$35-Drivers!$C$116)<0,0,MIN(((I$35-Drivers!$C$116)+1)/5,1)) -> 0.22 | J73: =Drivers!$C$114*Drivers!$C$115*IF((J$35-Drivers!$C$116)<0,0,MIN(((J$35-Drivers!$C$116)+1)/5,1)) -> 0.22 | ... U73: =Drivers!$C$114*Drivers!$C$115*IF((U$35-Drivers!$C$116)<0,0,MIN(((U$35-Drivers!$C$116)+1)/5,1)) -> 0.22
A74: MMA sales (risk-adjusted) | B74: $B | C74: =Drivers!$C$120*Drivers!$C$121*IF((C$35-Drivers!$C$122)<0,0,MIN(((C$35-Drivers!$C$122)+1)/5,1)) -> 0 | D74: =Drivers!$C$120*Drivers!$C$121*IF((D$35-Drivers!$C$122)<0,0,MIN(((D$35-Drivers!$C$122)+1)/5,1)) -> 0 | E74: =Drivers!$C$120*Drivers!$C$121*IF((E$35-Drivers!$C$122)<0,0,MIN(((E$35-Drivers!$C$122)+1)/5,1)) -> 0 | F74: =Drivers!$C$120*Drivers!$C$121*IF((F$35-Drivers!$C$122)<0,0,MIN(((F$35-Drivers!$C$122)+1)/5,1)) -> 0 | G74: =Drivers!$C$120*Drivers!$C$121*IF((G$35-Drivers!$C$122)<0,0,MIN(((G$35-Drivers!$C$122)+1)/5,1)) -> 0.016 | H74: =Drivers!$C$120*Drivers!$C$121*IF((H$35-Drivers!$C$122)<0,0,MIN(((H$35-Drivers!$C$122)+1)/5,1)) -> 0.032 | I74: =Drivers!$C$120*Drivers!$C$121*IF((I$35-Drivers!$C$122)<0,0,MIN(((I$35-Drivers!$C$122)+1)/5,1)) -> 0.048 | J74: =Drivers!$C$120*Drivers!$C$121*IF((J$35-Drivers!$C$122)<0,0,MIN(((J$35-Drivers!$C$122)+1)/5,1)) -> 0.064 | ... U74: =Drivers!$C$120*Drivers!$C$121*IF((U$35-Drivers!$C$122)<0,0,MIN(((U$35-Drivers!$C$122)+1)/5,1)) -> 0.08
A75: CF royalty (risk-adjusted) | B75: $B | C75: =Drivers!$C$125*Drivers!$C$126*IF((C$35-Drivers!$C$127)<0,0,MIN(((C$35-Drivers!$C$127)+1)/5,1))*Drivers!$C$128 -> 0 | D75: =Drivers!$C$125*Drivers!$C$126*IF((D$35-Drivers!$C$127)<0,0,MIN(((D$35-Drivers!$C$127)+1)/5,1))*Drivers!$C$128 -> 0 | E75: =Drivers!$C$125*Drivers!$C$126*IF((E$35-Drivers!$C$127)<0,0,MIN(((E$35-Drivers!$C$127)+1)/5,1))*Drivers!$C$128 -> 0 | F75: =Drivers!$C$125*Drivers!$C$126*IF((F$35-Drivers!$C$127)<0,0,MIN(((F$35-Drivers!$C$127)+1)/5,1))*Drivers!$C$128 -> 0 | G75: =Drivers!$C$125*Drivers!$C$126*IF((G$35-Drivers!$C$127)<0,0,MIN(((G$35-Drivers!$C$127)+1)/5,1))*Drivers!$C$128 -> 0.0016 | H75: =Drivers!$C$125*Drivers!$C$126*IF((H$35-Drivers!$C$127)<0,0,MIN(((H$35-Drivers!$C$127)+1)/5,1))*Drivers!$C$128 -> 0.0032 | I75: =Drivers!$C$125*Drivers!$C$126*IF((I$35-Drivers!$C$127)<0,0,MIN(((I$35-Drivers!$C$127)+1)/5,1))*Drivers!$C$128 -> 0.0048 | J75: =Drivers!$C$125*Drivers!$C$126*IF((J$35-Drivers!$C$127)<0,0,MIN(((J$35-Drivers!$C$127)+1)/5,1))*Drivers!$C$128 -> 0.0064 | ... U75: =Drivers!$C$125*Drivers!$C$126*IF((U$35-Drivers!$C$127)<0,0,MIN(((U$35-Drivers!$C$127)+1)/5,1))*Drivers!$C$128 -> 0.008
A76: Rare disease & royalties contribution | B76: $B | C76: =C73*Drivers!$C$117+Drivers!$C$114*(Drivers!$C$118*(C$35=Drivers!$C$116)+Drivers!$C$119*(C$35=Drivers!$C$116+3))+C74*Drivers!$C$123-Drivers!$C$124*Drivers!$C$114*AND(C$35>=2027,C$35<=2030)+C75 -> -0.044 | D76: =D73*Drivers!$C$117+Drivers!$C$114*(Drivers!$C$118*(D$35=Drivers!$C$116)+Drivers!$C$119*(D$35=Drivers!$C$116+3))+D74*Drivers!$C$123-Drivers!$C$124*Drivers!$C$114*AND(D$35>=2027,D$35<=2030)+D75 -> 0.0231 | E76: =E73*Drivers!$C$117+Drivers!$C$114*(Drivers!$C$118*(E$35=Drivers!$C$116)+Drivers!$C$119*(E$35=Drivers!$C$116+3))+E74*Drivers!$C$123-Drivers!$C$124*Drivers!$C$114*AND(E$35>=2027,E$35<=2030)+E75 -> -0.0308 | F76: =F73*Drivers!$C$117+Drivers!$C$114*(Drivers!$C$118*(F$35=Drivers!$C$116)+Drivers!$C$119*(F$35=Drivers!$C$116+3))+F74*Drivers!$C$123-Drivers!$C$124*Drivers!$C$114*AND(F$35>=2027,F$35<=2030)+F75 -> -0.0242 | G76: =G73*Drivers!$C$117+Drivers!$C$114*(Drivers!$C$118*(G$35=Drivers!$C$116)+Drivers!$C$119*(G$35=Drivers!$C$116+3))+G74*Drivers!$C$123-Drivers!$C$124*Drivers!$C$114*AND(G$35>=2027,G$35<=2030)+G75 -> 0.091 | H76: =H73*Drivers!$C$117+Drivers!$C$114*(Drivers!$C$118*(H$35=Drivers!$C$116)+Drivers!$C$119*(H$35=Drivers!$C$116+3))+H74*Drivers!$C$123-Drivers!$C$124*Drivers!$C$114*AND(H$35>=2027,H$35<=2030)+H75 -> 0.0522 | I76: =I73*Drivers!$C$117+Drivers!$C$114*(Drivers!$C$118*(I$35=Drivers!$C$116)+Drivers!$C$119*(I$35=Drivers!$C$116+3))+I74*Drivers!$C$123-Drivers!$C$124*Drivers!$C$114*AND(I$35>=2027,I$35<=2030)+I75 -> 0.0618 | J76: =J73*Drivers!$C$117+Drivers!$C$114*(Drivers!$C$118*(J$35=Drivers!$C$116)+Drivers!$C$119*(J$35=Drivers!$C$116+3))+J74*Drivers!$C$123-Drivers!$C$124*Drivers!$C$114*AND(J$35>=2027,J$35<=2030)+J75 -> 0.0714 | ... U76: =U73*Drivers!$C$117+Drivers!$C$114*(Drivers!$C$118*(U$35=Drivers!$C$116)+Drivers!$C$119*(U$35=Drivers!$C$116+3))+U74*Drivers!$C$123-Drivers!$C$124*Drivers!$C$114*AND(U$35>=2027,U$35<=2030)+U75 -> 0.081
A77: CORPORATE, TAX & FREE CASH FLOW
A78: Corporate G&A | B78: $B | C78: =Drivers!$C$129*(1+Drivers!$C$130)^C$36 -> 0.42 | D78: =Drivers!$C$129*(1+Drivers!$C$130)^D$36 -> 0.4284 | E78: =Drivers!$C$129*(1+Drivers!$C$130)^E$36 -> 0.436968 | F78: =Drivers!$C$129*(1+Drivers!$C$130)^F$36 -> 0.44570736 | G78: =Drivers!$C$129*(1+Drivers!$C$130)^G$36 -> 0.45462151 | H78: =Drivers!$C$129*(1+Drivers!$C$130)^H$36 -> 0.46371394 | I78: =Drivers!$C$129*(1+Drivers!$C$130)^I$36 -> 0.47298822 | J78: =Drivers!$C$129*(1+Drivers!$C$130)^J$36 -> 0.48244798 | ... U78: =Drivers!$C$129*(1+Drivers!$C$130)^U$36 -> 0.59986342
A79: Unallocated R&D (before scenario multiplier) | B79: $B | C79: =Drivers!$D$131 -> 1.2 | D79: =Drivers!$E$131 -> 1.15 | E79: =Drivers!$F$131 -> 1.12 | F79: =Drivers!$G$131 -> 1.1 | G79: =Drivers!$H$131 -> 1.1 | H79: =Drivers!$I$131 -> 1.1 | I79: =H79*(1+Drivers!$C$132) -> 1.122 | J79: =I79*(1+Drivers!$C$132) -> 1.14444 | K79: =J79*(1+Drivers!$C$132) -> 1.1673288 | L79: =K79*(1+Drivers!$C$132) -> 1.1906754 | M79: =L79*(1+Drivers!$C$132) -> 1.2144889 | N79: =M79*(1+Drivers!$C$132) -> 1.2387787 | O79: =N79*(1+Drivers!$C$132) -> 1.2635542 | P79: =O79*(1+Drivers!$C$132) -> 1.2888253 | ... U79: =T79*(1+Drivers!$C$132) -> 1.4229673
A80: Unallocated R&D | B80: $B | C80: =C79*$C$17 -> 1.2 | D80: =D79*$C$17 -> 1.15 | E80: =E79*$C$17 -> 1.12 | F80: =F79*$C$17 -> 1.1 | G80: =G79*$C$17 -> 1.1 | H80: =H79*$C$17 -> 1.1 | I80: =I79*$C$17 -> 1.122 | J80: =J79*$C$17 -> 1.14444 | ... U80: =U79*$C$17 -> 1.4229673
A81: Attributable revenue (resp + 50% INT + other) | B81: $B | C81: =C44+Drivers!$C$85*C64+C70+C74+C73*Drivers!$C$117+C75 -> 2.54236 | D81: =D44+Drivers!$C$85*D64+D70+D74+D73*Drivers!$C$117+D75 -> 3.0522 | E81: =E44+Drivers!$C$85*E64+E70+E74+E73*Drivers!$C$117+E75 -> 3.671 | F81: =F44+Drivers!$C$85*F64+F70+F74+F73*Drivers!$C$117+F75 -> 4.2898 | G81: =G44+Drivers!$C$85*G64+G70+G74+G73*Drivers!$C$117+G75 -> 5.02564 | H81: =H44+Drivers!$C$85*H64+H70+H74+H73*Drivers!$C$117+H75 -> 5.41066 | I81: =I44+Drivers!$C$85*I64+I70+I74+I73*Drivers!$C$117+I75 -> 5.8498 | J81: =J44+Drivers!$C$85*J64+J70+J74+J73*Drivers!$C$117+J75 -> 6.17292 | ... U81: =U44+Drivers!$C$85*U64+U70+U74+U73*Drivers!$C$117+U75 -> 6.8341639
A82: Capex | B82: $B | C82: =Drivers!$D$134 -> 0.3 | D82: =Drivers!$E$134 -> 0.25 | E82: =Drivers!$F$134 -> 0.25 | F82: =Drivers!$G$134 -> 0.25 | G82: =Drivers!$H$134 -> 0.25 | H82: =Drivers!$I$134 -> 0.25 | I82: =Drivers!$C$135*I81 -> 0.233992 | J82: =Drivers!$C$135*J81 -> 0.2469168 | K82: =Drivers!$C$135*K81 -> 0.26209598 | L82: =Drivers!$C$135*L81 -> 0.27639614 | M82: =Drivers!$C$135*M81 -> 0.28913688 | N82: =Drivers!$C$135*N81 -> 0.2973388 | O82: =Drivers!$C$135*O81 -> 0.29350653 | P82: =Drivers!$C$135*P81 -> 0.29571596 | ... U82: =Drivers!$C$135*U81 -> 0.27336656
A83: D&A | B83: $B | C83: =Drivers!$C$136 -> 0.23 | D83: =Drivers!$C$136 -> 0.23 | E83: =Drivers!$C$136 -> 0.23 | F83: =Drivers!$C$136 -> 0.23 | G83: =Drivers!$C$136 -> 0.23 | H83: =Drivers!$C$136 -> 0.23 | I83: =0.8*I82 -> 0.1871936 | J83: =0.8*J82 -> 0.19753344 | K83: =0.8*K82 -> 0.20967679 | L83: =0.8*L82 -> 0.22111692 | M83: =0.8*M82 -> 0.23130951 | N83: =0.8*N82 -> 0.23787104 | O83: =0.8*O82 -> 0.23480522 | P83: =0.8*P82 -> 0.23657277 | ... U83: =0.8*U82 -> 0.21869325
A84: Increase in working capital | B84: $B | C84: =Drivers!$C$82*(C81-Drivers!$C$35) -> 0.050236 | D84: =Drivers!$C$82*(D81-C81) -> 0.050984 | E84: =Drivers!$C$82*(E81-D81) -> 0.06188 | F84: =Drivers!$C$82*(F81-E81) -> 0.06188 | G84: =Drivers!$C$82*(G81-F81) -> 0.073584 | H84: =Drivers!$C$82*(H81-G81) -> 0.038502 | I84: =Drivers!$C$82*(I81-H81) -> 0.043914 | J84: =Drivers!$C$82*(J81-I81) -> 0.032312 | K84: =Drivers!$C$82*(K81-J81) -> 0.03794796 | ... U84: =Drivers!$C$82*(U81-T81) -> -0.0098916082
A85: EBIT | B85: $B | C85: =C52+C68+C72+C76-C78-C80 -> -1.791605 | D85: =D52+D68+D72+D76-D78-D80 -> -1.3041033 | E85: =E52+E68+E72+E76-E78-E80 -> -0.89521433 | F85: =F52+F68+F72+F76-F78-F80 -> -0.40098069 | G85: =G52+G68+G72+G76-G78-G80 -> 0.26854069 | H85: =H52+H68+H72+H76-H78-H80 -> 0.62251406 | I85: =I52+I68+I72+I76-I78-I80 -> 0.90494678 | J85: =J52+J68+J72+J76-J78-J80 -> 1.2063902 | ... U85: =U52+U68+U72+U76-U78-U80 -> 1.1087947
A86: NOL pool - opening | B86: $B | C86: =Drivers!$C$32 -> 12.5 | D86: =C89 -> 14.291605 | E86: =D89 -> 15.595708 | F86: =E89 -> 16.490923 | G86: =F89 -> 16.891903 | H86: =G89 -> 16.677071 | I86: =H89 -> 16.17906 | J86: =I89 -> 15.455102 | K86: =J89 -> 14.48999 | ... U86: =T89 -> 2.055291
A87: NOL used | B87: $B | C87: =IF(C85>0,MIN(C86,Drivers!$C$33*C85),0) -> 0 | D87: =IF(D85>0,MIN(D86,Drivers!$C$33*D85),0) -> 0 | E87: =IF(E85>0,MIN(E86,Drivers!$C$33*E85),0) -> 0 | F87: =IF(F85>0,MIN(F86,Drivers!$C$33*F85),0) -> 0 | G87: =IF(G85>0,MIN(G86,Drivers!$C$33*G85),0) -> 0.21483255 | H87: =IF(H85>0,MIN(H86,Drivers!$C$33*H85),0) -> 0.49801125 | I87: =IF(I85>0,MIN(I86,Drivers!$C$33*I85),0) -> 0.72395743 | J87: =IF(J85>0,MIN(J86,Drivers!$C$33*J85),0) -> 0.96511218 | ... U87: =IF(U85>0,MIN(U86,Drivers!$C$33*U85),0) -> 0.88703579
A88: Cash taxes | B88: $B | C88: =IF(C85>0,Drivers!$C$31*(C85-C87),0) -> 0 | D88: =IF(D85>0,Drivers!$C$31*(D85-D87),0) -> 0 | E88: =IF(E85>0,Drivers!$C$31*(E85-E87),0) -> 0 | F88: =IF(F85>0,Drivers!$C$31*(F85-F87),0) -> 0 | G88: =IF(G85>0,Drivers!$C$31*(G85-G87),0) -> 0.010204546 | H88: =IF(H85>0,Drivers!$C$31*(H85-H87),0) -> 0.023655534 | I88: =IF(I85>0,Drivers!$C$31*(I85-I87),0) -> 0.034387978 | J88: =IF(J85>0,Drivers!$C$31*(J85-J87),0) -> 0.045842828 | ... U88: =IF(U85>0,Drivers!$C$31*(U85-U87),0) -> 0.0421342
A89: NOL pool - closing | B89: $B | C89: =C86-C87+IF(C85<0,-C85,0) -> 14.291605 | D89: =D86-D87+IF(D85<0,-D85,0) -> 15.595708 | E89: =E86-E87+IF(E85<0,-E85,0) -> 16.490923 | F89: =F86-F87+IF(F85<0,-F85,0) -> 16.891903 | G89: =G86-G87+IF(G85<0,-G85,0) -> 16.677071 | H89: =H86-H87+IF(H85<0,-H85,0) -> 16.17906 | I89: =I86-I87+IF(I85<0,-I85,0) -> 15.455102 | J89: =J86-J87+IF(J85<0,-J85,0) -> 14.48999 | ... U89: =U86-U87+IF(U85<0,-U85,0) -> 1.1682552
A90: Free cash flow to firm | B90: $B | C90: =C85-C88-(C82-C83)-C84 -> -1.911841 | D90: =D85-D88-(D82-D83)-D84 -> -1.3750873 | E90: =E85-E88-(E82-E83)-E84 -> -0.97709433 | F90: =F85-F88-(F82-F83)-F84 -> -0.48286069 | G90: =G85-G88-(G82-G83)-G84 -> 0.16475215 | H90: =H85-H88-(H82-H83)-H84 -> 0.54035653 | I90: =I85-I88-(I82-I83)-I84 -> 0.77984641 | J90: =J85-J88-(J82-J83)-J84 -> 1.078852 | ... U90: =U85-U88-(U82-U83)-U84 -> 1.0218788
A91: Discount period (mid-year, from 9/30/26) | B91: yrs | C91: =0.25+C$36+0.5 -> 0.75 | D91: =0.25+D$36+0.5 -> 1.75 | E91: =0.25+E$36+0.5 -> 2.75 | F91: =0.25+F$36+0.5 -> 3.75 | G91: =0.25+G$36+0.5 -> 4.75 | H91: =0.25+H$36+0.5 -> 5.75 | I91: =0.25+I$36+0.5 -> 6.75 | J91: =0.25+J$36+0.5 -> 7.75 | ... U91: =0.25+U$36+0.5 -> 18.75
A92: Discount factor | B92: x | C92: =(1+$C$19)^(-C91) -> 0.92829219 | D92: =(1+$C$19)^(-D91) -> 0.84061595 | E92: =(1+$C$19)^(-E91) -> 0.76122063 | F92: =(1+$C$19)^(-F91) -> 0.68932413 | G92: =(1+$C$19)^(-G91) -> 0.62421817 | H92: =(1+$C$19)^(-H91) -> 0.56526141 | I92: =(1+$C$19)^(-I91) -> 0.51187305 | J92: =(1+$C$19)^(-J91) -> 0.46352716 | ... U92: =(1+$C$19)^(-U91) -> 0.15563863
A93: PV of FCFF | B93: $B | C93: =C90*C92 -> -1.7747471 | D93: =D90*D92 -> -1.1559203 | E93: =E90*E92 -> -0.74378437 | F93: =F90*F92 -> -0.33284753 | G93: =G90*G92 -> 0.10284128 | H93: =H90*H92 -> 0.30544269 | I93: =I90*I92 -> 0.39918236 | J93: =J90*J92 -> 0.50007722 | ... U93: =U90*U92 -> 0.15904382
A94: R&D creating future pipeline (credit base) | B94: $B | C94: =IF(C$35<=2032,Drivers!$C$133*C80,C80) -> 0.42 | D94: =IF(D$35<=2032,Drivers!$C$133*D80,D80) -> 0.4025 | E94: =IF(E$35<=2032,Drivers!$C$133*E80,E80) -> 0.392 | F94: =IF(F$35<=2032,Drivers!$C$133*F80,F80) -> 0.385 | G94: =IF(G$35<=2032,Drivers!$C$133*G80,G80) -> 0.385 | H94: =IF(H$35<=2032,Drivers!$C$133*H80,H80) -> 0.385 | I94: =IF(I$35<=2032,Drivers!$C$133*I80,I80) -> 1.122 | J94: =IF(J$35<=2032,Drivers!$C$133*J80,J80) -> 1.14444 | ... U94: =IF(U$35<=2032,Drivers!$C$133*U80,U80) -> 1.4229673
A96: VALUATION
A97: PV of Q4-2026 stub FCF | C97: =Drivers!$C$34*(1+$C$19)^(-0.125) -> -0.45433056
A98: PV of FCFF 2027-2045 | C98: =SUM(C93:U93) -> 1.4982074
A99: Terminal value at end-2045 | C99: =U90*(1+$C$20)/($C$19-$C$20) -> 9.797496
A100: PV of terminal value | C100: =$C$99*(1+$C$19)^(-19.25) -> 1.451072
A101: PV of pipeline-creating R&D (incl. terminal) | C101: =SUMPRODUCT(C94:U94,C92:U92)+U94*(1+$C$20)/($C$19-$C$20)*(1+$C$19)^(-19.25) -> 8.6143036
A102: Unidentified future pipeline (credit) | C102: =$C$18*$C$101*(1-Drivers!$C$31) -> 5.2331894
A103: Enterprise value | C103: =$C$97+$C$98+$C$100+$C$102 -> 7.7281382
...

Sheet M_Bull
A1: M_Bull - scenario model (Strong ESMO HR (~0.55) with OS trend; US net ~$420k (William Blair models $475k WAC); melanoma peak $5B; other INT PoS x1.33 incl. future tumours; respiratory ~$5-6B (mgmt path).)
A2: Scenario index (1=Failure..5=Blue-sky) | C2: 4
A4: Scenario levers (green = pulled from Drivers)
A5: COVID revenue multiplier | C5: =INDEX(Drivers!$D$39:$H$39,$C$2) -> 1.1
A6: Flu (mFLUSIVA) peak multiplier | C6: =INDEX(Drivers!$D$40:$H$40,$C$2) -> 1.6
A7: Flu+COVID combo peak multiplier | C7: =INDEX(Drivers!$D$41:$H$41,$C$2) -> 1.6
A8: Norovirus PoS | C8: =INDEX(Drivers!$D$42:$H$42,$C$2) -> 0.45
A9: Respiratory gross-margin shift | C9: =INDEX(Drivers!$D$43:$H$43,$C$2) -> 0.02
A10: INT melanoma PoS | C10: =INDEX(Drivers!$D$44:$H$44,$C$2) -> 0.93
A11: INT melanoma peak global sales ($B, before price factor) | C11: =INDEX(Drivers!$D$45:$H$45,$C$2) -> 5
A12: INT melanoma launch year | C12: =INDEX(Drivers!$D$46:$H$46,$C$2) -> 2027
A13: INT other-indication PoS multiplier (>=10 => all 100%) | C13: =INDEX(Drivers!$D$47:$H$47,$C$2) -> 1.33
A14: INT other-indication peak multiplier | C14: =INDEX(Drivers!$D$48:$H$48,$C$2) -> 1.2
A15: INT price factor (1.0 = US net ~$300k) | C15: =INDEX(Drivers!$D$49:$H$49,$C$2) -> 1.4
A16: INT mature profit-pool margin | C16: =INDEX(Drivers!$D$50:$H$50,$C$2) -> 0.55
A17: Unallocated R&D multiplier | C17: =INDEX(Drivers!$D$51:$H$51,$C$2) -> 1.05
A18: Future-pipeline credit factor | C18: =INDEX(Drivers!$D$52:$H$52,$C$2) -> 1
A19: WACC | C19: =INDEX(Drivers!$D$53:$H$53,$C$2) -> 0.1043
A20: Terminal growth | C20: =INDEX(Drivers!$D$54:$H$54,$C$2) -> 0.01
A21: Other patent litigation (expected cost) | C21: =INDEX(Drivers!$D$55:$H$55,$C$2) -> 0.3
A22: INT indications: scenario-adjusted launch / peak / PoS
A23: Indication | C23: Launch | D23: Peak | E23: PoS
A24: =Drivers!$B$95 -> Adjuvant melanoma IIB-IV (INTerpath-001) | C24: =$C$12 -> 2027 | D24: =$C$11 -> 5 | E24: =$C$10 -> 0.93
A25: =Drivers!$B$96 -> Adjuvant NSCLC II-IIIB (INTerpath-002) | C25: =Drivers!$D$96 -> 2031 | D25: =Drivers!$E$96*$C$14 -> 4.8 | E25: =MIN(Drivers!$F$96*$C$13,IF($C$13>=10,1,0.95)) -> 0.5985
A26: =Drivers!$B$97 -> Post-neoadjuvant non-pCR NSCLC (INTerpath-009) | C26: =Drivers!$D$97 -> 2034 | D26: =Drivers!$E$97*$C$14 -> 1.8 | E26: =MIN(Drivers!$F$97*$C$13,IF($C$13>=10,1,0.95)) -> 0.532
A27: =Drivers!$B$98 -> Resected stage I NSCLC (INTerpath-014) | C27: =Drivers!$D$98 -> 2035 | D27: =Drivers!$E$98*$C$14 -> 3 | E27: =MIN(Drivers!$F$98*$C$13,IF($C$13>=10,1,0.95)) -> 0.4655
A28: =Drivers!$B$99 -> Adjuvant RCC (INTerpath-004) | C28: =Drivers!$D$99 -> 2031 | D28: =Drivers!$E$99*$C$14 -> 1.44 | E28: =MIN(Drivers!$F$99*$C$13,IF($C$13>=10,1,0.95)) -> 0.3325
A29: =Drivers!$B$100 -> MIBC adjuvant (INTerpath-005) | C29: =Drivers!$D$100 -> 2033 | D29: =Drivers!$E$100*$C$14 -> 1.2 | E29: =MIN(Drivers!$F$100*$C$13,IF($C$13>=10,1,0.95)) -> 0.266
A30: =Drivers!$B$101 -> NMIBC + BCG (INTerpath-011) | C30: =Drivers!$D$101 -> 2034 | D30: =Drivers!$E$101*$C$14 -> 1.2 | E30: =MIN(Drivers!$F$101*$C$13,IF($C$13>=10,1,0.95)) -> 0.1995
A31: =Drivers!$B$102 -> 1L advanced melanoma (INTerpath-012) | C31: =Drivers!$D$102 -> 2031 | D31: =Drivers!$E$102*$C$14 -> 0.96 | E31: =MIN(Drivers!$F$102*$C$13,IF($C$13>=10,1,0.95)) -> 0.266
A32: =Drivers!$B$103 -> 1L metastatic squamous NSCLC (INTerpath-013) | C32: =Drivers!$D$103 -> 2032 | D32: =Drivers!$E$103*$C$14 -> 1.44 | E32: =MIN(Drivers!$F$103*$C$13,IF($C$13>=10,1,0.95)) -> 0.1995
A33: =Drivers!$B$104 -> Other solid tumours - future INT indications (pre-Ph2) | C33: =Drivers!$D$104 -> 2035 | D33: =Drivers!$E$104*$C$14 -> 7.2 | E33: =MIN(Drivers!$F$104*$C$13,IF($C$13>=10,1,0.95)) -> 0.133
A35: Year | B35: unit | C35: 2027 | D35: 2028 | E35: 2029 | F35: 2030 | G35: 2031 | H35: 2032 | I35: 2033 | J35: 2034 | K35: 2035 | L35: 2036 | M35: 2037 | N35: 2038 | O35: 2039 | P35: 2040 | Q35: 2041 | R35: 2042 | S35: 2043 | T35: 2044 | U35: 2045
A36: Year index i | C36: 0 | D36: 1 | E36: 2 | F36: 3 | G36: 4 | H36: 5 | I36: 6 | J36: 7 | K36: 8 | L36: 9 | M36: 10 | N36: 11 | O36: 12 | P36: 13 | Q36: 14 | R36: 15 | S36: 16 | T36: 17 | U36: 18
A37: RESPIRATORY FRANCHISE
A38: COVID (Spikevax, mNEXSPIKE, partnerships) | B38: $B | C38: =Drivers!$D$60*$C$5 -> 2.035 | D38: =Drivers!$E$60*$C$5 -> 1.87 | E38: =Drivers!$F$60*$C$5 -> 1.705 | F38: =Drivers!$G$60*$C$5 -> 1.595 | G38: =Drivers!$H$60*$C$5 -> 1.518 | H38: =Drivers!$I$60*$C$5 -> 1.43 | I38: =H38*(1+Drivers!$C$61) -> 1.4014 | J38: =I38*(1+Drivers!$C$61) -> 1.373372 | K38: =J38*(1+Drivers!$C$61) -> 1.3459046 | L38: =K38*(1+Drivers!$C$61) -> 1.3189865 | M38: =L38*(1+Drivers!$C$61) -> 1.2926067 | N38: =M38*(1+Drivers!$C$61) -> 1.2667546 | O38: =N38*(1+Drivers!$C$61) -> 1.2414195 | P38: =O38*(1+Drivers!$C$61) -> 1.2165911 | ... U38: =T38*(1+Drivers!$C$61) -> 1.099702
A39: Flu (mFLUSIVA) | B39: $B | C39: =Drivers!$C$62*IF((C$35-Drivers!$C$63)<0,0,MIN(((C$35-Drivers!$C$63)+1)/Drivers!$C$64,1))*$C$6 -> 0.256 | D39: =Drivers!$C$62*IF((D$35-Drivers!$C$63)<0,0,MIN(((D$35-Drivers!$C$63)+1)/Drivers!$C$64,1))*$C$6 -> 0.512 | E39: =Drivers!$C$62*IF((E$35-Drivers!$C$63)<0,0,MIN(((E$35-Drivers!$C$63)+1)/Drivers!$C$64,1))*$C$6 -> 0.768 | F39: =Drivers!$C$62*IF((F$35-Drivers!$C$63)<0,0,MIN(((F$35-Drivers!$C$63)+1)/Drivers!$C$64,1))*$C$6 -> 1.024 | G39: =Drivers!$C$62*IF((G$35-Drivers!$C$63)<0,0,MIN(((G$35-Drivers!$C$63)+1)/Drivers!$C$64,1))*$C$6 -> 1.28 | H39: =Drivers!$C$62*IF((H$35-Drivers!$C$63)<0,0,MIN(((H$35-Drivers!$C$63)+1)/Drivers!$C$64,1))*$C$6 -> 1.28 | I39: =Drivers!$C$62*IF((I$35-Drivers!$C$63)<0,0,MIN(((I$35-Drivers!$C$63)+1)/Drivers!$C$64,1))*$C$6 -> 1.28 | J39: =Drivers!$C$62*IF((J$35-Drivers!$C$63)<0,0,MIN(((J$35-Drivers!$C$63)+1)/Drivers!$C$64,1))*$C$6 -> 1.28 | ... U39: =Drivers!$C$62*IF((U$35-Drivers!$C$63)<0,0,MIN(((U$35-Drivers!$C$63)+1)/Drivers!$C$64,1))*$C$6 -> 1.28
A40: Flu+COVID combo (mCOMBRIAX) | B40: $B | C40: =Drivers!$C$65*IF((C$35-Drivers!$C$66)<0,0,MIN(((C$35-Drivers!$C$66)+1)/Drivers!$C$67,1))*$C$7*((1-Drivers!$C$69)+Drivers!$C$69*Drivers!$C$68) -> 0.37408 | D40: =Drivers!$C$65*IF((D$35-Drivers!$C$66)<0,0,MIN(((D$35-Drivers!$C$66)+1)/Drivers!$C$67,1))*$C$7*((1-Drivers!$C$69)+Drivers!$C$69*Drivers!$C$68) -> 0.74816 | E40: =Drivers!$C$65*IF((E$35-Drivers!$C$66)<0,0,MIN(((E$35-Drivers!$C$66)+1)/Drivers!$C$67,1))*$C$7*((1-Drivers!$C$69)+Drivers!$C$69*Drivers!$C$68) -> 1.12224 | F40: =Drivers!$C$65*IF((F$35-Drivers!$C$66)<0,0,MIN(((F$35-Drivers!$C$66)+1)/Drivers!$C$67,1))*$C$7*((1-Drivers!$C$69)+Drivers!$C$69*Drivers!$C$68) -> 1.49632 | G40: =Drivers!$C$65*IF((G$35-Drivers!$C$66)<0,0,MIN(((G$35-Drivers!$C$66)+1)/Drivers!$C$67,1))*$C$7*((1-Drivers!$C$69)+Drivers!$C$69*Drivers!$C$68) -> 1.8704 | H40: =Drivers!$C$65*IF((H$35-Drivers!$C$66)<0,0,MIN(((H$35-Drivers!$C$66)+1)/Drivers!$C$67,1))*$C$7*((1-Drivers!$C$69)+Drivers!$C$69*Drivers!$C$68) -> 1.8704 | I40: =Drivers!$C$65*IF((I$35-Drivers!$C$66)<0,0,MIN(((I$35-Drivers!$C$66)+1)/Drivers!$C$67,1))*$C$7*((1-Drivers!$C$69)+Drivers!$C$69*Drivers!$C$68) -> 1.8704 | J40: =Drivers!$C$65*IF((J$35-Drivers!$C$66)<0,0,MIN(((J$35-Drivers!$C$66)+1)/Drivers!$C$67,1))*$C$7*((1-Drivers!$C$69)+Drivers!$C$69*Drivers!$C$68) -> 1.8704 | ... U40: =Drivers!$C$65*IF((U$35-Drivers!$C$66)<0,0,MIN(((U$35-Drivers!$C$66)+1)/Drivers!$C$67,1))*$C$7*((1-Drivers!$C$69)+Drivers!$C$69*Drivers!$C$68) -> 1.8704
A41: RSV (mRESVIA) | B41: $B | C41: =Drivers!$C$70*MIN((C$35-2026)/3,1) -> 0.05 | D41: =Drivers!$C$70*MIN((D$35-2026)/3,1) -> 0.1 | E41: =Drivers!$C$70*MIN((E$35-2026)/3,1) -> 0.15 | F41: =Drivers!$C$70*MIN((F$35-2026)/3,1) -> 0.15 | G41: =Drivers!$C$70*MIN((G$35-2026)/3,1) -> 0.15 | H41: =Drivers!$C$70*MIN((H$35-2026)/3,1) -> 0.15 | I41: =Drivers!$C$70*MIN((I$35-2026)/3,1) -> 0.15 | J41: =Drivers!$C$70*MIN((J$35-2026)/3,1) -> 0.15 | ... U41: =Drivers!$C$70*MIN((U$35-2026)/3,1) -> 0.15
A42: Norovirus (risk-adjusted) | B42: $B | C42: =$C$8*Drivers!$C$71*IF((C$35-Drivers!$C$72)<0,0,MIN(((C$35-Drivers!$C$72)+1)/Drivers!$C$73,1)) -> 0 | D42: =$C$8*Drivers!$C$71*IF((D$35-Drivers!$C$72)<0,0,MIN(((D$35-Drivers!$C$72)+1)/Drivers!$C$73,1)) -> 0 | E42: =$C$8*Drivers!$C$71*IF((E$35-Drivers!$C$72)<0,0,MIN(((E$35-Drivers!$C$72)+1)/Drivers!$C$73,1)) -> 0.108 | F42: =$C$8*Drivers!$C$71*IF((F$35-Drivers!$C$72)<0,0,MIN(((F$35-Drivers!$C$72)+1)/Drivers!$C$73,1)) -> 0.216 | G42: =$C$8*Drivers!$C$71*IF((G$35-Drivers!$C$72)<0,0,MIN(((G$35-Drivers!$C$72)+1)/Drivers!$C$73,1)) -> 0.324 | H42: =$C$8*Drivers!$C$71*IF((H$35-Drivers!$C$72)<0,0,MIN(((H$35-Drivers!$C$72)+1)/Drivers!$C$73,1)) -> 0.432 | I42: =$C$8*Drivers!$C$71*IF((I$35-Drivers!$C$72)<0,0,MIN(((I$35-Drivers!$C$72)+1)/Drivers!$C$73,1)) -> 0.54 | J42: =$C$8*Drivers!$C$71*IF((J$35-Drivers!$C$72)<0,0,MIN(((J$35-Drivers!$C$72)+1)/Drivers!$C$73,1)) -> 0.54 | ... U42: =$C$8*Drivers!$C$71*IF((U$35-Drivers!$C$72)<0,0,MIN(((U$35-Drivers!$C$72)+1)/Drivers!$C$73,1)) -> 0.54
A43: Other revenue | B43: $B | C43: =Drivers!$C$74 -> 0.15 | D43: =Drivers!$C$74 -> 0.15 | E43: =Drivers!$C$74 -> 0.15 | F43: =Drivers!$C$74 -> 0.15 | G43: =Drivers!$C$74 -> 0.15 | H43: =Drivers!$C$74 -> 0.15 | I43: =Drivers!$C$74 -> 0.15 | J43: =Drivers!$C$74 -> 0.15 | ... U43: =Drivers!$C$74 -> 0.15
A44: Respiratory revenue | B44: $B | C44: =SUM(C38:C43) -> 2.86508 | D44: =SUM(D38:D43) -> 3.38016 | E44: =SUM(E38:E43) -> 4.00324 | F44: =SUM(F38:F43) -> 4.63132 | G44: =SUM(G38:G43) -> 5.2924 | H44: =SUM(H38:H43) -> 5.3124 | I44: =SUM(I38:I43) -> 5.3918 | J44: =SUM(J38:J43) -> 5.363772 | ... U44: =SUM(U38:U43) -> 5.090102
A45: Gross margin | B45: % | C45: =Drivers!$D$75+$C$9 -> 0.66 | D45: =Drivers!$E$75+$C$9 -> 0.7 | E45: =Drivers!$F$75+$C$9 -> 0.73 | F45: =Drivers!$G$75+$C$9 -> 0.75 | G45: =Drivers!$H$75+$C$9 -> 0.76 | H45: =Drivers!$I$75+$C$9 -> 0.77 | I45: =Drivers!$I$75+$C$9 -> 0.77 | J45: =Drivers!$I$75+$C$9 -> 0.77 | K45: =Drivers!$I$75+$C$9 -> 0.77 | L45: =Drivers!$I$75+$C$9 -> 0.77 | M45: =Drivers!$I$75+$C$9 -> 0.77 | N45: =Drivers!$I$75+$C$9 -> 0.77 | O45: =Drivers!$I$75+$C$9 -> 0.77 | ... U45: =Drivers!$I$75+$C$9 -> 0.77
A46: Flu + combo revenue | B46: $B | C46: =C39+C40 -> 0.63008 | D46: =D39+D40 -> 1.26016 | E46: =E39+E40 -> 1.89024 | F46: =F39+F40 -> 2.52032 | G46: =G39+G40 -> 3.1504 | H46: =H39+H40 -> 3.1504 | I46: =I39+I40 -> 3.1504 | J46: =J39+J40 -> 3.1504 | ... U46: =U39+U40 -> 3.1504
A47: Blackstone sales milestones paid | B47: $B | C47: =MIN(Drivers!$C$77-0,Drivers!$C$78*C46) -> 0.0504064 | D47: =MIN(Drivers!$C$77-C48,Drivers!$C$78*D46) -> 0.1008128 | E47: =MIN(Drivers!$C$77-D48,Drivers!$C$78*E46) -> 0.1512192 | F47: =MIN(Drivers!$C$77-E48,Drivers!$C$78*F46) -> 0.2016256 | G47: =MIN(Drivers!$C$77-F48,Drivers!$C$78*G46) -> 0.245936 | H47: =MIN(Drivers!$C$77-G48,Drivers!$C$78*H46) -> 0 | I47: =MIN(Drivers!$C$77-H48,Drivers!$C$78*I46) -> 0 | J47: =MIN(Drivers!$C$77-I48,Drivers!$C$78*J46) -> 0 | K47: =MIN(Drivers!$C$77-J48,Drivers!$C$78*K46) -> 0 | ... U47: =MIN(Drivers!$C$77-T48,Drivers!$C$78*U46) -> 0
A48: Blackstone milestones cumulative | B48: $B | C48: =C47 -> 0.0504064 | D48: =C48+D47 -> 0.1512192 | E48: =D48+E47 -> 0.3024384 | F48: =E48+F47 -> 0.504064 | G48: =F48+G47 -> 0.75 | H48: =G48+H47 -> 0.75 | I48: =H48+I47 -> 0.75 | J48: =I48+J47 -> 0.75 | K48: =J48+K47 -> 0.75 | ... U48: =T48+U47 -> 0.75
A49: Blackstone royalty + milestones | B49: $B | C49: =Drivers!$C$76*C46+C47 -> 0.0661584 | D49: =Drivers!$C$76*D46+D47 -> 0.1323168 | E49: =Drivers!$C$76*E46+E47 -> 0.1984752 | F49: =Drivers!$C$76*F46+F47 -> 0.2646336 | G49: =Drivers!$C$76*G46+G47 -> 0.324696 | H49: =Drivers!$C$76*H46+H47 -> 0.07876 | I49: =Drivers!$C$76*I46+I47 -> 0.07876 | J49: =Drivers!$C$76*J46+J47 -> 0.07876 | ... U49: =Drivers!$C$76*U46+U47 -> 0.07876
A50: Respiratory S&M | B50: $B | C50: =MAX(Drivers!$C$80,Drivers!$C$79*C44) -> 0.4011112 | D50: =MAX(Drivers!$C$80,Drivers!$C$79*D44) -> 0.4732224 | E50: =MAX(Drivers!$C$80,Drivers!$C$79*E44) -> 0.5604536 | F50: =MAX(Drivers!$C$80,Drivers!$C$79*F44) -> 0.6483848 | G50: =MAX(Drivers!$C$80,Drivers!$C$79*G44) -> 0.740936 | H50: =MAX(Drivers!$C$80,Drivers!$C$79*H44) -> 0.743736 | I50: =MAX(Drivers!$C$80,Drivers!$C$79*I44) -> 0.754852 | J50: =MAX(Drivers!$C$80,Drivers!$C$79*J44) -> 0.75092808 | ... U50: =MAX(Drivers!$C$80,Drivers!$C$79*U44) -> 0.71261428
A51: Respiratory R&D | B51: $B | C51: =Drivers!$D$81 -> 0.75 | D51: =Drivers!$E$81 -> 0.62 | E51: =Drivers!$F$81 -> 0.55 | F51: =Drivers!$G$81 -> 0.5 | G51: =Drivers!$H$81 -> 0.48 | H51: =Drivers!$I$81 -> 0.46 | I51: =H51*1.02 -> 0.4692 | J51: =I51*1.02 -> 0.478584 | K51: =J51*1.02 -> 0.48815568 | L51: =K51*1.02 -> 0.49791879 | M51: =L51*1.02 -> 0.50787717 | N51: =M51*1.02 -> 0.51803471 | O51: =N51*1.02 -> 0.52839541 | P51: =O51*1.02 -> 0.53896332 | ... U51: =T51*1.02 -> 0.59505905
A52: Respiratory contribution | B52: $B | C52: =C44*C45-C49-C50-C51 -> 0.6736832 | D52: =D44*D45-D49-D50-D51 -> 1.1405728 | E52: =E44*E45-E49-E50-E51 -> 1.6134364 | F52: =F44*F45-F49-F50-F51 -> 2.0604716 | G52: =G44*G45-G49-G50-G51 -> 2.476592 | H52: =H44*H45-H49-H50-H51 -> 2.808052 | I52: =I44*I45-I49-I50-I51 -> 2.848874 | J52: =J44*J45-J49-J50-J51 -> 2.8218324 | ... U52: =U44*U45-U49-U50-U51 -> 2.5329452
A53: INTISMERAN (risk-adjusted global sales; Moderna books 50% of profit pool)
A54: Adjuvant melanoma IIB-IV (INTerpath-001) | B54: $B | C54: =$D$24*$C$15*IF((C$35-$C$24)<0,0,IF((C$35-$C$24)>=7,1,INDEX(Drivers!$D$86:$J$86,(C$35-$C$24)+1)))*IF((C$35-$C$24)<Drivers!$C$87,1,Drivers!$C$88*Drivers!$C$89^((C$35-$C$24)-Drivers!$C$87))*$E$24 -> 0.5208 | D54: =$D$24*$C$15*IF((D$35-$C$24)<0,0,IF((D$35-$C$24)>=7,1,INDEX(Drivers!$D$86:$J$86,(D$35-$C$24)+1)))*IF((D$35-$C$24)<Drivers!$C$87,1,Drivers!$C$88*Drivers!$C$89^((D$35-$C$24)-Drivers!$C$87))*$E$24 -> 1.6275 | E54: =$D$24*$C$15*IF((E$35-$C$24)<0,0,IF((E$35-$C$24)>=7,1,INDEX(Drivers!$D$86:$J$86,(E$35-$C$24)+1)))*IF((E$35-$C$24)<Drivers!$C$87,1,Drivers!$C$88*Drivers!$C$89^((E$35-$C$24)-Drivers!$C$87))*$E$24 -> 2.9295 | F54: =$D$24*$C$15*IF((F$35-$C$24)<0,0,IF((F$35-$C$24)>=7,1,INDEX(Drivers!$D$86:$J$86,(F$35-$C$24)+1)))*IF((F$35-$C$24)<Drivers!$C$87,1,Drivers!$C$88*Drivers!$C$89^((F$35-$C$24)-Drivers!$C$87))*$E$24 -> 4.2315 | G54: =$D$24*$C$15*IF((G$35-$C$24)<0,0,IF((G$35-$C$24)>=7,1,INDEX(Drivers!$D$86:$J$86,(G$35-$C$24)+1)))*IF((G$35-$C$24)<Drivers!$C$87,1,Drivers!$C$88*Drivers!$C$89^((G$35-$C$24)-Drivers!$C$87))*$E$24 -> 5.3382 | H54: =$D$24*$C$15*IF((H$35-$C$24)<0,0,IF((H$35-$C$24)>=7,1,INDEX(Drivers!$D$86:$J$86,(H$35-$C$24)+1)))*IF((H$35-$C$24)<Drivers!$C$87,1,Drivers!$C$88*Drivers!$C$89^((H$35-$C$24)-Drivers!$C$87))*$E$24 -> 6.0543 | I54: =$D$24*$C$15*IF((I$35-$C$24)<0,0,IF((I$35-$C$24)>=7,1,INDEX(Drivers!$D$86:$J$86,(I$35-$C$24)+1)))*IF((I$35-$C$24)<Drivers!$C$87,1,Drivers!$C$88*Drivers!$C$89^((I$35-$C$24)-Drivers!$C$87))*$E$24 -> 6.51 | J54: =$D$24*$C$15*IF((J$35-$C$24)<0,0,IF((J$35-$C$24)>=7,1,INDEX(Drivers!$D$86:$J$86,(J$35-$C$24)+1)))*IF((J$35-$C$24)<Drivers!$C$87,1,Drivers!$C$88*Drivers!$C$89^((J$35-$C$24)-Drivers!$C$87))*$E$24 -> 6.51 | ... U54: =$D$24*$C$15*IF((U$35-$C$24)<0,0,IF((U$35-$C$24)>=7,1,INDEX(Drivers!$D$86:$J$86,(U$35-$C$24)+1)))*IF((U$35-$C$24)<Drivers!$C$87,1,Drivers!$C$88*Drivers!$C$89^((U$35-$C$24)-Drivers!$C$87))*$E$24 -> 4.3381182
